Workbook
Name Print_Titles: Ввод!$4:$5
Name БазоваяПапка: Справочники!$N$1

Sheet Ввод
A2: Дата отчёта: | C2: 46304
E4: ПОРТФЕЛЬ | G4: ПРОСРОЧКА | I4: ЗВОНКИ | K4: GAPLASHGAN / ОБЕЩАЛИ | O4: НЕ ДОЗВОНИЛИСЬ / ОБЪЕЗД | S4: ОПЛАЧЕНО ЗА ДЕНЬ | Y4: ЭФФЕКТИВНОСТЬ И НАГРУЗКА
A5: № | B5: Область | C5: Ответственный | D5: Сотруд- ников | E5: Портфель, сум | F5: Портфель, шт | G5: Просрочка, сум | H5: Просрочка, шт | I5: Звонков всего, сум | J5: Звонков всего, шт | K5: Gaplashgan, сум | L5: Gaplashgan, шт | M5: Обещали, сум | N5: Обещали, шт | O5: Ko'tarmadi, сум | P5: Ko'tarmadi, шт | Q5: Объезд, сум | R5: Объезд, шт | S5: Оплатил дозвон, сум | T5: Оплатил дозвон, шт | U5: Объезд оплатил, сум | V5: Объезд оплатил, шт | W5: Оплачено общее, сум | X5: Оплачено общее, шт | Y5: % дозвона (шт) | Z5: % обещаний (от дозвона) | AA5: Просрочка на 1 сотр. | AB5: Дозвон на 1 сотр. | AE5: служ. (для сортировки)
A6: 1 | B6: АНДИЖОН ВИЛОЯТИ | C6: =IFERROR(INDEX(Справочники!$D$4:$D$21,MATCH($B6,Справочники!$B$4:$B$21,0)),"") | D6: =SUMIF(Справочники!$H$4:$H$21,$B6,Справочники!$E$4:$E$21) | E6: 2.1670184e+10 | F6: 445 | G6: 7.1770335e+08 | H6: 173 | I6: 5.2222476e+08 | J6: 132 | K6: 400186527 | L6: 110 | M6: 11537226 | N6: 3 | O6: 48777884 | P6: 5 | Q6: 73260353 | R6: 17 | S6: 22868116 | T6: 10 | U6: 0 | V6: 0 | W6: 22868116 | X6: 10 | Y6: =IFERROR($L6/$H6,"") | Z6: =IFERROR($N6/$L6,"") | AA6: =IFERROR($H6/$D6,"") | AB6: =IFERROR($L6/$D6,"") | AE6: =IFERROR($Y6,0)+ROW()/1000000
A7: 2 | B7: БУХОРО ВИЛОЯТИ | C7: =IFERROR(INDEX(Справочники!$D$4:$D$21,MATCH($B7,Справочники!$B$4:$B$21,0)),"") | D7: =SUMIF(Справочники!$H$4:$H$21,$B7,Справочники!$E$4:$E$21) | E7: 5.1231734e+09 | F7: 167 | G7: 2.5393763e+08 | H7: 55 | I7: 2.5393763e+08 | J7: 55 | K7: 1.6450494e+08 | L7: 47 | M7: 1.4950169e+08 | N7: 41 | O7: 87611719 | P7: 7 | Q7: 1820966 | R7: 1 | S7: 15003253 | T7: 6 | U7: 0 | V7: 0 | W7: 15003253 | X7: 6 | Y7: =IFERROR($L7/$H7,"") | Z7: =IFERROR($N7/$L7,"") | AA7: =IFERROR($H7/$D7,"") | AB7: =IFERROR($L7/$D7,"") | AE7: =IFERROR($Y7,0)+ROW()/1000000
A8: 3 | B8: ЖИЗЗАХ ВИЛОЯТИ | C8: =IFERROR(INDEX(Справочники!$D$4:$D$21,MATCH($B8,Справочники!$B$4:$B$21,0)),"") | D8: =SUMIF(Справочники!$H$4:$H$21,$B8,Справочники!$E$4:$E$21) | E8: 1.3904205e+10 | F8: 493 | G8: 5.4846917e+08 | H8: 167 | I8: 3.8151984e+08 | J8: 125 | K8: 2.563657e+08 | L8: 87 | M8: 2.0683424e+08 | N8: 64 | O8: 1.2515414e+08 | P8: 38 | Q8: 0 | R8: 0 | S8: 28866200 | T8: 16 | U8: 0 | V8: 0 | W8: 28866200 | X8: 16 | Y8: =IFERROR($L8/$H8,"") | Z8: =IFERROR($N8/$L8,"") | AA8: =IFERROR($H8/$D8,"") | AB8: =IFERROR($L8/$D8,"") | AE8: =IFERROR($Y8,0)+ROW()/1000000
A9: 4 | B9: КАШКАДАРЁ ВИЛОЯТИ | C9: =IFERROR(INDEX(Справочники!$D$4:$D$21,MATCH($B9,Справочники!$B$4:$B$21,0)),"") | D9: =SUMIF(Справочники!$H$4:$H$21,$B9,Справочники!$E$4:$E$21) | E9: 1.2186569e+10 | F9: 418 | G9: 3.3572778e+08 | H9: 158 | I9: 7478935.6 | J9: 69 | K9: 1759260 | L9: 49 | M9: 1759260 | N9: 21 | O9: 0 | P9: 17 | Q9: 5719675.6 | R9: 3 | S9: 0 | T9: 7 | U9: 0 | V9: 0 | W9: 0 | X9: 7 | Y9: =IFERROR($L9/$H9,"") | Z9: =IFERROR($N9/$L9,"") | AA9: =IFERROR($H9/$D9,"") | AB9: =IFERROR($L9/$D9,"") | AE9: =IFERROR($Y9,0)+ROW()/1000000
A10: 5 | B10: КОРАКАЛПОГИСТОН РЕСПУБЛИКАСИ | C10: =IFERROR(INDEX(Справочники!$D$4:$D$21,MATCH($B10,Справочники!$B$4:$B$21,0)),"") | D10: =SUMIF(Справочники!$H$4:$H$21,$B10,Справочники!$E$4:$E$21) | E10: 1.1119545e+10 | F10: 269 | G10: 4.8467592e+08 | H10: 113 | I10: 1.2179712e+08 | J10: 37 | K10: 1.013246e+08 | L10: 33 | M10: 30601547 | N10: 9 | O10: 20472522 | P10: 4 | Q10: 0 | R10: 0 | S10: 50496784 | T10: 16 | U10: 0 | V10: 0 | W10: 50496784 | X10: 16 | Y10: =IFERROR($L10/$H10,"") | Z10: =IFERROR($N10/$L10,"") | AA10: =IFERROR($H10/$D10,"") | AB10: =IFERROR($L10/$D10,"") | AE10: =IFERROR($Y10,0)+ROW()/1000000
A11: 6 | B11: НАВОИЙ ВИЛОЯТИ | C11: =IFERROR(INDEX(Справочники!$D$4:$D$21,MATCH($B11,Справочники!$B$4:$B$21,0)),"") | D11: =SUMIF(Справочники!$H$4:$H$21,$B11,Справочники!$E$4:$E$21) | E11: 6.476845e+09 | F11: 209 | G11: 3.0389556e+08 | H11: 83 | I11: 2810986.4 | J11: 1 | K11: 0 | L11: 0 | M11: 0 | N11: 0 | O11: 2810986.4 | P11: 1 | Q11: 0 | R11: 0 | S11: 0 | T11: 0 | U11: 0 | V11: 0 | W11: 0 | X11: 0 | Y11: =IFERROR($L11/$H11,"") | Z11: =IFERROR($N11/$L11,"") | AA11: =IFERROR($H11/$D11,"") | AB11: =IFERROR($L11/$D11,"") | AE11: =IFERROR($Y11,0)+ROW()/1000000
A12: 7 | B12: НАМАНГАН ВИЛОЯТИ | C12: =IFERROR(INDEX(Справочники!$D$4:$D$21,MATCH($B12,Справочники!$B$4:$B$21,0)),"") | D12: =SUMIF(Справочники!$H$4:$H$21,$B12,Справочники!$E$4:$E$21) | E12: 1.4729616e+10 | F12: 438 | G12: 1.0084511e+09 | H12: 171 | I12: 6.1986501e+08 | J12: 107 | K12: 2.2254297e+08 | L12: 57 | M12: 42191979 | N12: 14 | O12: 3.9198636e+08 | P12: 47 | Q12: 5335685 | R12: 3 | S12: 20606529 | T12: 7 | U12: 0 | V12: 0 | W12: 20606529 | X12: 7 | Y12: =IFERROR($L12/$H12,"") | Z12: =IFERROR($N12/$L12,"") | AA12: =IFERROR($H12/$D12,"") | AB12: =IFERROR($L12/$D12,"") | AE12: =IFERROR($Y12,0)+ROW()/1000000
A13: 8 | B13: САМАРКАНД ВИЛОЯТИ | C13: =IFERROR(INDEX(Справочники!$D$4:$D$21,MATCH($B13,Справочники!$B$4:$B$21,0)),"") | D13: =SUMIF(Справочники!$H$4:$H$21,$B13,Справочники!$E$4:$E$21) | E13: 1.6007859e+10 | F13: 549 | G13: 8.0057963e+08 | H13: 232 | I13: 1.2506546e+08 | J13: 42 | K13: 72321805 | L13: 30 | M13: 48397085 | N13: 24 | O13: 52743657 | P13: 12 | Q13: 0 | R13: 0 | S13: 1856396.5 | T13: 3 | U13: 0 | V13: 0 | W13: 1856396.5 | X13: 3 | Y13: =IFERROR($L13/$H13,"") | Z13: =IFERROR($N13/$L13,"") | AA13: =IFERROR($H13/$D13,"") | AB13: =IFERROR($L13/$D13,"") | AE13: =IFERROR($Y13,0)+ROW()/1000000
A14: 9 | B14: СИРДАРЁ ВИЛОЯТИ | C14: =IFERROR(INDEX(Справочники!$D$4:$D$21,MATCH($B14,Справочники!$B$4:$B$21,0)),"") | D14: =SUMIF(Справочники!$H$4:$H$21,$B14,Справочники!$E$4:$E$21) | E14: 7.1897605e+09 | F14: 151 | G14: 2.7876346e+08 | H14: 65 | I14: 0 | J14: 0 | K14: 0 | L14: 0 | M14: 0 | N14: 0 | O14: 0 | P14: 0 | Q14: 0 | R14: 0 | S14: 0 | T14: 0 | U14: 0 | V14: 0 | W14: 0 | X14: 0 | Y14: =IFERROR($L14/$H14,"") | Z14: =IFERROR($N14/$L14,"") | AA14: =IFERROR($H14/$D14,"") | AB14: =IFERROR($L14/$D14,"") | AE14: =IFERROR($Y14,0)+ROW()/1000000
A15: 10 | B15: СУРХОНДАРЁ ВИЛОЯТИ | C15: =IFERROR(INDEX(Справочники!$D$4:$D$21,MATCH($B15,Справочники!$B$4:$B$21,0)),"") | D15: =SUMIF(Справочники!$H$4:$H$21,$B15,Справочники!$E$4:$E$21) | E15: 1.6585229e+10 | F15: 558 | G15: 1.5880336e+09 | H15: 218 | I15: 1.5880336e+09 | J15: 218 | K15: 1.1378257e+09 | L15: 139 | M15: 57633348 | N15: 24 | O15: 4.0632155e+08 | P15: 63 | Q15: 43886316 | R15: 16 | S15: 14932571 | T15: 7 | U15: 0 | V15: 0 | W15: 14932571 | X15: 7 | Y15: =IFERROR($L15/$H15,"") | Z15: =IFERROR($N15/$L15,"") | AA15: =IFERROR($H15/$D15,"") | AB15: =IFERROR($L15/$D15,"") | AE15: =IFERROR($Y15,0)+ROW()/1000000
A16: 11 | B16: ТОШКЕНТ ВИЛОЯТИ | C16: =IFERROR(INDEX(Справочники!$D$4:$D$21,MATCH($B16,Справочники!$B$4:$B$21,0)),"") | D16: =SUMIF(Справочники!$H$4:$H$21,$B16,Справочники!$E$4:$E$21) | E16: 3.6871387e+10 | F16: 842 | G16: 1.4550173e+09 | H16: 321 | I16: 0 | J16: 0 | K16: 0 | L16: 0 | M16: 0 | N16: 0 | O16: 0 | P16: 0 | Q16: 0 | R16: 0 | S16: 0 | T16: 0 | U16: 0 | V16: 0 | W16: 0 | X16: 0 | Y16: =IFERROR($L16/$H16,"") | Z16: =IFERROR($N16/$L16,"") | AA16: =IFERROR($H16/$D16,"") | AB16: =IFERROR($L16/$D16,"") | AE16: =IFERROR($Y16,0)+ROW()/1000000
A17: 12 | B17: ТОШКЕНТ ШАХРИ | C17: =IFERROR(INDEX(Справочники!$D$4:$D$21,MATCH($B17,Справочники!$B$4:$B$21,0)),"") | D17: =SUMIF(Справочники!$H$4:$H$21,$B17,Справочники!$E$4:$E$21) | E17: 4.3531855e+10 | F17: 908 | G17: 1.9704467e+09 | H17: 295 | I17: 1.4059493e+09 | J17: 161 | K17: 8.2671328e+08 | L17: 96 | M17: 5.7953195e+08 | N17: 74 | O17: 5.0072502e+08 | P17: 49 | Q17: 78511013 | R17: 16 | S17: 1.6690603e+08 | T17: 16 | U17: 0 | V17: 0 | W17: 1.6690603e+08 | X17: 16 | Y17: =IFERROR($L17/$H17,"") | Z17: =IFERROR($N17/$L17,"") | AA17: =IFERROR($H17/$D17,"") | AB17: =IFERROR($L17/$D17,"") | AE17: =IFERROR($Y17,0)+ROW()/1000000
... A19: 14 | B19: ХОРАЗМ ВИЛОЯТИ | C19: =IFERROR(INDEX(Справочники!$D$4:$D$21,MATCH($B19,Справочники!$B$4:$B$21,0)),"") | D19: =SUMIF(Справочники!$H$4:$H$21,$B19,Справочники!$E$4:$E$21) | E19: 2.0499096e+10 | F19: 504 | G19: 7.1184917e+08 | H19: 176 | I19: 3.9373943e+08 | J19: 108 | K19: 2.3235121e+08 | L19: 72 | M19: 1.1876296e+08 | N19: 43 | O19: 80712644 | P19: 28 | Q19: 80675581 | R19: 8 | S19: 16024023 | T19: 9 | U19: 0 | V19: 0 | W19: 16024023 | X19: 9 | Y19: =IFERROR($L19/$H19,"") | Z19: =IFERROR($N19/$L19,"") | AA19: =IFERROR($H19/$D19,"") | AB19: =IFERROR($L19/$D19,"") | AE19: =IFERROR($Y19,0)+ROW()/1000000
B20: ИТОГО | D20: =SUM(D6:D19) | E20: =SUM(E6:E19) | F20: =SUM(F6:F19) | G20: =SUM(G6:G19) | H20: =SUM(H6:H19) | I20: =SUM(I6:I19) | J20: =SUM(J6:J19) | K20: =SUM(K6:K19) | ... X20: =SUM(X6:X19) | Y20: =IFERROR($L20/$H20,"") | Z20: =IFERROR($N20/$L20,"") | AA20: =IFERROR($H20/$D20,"") | AB20: =IFERROR($L20/$D20,"")
G21: = все кредиты в просрочке | I21: = Gaplashgan + Ko'tarmadi + Объезд (вся работа за день) | K21: = все, кто взял трубку: Va'da berdi + To'ladi | W21: = Оплатил дозвон + Объезд оплатил
B23: ОТКРЫТЬ СПИСОК КЛИЕНТОВ
B24: Область | C24: Gaplashgan | D24: Обещали | E24: Ko'tarmadi | F24: Объезд | G24: Оплатили | H24: Опл. без разг.
B25: АНДИЖОН ВИЛОЯТИ | C25: ▸ | D25: ▸ | E25: ▸ | F25: ▸ | G25: ▸
B26: БУХОРО ВИЛОЯТИ | C26: ▸ | D26: ▸ | E26: ▸ | F26: ▸ | G26: ▸
B27: ЖИЗЗАХ ВИЛОЯТИ | C27: ▸ | D27: ▸ | E27: ▸ | G27: ▸
B28: КАШКАДАРЁ ВИЛОЯТИ | C28: ▸ | D28: ▸ | E28: ▸ | F28: ▸ | G28: ▸
B29: КОРАКАЛПОГИСТОН РЕСПУБЛИКАСИ | C29: ▸ | D29: ▸ | E29: ▸ | G29: ▸
B30: НАВОИЙ ВИЛОЯТИ | E30: ▸
B31: НАМАНГАН ВИЛОЯТИ | C31: ▸ | D31: ▸ | E31: ▸ | F31: ▸ | G31: ▸
B32: САМАРКАНД ВИЛОЯТИ | C32: ▸ | D32: ▸ | E32: ▸ | G32: ▸
B33: СИРДАРЁ ВИЛОЯТИ
B34: СУРХОНДАРЁ ВИЛОЯТИ | C34: ▸ | D34: ▸ | E34: ▸ | F34: ▸ | G34: ▸
B35: ТОШКЕНТ ВИЛОЯТИ
B36: ТОШКЕНТ ШАХРИ | C36: ▸ | D36: ▸ | E36: ▸ | F36: ▸ | G36: ▸ | H36: ▸
B37: ФАРГОНА ВИЛОЯТИ | C37: ▸ | D37: ▸ | E37: ▸ | F37: ▸ | G37: ▸
B38: ХОРАЗМ ВИЛОЯТИ | C38: ▸ | D38: ▸ | E38: ▸ | F38: ▸ | G38: ▸

Sheet Отчёт_дня
A3: Дата отчёта: | C3: =Ввод!$C$2 -> 46272
A6: 1. ПОКАЗАТЕЛИ ДНЯ
A7: Портфель, сум | D7: =Ввод!$E$20 -> 2.4329876e+11
A8: Просрочка, сум | D8: =Ввод!$G$20 -> 6.9014395e+09
A9: % просрочки к портфелю | D9: =IFERROR(Ввод!$G$20/Ввод!$E$20,"")
A10: Просрочка, шт | D10: =Ввод!$H$20 -> 725
A11: Звонков всего, шт | D11: =Ввод!$J$20
A12: Gaplashgan, шт | D12: =Ввод!$L$20
A13: % дозвона | D13: =Ввод!$Y$20
A14: Обещали оплату, шт | D14: =Ввод!$N$20
A15: Не взяли трубку (Ko'tarmadi), шт | D15: =Ввод!$P$20
A16: Объезд, шт | D16: =Ввод!$R$20
A17: Не тронуты (Ishlanmagan), шт | D17: =Ввод!$H$20-Ввод!$L$20-Ввод!$P$20-Ввод!$R$20
A18: Оплачено общее (дозвон + объезд), сум | D18: =Ввод!$W$20
A19: 2. ДЕТАЛИЗАЦИЯ ПО ОБЛАСТЯМ
A21: Область | B21: Ответственный | C21: Сотруд- ников | D21: % дозвона | E21: Просрочка на 1 сотр. | F21: Оплачено, сум | G21: Оценка
A22: =Ввод!$B$6 -> АНДИЖОН ВИЛОЯТИ | B22: =Ввод!$C$6 | C22: =Ввод!$D$6 -> 0 | D22: =IFERROR(Ввод!$Y$6,0) -> 0 | E22: =IFERROR(Ввод!$AA$6,0) | F22: =Ввод!$W$6 -> 0 | G22: =IF(Ввод!$H$6=0,"Нет данных",IF($D22>=0.8,"Отлично",IF($D22>=0.5,"Хорошо","Требует внимания"))) -> Требует внимания
A23: =Ввод!$B$7 -> БУХОРО ВИЛОЯТИ | B23: =Ввод!$C$7 | C23: =Ввод!$D$7 -> 0 | D23: =IFERROR(Ввод!$Y$7,0) -> 0 | E23: =IFERROR(Ввод!$AA$7,0) | F23: =Ввод!$W$7 -> 0 | G23: =IF(Ввод!$H$7=0,"Нет данных",IF($D23>=0.8,"Отлично",IF($D23>=0.5,"Хорошо","Требует внимания"))) -> Требует внимания
A24: =Ввод!$B$8 -> ЖИЗЗАХ ВИЛОЯТИ | B24: =Ввод!$C$8 | C24: =Ввод!$D$8 -> 0 | D24: =IFERROR(Ввод!$Y$8,0) -> 0.39215686 | E24: =IFERROR(Ввод!$AA$8,0) | F24: =Ввод!$W$8 -> 0 | G24: =IF(Ввод!$H$8=0,"Нет данных",IF($D24>=0.8,"Отлично",IF($D24>=0.5,"Хорошо","Требует внимания"))) -> Требует внимания
A25: =Ввод!$B$9 -> КАШКАДАРЁ ВИЛОЯТИ | B25: =Ввод!$C$9 | C25: =Ввод!$D$9 -> 0 | D25: =IFERROR(Ввод!$Y$9,0) -> 0.87878788 | E25: =IFERROR(Ввод!$AA$9,0) | F25: =Ввод!$W$9 -> 0 | G25: =IF(Ввод!$H$9=0,"Нет данных",IF($D25>=0.8,"Отлично",IF($D25>=0.5,"Хорошо","Требует внимания"))) -> Отлично
A26: =Ввод!$B$10 -> КОРАКАЛПОГИСТОН РЕСПУБЛИКАСИ | B26: =Ввод!$C$10 | C26: =Ввод!$D$10 -> 0 | D26: =IFERROR(Ввод!$Y$10,0) -> 0.76923077 | E26: =IFERROR(Ввод!$AA$10,0) | F26: =Ввод!$W$10 -> 0 | G26: =IF(Ввод!$H$10=0,"Нет данных",IF($D26>=0.8,"Отлично",IF($D26>=0.5,"Хорошо","Требует внимания"))) -> Хорошо
A27: =Ввод!$B$11 -> НАВОИЙ ВИЛОЯТИ | B27: =Ввод!$C$11 | C27: =Ввод!$D$11 -> 0 | D27: =IFERROR(Ввод!$Y$11,0) -> 0.055555556 | E27: =IFERROR(Ввод!$AA$11,0) | F27: =Ввод!$W$11 -> 0 | G27: =IF(Ввод!$H$11=0,"Нет данных",IF($D27>=0.8,"Отлично",IF($D27>=0.5,"Хорошо","Требует внимания"))) -> Требует внимания
A28: =Ввод!$B$12 -> НАМАНГАН ВИЛОЯТИ | B28: =Ввод!$C$12 | C28: =Ввод!$D$12 -> 0 | D28: =IFERROR(Ввод!$Y$12,0) -> 0.48387097 | E28: =IFERROR(Ввод!$AA$12,0) | F28: =Ввод!$W$12 -> 0 | G28: =IF(Ввод!$H$12=0,"Нет данных",IF($D28>=0.8,"Отлично",IF($D28>=0.5,"Хорошо","Требует внимания"))) -> Требует внимания
A29: =Ввод!$B$13 -> САМАРКАНД ВИЛОЯТИ | B29: =Ввод!$C$13 | C29: =Ввод!$D$13 -> 0 | D29: =IFERROR(Ввод!$Y$13,0) -> 0.24590164 | E29: =IFERROR(Ввод!$AA$13,0) | F29: =Ввод!$W$13 -> 0 | G29: =IF(Ввод!$H$13=0,"Нет данных",IF($D29>=0.8,"Отлично",IF($D29>=0.5,"Хорошо","Требует внимания"))) -> Требует внимания
A30: =Ввод!$B$14 -> СИРДАРЁ ВИЛОЯТИ | B30: =Ввод!$C$14 | C30: =Ввод!$D$14 -> 0 | D30: =IFERROR(Ввод!$Y$14,0) -> 0.58823529 | E30: =IFERROR(Ввод!$AA$14,0) | F30: =Ввод!$W$14 -> 0 | G30: =IF(Ввод!$H$14=0,"Нет данных",IF($D30>=0.8,"Отлично",IF($D30>=0.5,"Хорошо","Требует внимания"))) -> Хорошо
A31: =Ввод!$B$15 -> СУРХОНДАРЁ ВИЛОЯТИ | B31: =Ввод!$C$15 | C31: =Ввод!$D$15 -> 0 | D31: =IFERROR(Ввод!$Y$15,0) -> 0.18556701 | E31: =IFERROR(Ввод!$AA$15,0) | F31: =Ввод!$W$15 -> 0 | G31: =IF(Ввод!$H$15=0,"Нет данных",IF($D31>=0.8,"Отлично",IF($D31>=0.5,"Хорошо","Требует внимания"))) -> Требует внимания
A32: =Ввод!$B$16 -> ТОШКЕНТ ВИЛОЯТИ | B32: =Ввод!$C$16 | C32: =Ввод!$D$16 -> 0 | D32: =IFERROR(Ввод!$Y$16,0) -> 0 | E32: =IFERROR(Ввод!$AA$16,0) | F32: =Ввод!$W$16 -> 0 | G32: =IF(Ввод!$H$16=0,"Нет данных",IF($D32>=0.8,"Отлично",IF($D32>=0.5,"Хорошо","Требует внимания"))) -> Требует внимания
A33: =Ввод!$B$17 -> ТОШКЕНТ ШАХРИ | B33: =Ввод!$C$17 | C33: =Ввод!$D$17 -> 0 | D33: =IFERROR(Ввод!$Y$17,0) -> 0 | E33: =IFERROR(Ввод!$AA$17,0) | F33: =Ввод!$W$17 -> 0 | G33: =IF(Ввод!$H$17=0,"Нет данных",IF($D33>=0.8,"Отлично",IF($D33>=0.5,"Хорошо","Требует внимания"))) -> Требует внимания
A34: =Ввод!$B$18 -> ФАРГОНА ВИЛОЯТИ | B34: =Ввод!$C$18 | C34: =Ввод!$D$18 -> 0 | D34: =IFERROR(Ввод!$Y$18,0) -> 0 | E34: =IFERROR(Ввод!$AA$18,0) | F34: =Ввод!$W$18 -> 0 | G34: =IF(Ввод!$H$18=0,"Нет данных",IF($D34>=0.8,"Отлично",IF($D34>=0.5,"Хорошо","Требует внимания"))) -> Требует внимания
A35: =Ввод!$B$19 -> ХОРАЗМ ВИЛОЯТИ | B35: =Ввод!$C$19 | C35: =Ввод!$D$19 -> 0 | D35: =IFERROR(Ввод!$Y$19,0) -> 0.46938776 | E35: =IFERROR(Ввод!$AA$19,0) | F35: =Ввод!$W$19 -> 0 | G35: =IF(Ввод!$H$19=0,"Нет данных",IF($D35>=0.8,"Отлично",IF($D35>=0.5,"Хорошо","Требует внимания"))) -> Требует внимания
A41: 6. ЛИДЕРЫ И ОТСТАЮЩИЕ ПО % ДОЗВОНА (по областям)
A42: Лидеры | C42: % дозвона | E42: Требуют внимания | H42: % дозвона
A43: =IFERROR(INDEX(Ввод!$B$6:$B$19,MATCH(LARGE(Ввод!$AE$6:$AE$19,1),Ввод!$AE$6:$AE$19,0)),"") -> КАШКАДАРЁ ВИЛОЯТИ | C43: =IFERROR(INDEX(Ввод!$Y$6:$Y$19,MATCH(LARGE(Ввод!$AE$6:$AE$19,1),Ввод!$AE$6:$AE$19,0)),"") -> 0.87878788 | E43: =IFERROR(INDEX(Ввод!$B$6:$B$19,MATCH(SMALL(Ввод!$AE$6:$AE$19,1),Ввод!$AE$6:$AE$19,0)),"") -> АНДИЖОН ВИЛОЯТИ | H43: =IFERROR(INDEX(Ввод!$Y$6:$Y$19,MATCH(SMALL(Ввод!$AE$6:$AE$19,1),Ввод!$AE$6:$AE$19,0)),"") -> 0
A44: =IFERROR(INDEX(Ввод!$B$6:$B$19,MATCH(LARGE(Ввод!$AE$6:$AE$19,2),Ввод!$AE$6:$AE$19,0)),"") -> КОРАКАЛПОГИСТОН РЕСПУБЛИКАСИ | C44: =IFERROR(INDEX(Ввод!$Y$6:$Y$19,MATCH(LARGE(Ввод!$AE$6:$AE$19,2),Ввод!$AE$6:$AE$19,0)),"") -> 0.76923077 | E44: =IFERROR(INDEX(Ввод!$B$6:$B$19,MATCH(SMALL(Ввод!$AE$6:$AE$19,2),Ввод!$AE$6:$AE$19,0)),"") -> БУХОРО ВИЛОЯТИ | H44: =IFERROR(INDEX(Ввод!$Y$6:$Y$19,MATCH(SMALL(Ввод!$AE$6:$AE$19,2),Ввод!$AE$6:$AE$19,0)),"") -> 0
A45: =IFERROR(INDEX(Ввод!$B$6:$B$19,MATCH(LARGE(Ввод!$AE$6:$AE$19,3),Ввод!$AE$6:$AE$19,0)),"") -> СИРДАРЁ ВИЛОЯТИ | C45: =IFERROR(INDEX(Ввод!$Y$6:$Y$19,MATCH(LARGE(Ввод!$AE$6:$AE$19,3),Ввод!$AE$6:$AE$19,0)),"") -> 0.58823529 | E45: =IFERROR(INDEX(Ввод!$B$6:$B$19,MATCH(SMALL(Ввод!$AE$6:$AE$19,3),Ввод!$AE$6:$AE$19,0)),"") -> ТОШКЕНТ ВИЛОЯТИ | H45: =IFERROR(INDEX(Ввод!$Y$6:$Y$19,MATCH(SMALL(Ввод!$AE$6:$AE$19,3),Ввод!$AE$6:$AE$19,0)),"") -> 0

Sheet Дашборд
A3: Дата отчёта: | C3: =Ввод!$C$2 -> 46272 | E3: Просрочка, сум | H3: =Ввод!$G$20 -> 6.9014395e+09
E4: Оплачено за день, сум | H4: =Ввод!$W$20 -> 0
E5: Просрочка на 1 сотрудника, шт | H5: =IFERROR(Ввод!$H$20/Ввод!$D$20,0) -> 0
A7: СВОД ПО ОБЛАСТЯМ
A8: Область | B8: Тип | C8: Сотруд- ников | D8: Портфель, сум | E8: Просрочка, сум | F8: % просрочки | G8: Просрочка, шт | H8: Дозвон, шт | I8: % дозвона | J8: Просрочка на 1 сотр. | K8: Обещали, шт | L8: Оплачено, сум | M8: Оценка | N8: Область
A9: =Ввод!$B$6 -> АНДИЖОН ВИЛОЯТИ | C9: =Ввод!$D$6 -> 0 | D9: =Ввод!$E$6 -> 2.1670184e+10 | E9: =Ввод!$G$6 -> 2.1699731e+08 | F9: =IFERROR($E9/$D9,0) -> 0.010013635 | G9: =Ввод!$H$6 -> 32 | H9: =Ввод!$L$6 -> 0 | I9: =IFERROR($H9/$G9,0) -> 0 | J9: =IFERROR($G9/$C9,0) -> 0 | K9: =Ввод!$N$6 -> 0 | L9: =Ввод!$W$6 -> 0 | M9: =IF($G9=0,"Нет данных",IF($I9>=0.8,"Отлично",IF($I9>=0.5,"Хорошо","Требует внимания"))) -> Требует внимания | N9: =IFERROR(INDEX(Справочники!$H$4:$H$21,MATCH($A9,Справочники!$B$4:$B$21,0)),"")
A10: =Ввод!$B$7 -> БУХОРО ВИЛОЯТИ | C10: =Ввод!$D$7 -> 0 | D10: =Ввод!$E$7 -> 5.1231734e+09 | E10: =Ввод!$G$7 -> 2.0266951e+08 | F10: =IFERROR($E10/$D10,0) -> 0.03955937 | G10: =Ввод!$H$7 -> 18 | H10: =Ввод!$L$7 -> 0 | I10: =IFERROR($H10/$G10,0) -> 0 | J10: =IFERROR($G10/$C10,0) -> 0 | K10: =Ввод!$N$7 -> 0 | L10: =Ввод!$W$7 -> 0 | M10: =IF($G10=0,"Нет данных",IF($I10>=0.8,"Отлично",IF($I10>=0.5,"Хорошо","Требует внимания"))) -> Требует внимания | N10: =IFERROR(INDEX(Справочники!$H$4:$H$21,MATCH($A10,Справочники!$B$4:$B$21,0)),"")
A11: =Ввод!$B$8 -> ЖИЗЗАХ ВИЛОЯТИ | C11: =Ввод!$D$8 -> 0 | D11: =Ввод!$E$8 -> 1.3904205e+10 | E11: =Ввод!$G$8 -> 2.498528e+08 | F11: =IFERROR($E11/$D11,0) -> 0.017969585 | G11: =Ввод!$H$8 -> 51 | H11: =Ввод!$L$8 -> 20 | I11: =IFERROR($H11/$G11,0) -> 0.39215686 | J11: =IFERROR($G11/$C11,0) -> 0 | K11: =Ввод!$N$8 -> 19 | L11: =Ввод!$W$8 -> 0 | M11: =IF($G11=0,"Нет данных",IF($I11>=0.8,"Отлично",IF($I11>=0.5,"Хорошо","Требует внимания"))) -> Требует внимания | N11: =IFERROR(INDEX(Справочники!$H$4:$H$21,MATCH($A11,Справочники!$B$4:$B$21,0)),"")
A12: =Ввод!$B$9 -> КАШКАДАРЁ ВИЛОЯТИ | C12: =Ввод!$D$9 -> 0 | D12: =Ввод!$E$9 -> 1.2186569e+10 | E12: =Ввод!$G$9 -> 2.0555796e+08 | F12: =IFERROR($E12/$D12,0) -> 0.016867583 | G12: =Ввод!$H$9 -> 33 | H12: =Ввод!$L$9 -> 29 | I12: =IFERROR($H12/$G12,0) -> 0.87878788 | J12: =IFERROR($G12/$C12,0) -> 0 | K12: =Ввод!$N$9 -> 18 | L12: =Ввод!$W$9 -> 0 | M12: =IF($G12=0,"Нет данных",IF($I12>=0.8,"Отлично",IF($I12>=0.5,"Хорошо","Требует внимания"))) -> Отлично | N12: =IFERROR(INDEX(Справочники!$H$4:$H$21,MATCH($A12,Справочники!$B$4:$B$21,0)),"")
A13: =Ввод!$B$10 -> КОРАКАЛПОГИСТОН РЕСПУБЛИКАСИ | C13: =Ввод!$D$10 -> 0 | D13: =Ввод!$E$10 -> 1.1119545e+10 | E13: =Ввод!$G$10 -> 2.5963958e+08 | F13: =IFERROR($E13/$D13,0) -> 0.023349839 | G13: =Ввод!$H$10 -> 26 | H13: =Ввод!$L$10 -> 20 | I13: =IFERROR($H13/$G13,0) -> 0.76923077 | J13: =IFERROR($G13/$C13,0) -> 0 | K13: =Ввод!$N$10 -> 4 | L13: =Ввод!$W$10 -> 0 | M13: =IF($G13=0,"Нет данных",IF($I13>=0.8,"Отлично",IF($I13>=0.5,"Хорошо","Требует внимания"))) -> Хорошо | N13: =IFERROR(INDEX(Справочники!$H$4:$H$21,MATCH($A13,Справочники!$B$4:$B$21,0)),"")
A14: =Ввод!$B$11 -> НАВОИЙ ВИЛОЯТИ | C14: =Ввод!$D$11 -> 0 | D14: =Ввод!$E$11 -> 6.476845e+09 | E14: =Ввод!$G$11 -> 1.0708535e+08 | F14: =IFERROR($E14/$D14,0) -> 0.016533567 | G14: =Ввод!$H$11 -> 18 | H14: =Ввод!$L$11 -> 1 | I14: =IFERROR($H14/$G14,0) -> 0.055555556 | J14: =IFERROR($G14/$C14,0) -> 0 | K14: =Ввод!$N$11 -> 1 | L14: =Ввод!$W$11 -> 0 | M14: =IF($G14=0,"Нет данных",IF($I14>=0.8,"Отлично",IF($I14>=0.5,"Хорошо","Требует внимания"))) -> Требует внимания | N14: =IFERROR(INDEX(Справочники!$H$4:$H$21,MATCH($A14,Справочники!$B$4:$B$21,0)),"")
A15: =Ввод!$B$12 -> НАМАНГАН ВИЛОЯТИ | C15: =Ввод!$D$12 -> 0 | D15: =Ввод!$E$12 -> 1.4729616e+10 | E15: =Ввод!$G$12 -> 5.9799851e+08 | F15: =IFERROR($E15/$D15,0) -> 0.040598377 | G15: =Ввод!$H$12 -> 62 | H15: =Ввод!$L$12 -> 30 | I15: =IFERROR($H15/$G15,0) -> 0.48387097 | J15: =IFERROR($G15/$C15,0) -> 0 | K15: =Ввод!$N$12 -> 30 | L15: =Ввод!$W$12 -> 0 | M15: =IF($G15=0,"Нет данных",IF($I15>=0.8,"Отлично",IF($I15>=0.5,"Хорошо","Требует внимания"))) -> Требует внимания | N15: =IFERROR(INDEX(Справочники!$H$4:$H$21,MATCH($A15,Справочники!$B$4:$B$21,0)),"")
A16: =Ввод!$B$13 -> САМАРКАНД ВИЛОЯТИ | C16: =Ввод!$D$13 -> 0 | D16: =Ввод!$E$13 -> 1.6007859e+10 | E16: =Ввод!$G$13 -> 2.6721243e+08 | F16: =IFERROR($E16/$D16,0) -> 0.016692577 | G16: =Ввод!$H$13 -> 61 | H16: =Ввод!$L$13 -> 15 | I16: =IFERROR($H16/$G16,0) -> 0.24590164 | J16: =IFERROR($G16/$C16,0) -> 0 | K16: =Ввод!$N$13 -> 15 | L16: =Ввод!$W$13 -> 0 | M16: =IF($G16=0,"Нет данных",IF($I16>=0.8,"Отлично",IF($I16>=0.5,"Хорошо","Требует внимания"))) -> Требует внимания | N16: =IFERROR(INDEX(Справочники!$H$4:$H$21,MATCH($A16,Справочники!$B$4:$B$21,0)),"")
A17: =Ввод!$B$14 -> СИРДАРЁ ВИЛОЯТИ | C17: =Ввод!$D$14 -> 0 | D17: =Ввод!$E$14 -> 7.1897605e+09 | E17: =Ввод!$G$14 -> 97690450 | F17: =IFERROR($E17/$D17,0) -> 0.013587441 | G17: =Ввод!$H$14 -> 17 | H17: =Ввод!$L$14 -> 10 | I17: =IFERROR($H17/$G17,0) -> 0.58823529 | J17: =IFERROR($G17/$C17,0) -> 0 | K17: =Ввод!$N$14 -> 1 | L17: =Ввод!$W$14 -> 0 | M17: =IF($G17=0,"Нет данных",IF($I17>=0.8,"Отлично",IF($I17>=0.5,"Хорошо","Требует внимания"))) -> Хорошо | N17: =IFERROR(INDEX(Справочники!$H$4:$H$21,MATCH($A17,Справочники!$B$4:$B$21,0)),"")
A18: =Ввод!$B$15 -> СУРХОНДАРЁ ВИЛОЯТИ | C18: =Ввод!$D$15 -> 0 | D18: =Ввод!$E$15 -> 1.6585229e+10 | E18: =Ввод!$G$15 -> 1.0837511e+09 | F18: =IFERROR($E18/$D18,0) -> 0.065344354 | G18: =Ввод!$H$15 -> 97 | H18: =Ввод!$L$15 -> 18 | I18: =IFERROR($H18/$G18,0) -> 0.18556701 | J18: =IFERROR($G18/$C18,0) -> 0 | K18: =Ввод!$N$15 -> 2 | L18: =Ввод!$W$15 -> 0 | M18: =IF($G18=0,"Нет данных",IF($I18>=0.8,"Отлично",IF($I18>=0.5,"Хорошо","Требует внимания"))) -> Требует внимания | N18: =IFERROR(INDEX(Справочники!$H$4:$H$21,MATCH($A18,Справочники!$B$4:$B$21,0)),"")
A19: =Ввод!$B$16 -> ТОШКЕНТ ВИЛОЯТИ | C19: =Ввод!$D$16 -> 0 | D19: =Ввод!$E$16 -> 3.6871387e+10 | E19: =Ввод!$G$16 -> 8.8698663e+08 | F19: =IFERROR($E19/$D19,0) -> 0.024056232 | G19: =Ввод!$H$16 -> 93 | H19: =Ввод!$L$16 -> 0 | I19: =IFERROR($H19/$G19,0) -> 0 | J19: =IFERROR($G19/$C19,0) -> 0 | K19: =Ввод!$N$16 -> 0 | L19: =Ввод!$W$16 -> 0 | M19: =IF($G19=0,"Нет данных",IF($I19>=0.8,"Отлично",IF($I19>=0.5,"Хорошо","Требует внимания"))) -> Требует внимания | N19: =IFERROR(INDEX(Справочники!$H$4:$H$21,MATCH($A19,Справочники!$B$4:$B$21,0)),"")
A20: =Ввод!$B$17 -> ТОШКЕНТ ШАХРИ | C20: =Ввод!$D$17 -> 0 | D20: =Ввод!$E$17 -> 4.3531855e+10 | E20: =Ввод!$G$17 -> 1.6257267e+09 | F20: =IFERROR($E20/$D20,0) -> 0.037345679 | G20: =Ввод!$H$17 -> 115 | H20: =Ввод!$L$17 -> 0 | I20: =IFERROR($H20/$G20,0) -> 0 | J20: =IFERROR($G20/$C20,0) -> 0 | K20: =Ввод!$N$17 -> 0 | L20: =Ввод!$W$17 -> 0 | M20: =IF($G20=0,"Нет данных",IF($I20>=0.8,"Отлично",IF($I20>=0.5,"Хорошо","Требует внимания"))) -> Требует внимания | N20: =IFERROR(INDEX(Справочники!$H$4:$H$21,MATCH($A20,Справочники!$B$4:$B$21,0)),"")
A21: =Ввод!$B$18 -> ФАРГОНА ВИЛОЯТИ | C21: =Ввод!$D$18 -> 0 | D21: =Ввод!$E$18 -> 1.7403439e+10 | E21: =Ввод!$G$18 -> 806811380 | F21: =IFERROR($E21/$D21,0) -> 0.046359308 | G21: =Ввод!$H$18 -> 53 | H21: =Ввод!$L$18 -> 0 | I21: =IFERROR($H21/$G21,0) -> 0 | J21: =IFERROR($G21/$C21,0) -> 0 | K21: =Ввод!$N$18 -> 0 | L21: =Ввод!$W$18 -> 0 | M21: =IF($G21=0,"Нет данных",IF($I21>=0.8,"Отлично",IF($I21>=0.5,"Хорошо","Требует внимания"))) -> Требует внимания | N21: =IFERROR(INDEX(Справочники!$H$4:$H$21,MATCH($A21,Справочники!$B$4:$B$21,0)),"")
A22: =Ввод!$B$19 -> ХОРАЗМ ВИЛОЯТИ | C22: =Ввод!$D$19 -> 0 | D22: =Ввод!$E$19 -> 2.0499096e+10 | E22: =Ввод!$G$19 -> 2.9345986e+08 | F22: =IFERROR($E22/$D22,0) -> 0.014315746 | G22: =Ввод!$H$19 -> 49 | H22: =Ввод!$L$19 -> 23 | I22: =IFERROR($H22/$G22,0) -> 0.46938776 | J22: =IFERROR($G22/$C22,0) -> 0 | K22: =Ввод!$N$19 -> 6 | L22: =Ввод!$W$19 -> 0 | M22: =IF($G22=0,"Нет данных",IF($I22>=0.8,"Отлично",IF($I22>=0.5,"Хорошо","Требует внимания"))) -> Требует внимания | N22: =IFERROR(INDEX(Справочники!$H$4:$H$21,MATCH($A22,Справочники!$B$4:$B$21,0)),"")
A27: ИТОГО | C27: =SUM(C9:C26) -> 0 | D27: =SUM(D9:D26) -> 2.4329876e+11 | E27: =SUM(E9:E26) -> 6.9014395e+09 | F27: =IFERROR($E27/$D27,0) -> 0.02836611 | G27: =SUM(G9:G26) -> 725 | H27: =SUM(H9:H26) -> 166 | I27: =IFERROR($H27/$G27,0) -> 0.22896552 | J27: =IFERROR($G27/$C27,0) -> 0 | K27: =SUM(K9:K26) -> 96 | L27: =SUM(L9:L26) -> 0 | M27: =IF($I27>=0.8,"Отлично",IF($I27>=0.5,"Хорошо","Требует внимания")) -> Требует внимания
A30: СТРУКТУРА РАБОТЫ С ПРОСРОЧКОЙ
A31: Группа | B31: Кредитов, шт | C31: Доля
A32: Gaplashgan | B32: =Ввод!$L$20 | C32: =IFERROR(B32/SUM($B$32:$B$35),0)
A33: Ko'tarmadi | B33: =Ввод!$P$20 | C33: =IFERROR(B33/SUM($B$32:$B$35),0)
A34: Объезд | B34: =Ввод!$R$20 | C34: =IFERROR(B34/SUM($B$32:$B$35),0)
A35: Ishlanmagan | B35: =Ввод!$H$20-Ввод!$L$20-Ввод!$P$20-Ввод!$R$20 | C35: =IFERROR(B35/SUM($B$32:$B$35),0)

Sheet Справочники
A3: № | B3: Филиал (точно как в файлах) | C3: Тип | D3: Ответственный (Ф.И.О.) | E3: Кол-во сотрудников | F3: Телефон | G3: Норматив % просрочки | H3: Область | K3: Оценка эффективности | N3: Статус проверки
A4: 1 | B4: Урганч филиали | C4: Регион | D4: — впишите — | E4: 0 | F4: +998 __ ___ __ __ | G4: 0.05 | H4: ХОРАЗМ ВИЛОЯТИ | K4: Отлично (≥80% дозвона) | N4: Не проверено
A5: 2 | B5: Самарқанд филиали | C5: Регион | D5: — впишите — | E5: 0 | F5: +998 __ ___ __ __ | G5: 0.05 | H5: САМАРКАНД ВИЛОЯТИ | K5: Хорошо (50–79%) | N5: Проверено куратором
A6: 3 | B6: Денов филиали | C6: Регион | D6: — впишите — | E6: 0 | F6: +998 __ ___ __ __ | G6: 0.05 | H6: СУРХОНДАРЁ ВИЛОЯТИ | K6: Требует внимания (<50%)
A7: 4 | B7: Жиззах филиали | C7: Регион | D7: — впишите — | E7: 0 | F7: +998 __ ___ __ __ | G7: 0.05 | H7: ЖИЗЗАХ ВИЛОЯТИ | K7: Нет данных
A8: 5 | B8: Андижон филиали | C8: Регион | D8: — впишите — | E8: 0 | F8: +998 __ ___ __ __ | G8: 0.05 | H8: АНДИЖОН ВИЛОЯТИ
A9: 6 | B9: Наманган филиали | C9: Регион | D9: — впишите — | E9: 0 | F9: +998 __ ___ __ __ | G9: 0.05 | H9: НАМАНГАН ВИЛОЯТИ
A10: 7 | B10: Фарғона филиали | C10: Регион | D10: — впишите — | E10: 0 | F10: +998 __ ___ __ __ | G10: 0.05 | H10: ФАРГОНА ВИЛОЯТИ
A11: 8 | B11: Қарши филиали | C11: Регион | D11: — впишите — | E11: 0 | F11: +998 __ ___ __ __ | G11: 0.05 | H11: КАШКАДАРЁ ВИЛОЯТИ
A12: 9 | B12: Нукус филиали | C12: Регион | D12: — впишите — | E12: 0 | F12: +998 __ ___ __ __ | G12: 0.05 | H12: КОРАКАЛПОГИСТОН РЕСПУБЛИКАСИ
A13: 10 | B13: Навоий филиали | C13: Регион | D13: — впишите — | E13: 0 | F13: +998 __ ___ __ __ | G13: 0.05 | H13: НАВОИЙ ВИЛОЯТИ
A14: 11 | B14: Бухоро филиали | C14: Регион | D14: — впишите — | E14: 0 | F14: +998 __ ___ __ __ | G14: 0.05 | H14: БУХОРО ВИЛОЯТИ
A15: 12 | B15: Термиз филиали | C15: Регион | D15: — впишите — | E15: 0 | F15: +998 __ ___ __ __ | G15: 0.05 | H15: СУРХОНДАРЁ ВИЛОЯТИ
A16: 13 | B16: Гулистон филиали | C16: Регион | D16: — впишите — | E16: 0 | F16: +998 __ ___ __ __ | G16: 0.05 | H16: СИРДАРЁ ВИЛОЯТИ
A17: 14 | B17: Олмалиқ филиали | C17: Регион | D17: — впишите — | E17: 0 | F17: +998 __ ___ __ __ | G17: 0.05 | H17: ТОШКЕНТ ВИЛОЯТИ
A18: 15 | B18: Чирчик филиали | C18: Регион | D18: — впишите — | E18: 0 | F18: +998 __ ___ __ __ | G18: 0.05 | H18: ТОШКЕНТ ВИЛОЯТИ
A19: 16 | B19: Янги Йул филиали | C19: Регион | D19: — впишите — | E19: 0 | F19: +998 __ ___ __ __ | G19: 0.05 | H19: ТОШКЕНТ ВИЛОЯТИ
... A21: 18 | B21: BOSH OFIS | C21: Центральное | D21: — впишите — | E21: 0 | F21: +998 __ ___ __ __ | G21: 0.05 | H21: ТОШКЕНТ ШАХРИ
B22: ИТОГО | E22: =SUM(E4:E21) -> 0

Sheet Gaplashgan
A1: ← Вернуться в отчёт
A2: Область | B2: Филиал | C2: Группа | D2: Код клиента | E2: Клиент | F2: Номер телефона | G2: Адрес | H2: Кол-во просроченных дней | I2: Итого просрочка | J2: Оплата | K2: Izoh
A3: АНДИЖОН ВИЛОЯТИ | B3: BOSH OFIS | C3: Ko'tardi | D3: Кр-99041217-1 | E3: MAMATQULOVA ARAPAT ABDIRASHIDOVNA | F3: 998951010159 SMS O’ZI, 998940898185 SMS O’G’LI, 998959020123 SMS KELINI, 998998018591 SMS UYI, | G3: ANDIJON VILOYATI IZBOSKAN TUMANI BOTIROBOD MFY, SAXOVAT KO’CHASI 62-UY | H3: 3 | I3: 5486553.7 | K3: 15 kunga tolaydi
A4: АНДИЖОН ВИЛОЯТИ | B4: BOSH OFIS | C4: Оплатил дозвон | D4: Кр-99027266-4 | E4: RAXMONOV ISROILJON XXX | F4: 998971516979 SMS O'ZI, 998331516979 SMS AYOLI, 998951086979 SMS O’G’LI, 998950902334 SMS QIZI, +998971516979 SMS O’ZI, 998889956979 SMS AYOLI, | G4: ANDIJON VILOYATI ANDIJON TUMANI ZAVROQ MFY SHOXI-ZINDA KO’CHASI 4-UY | H4: 3 | I4: 3717878 | J4: 3717878
A5: АНДИЖОН ВИЛОЯТИ | B5: BOSH OFIS | C5: Ko'tardi | D5: Кр-99041718-1 | E5: UMIRZAKOV ULUGBEK ABDUKOXXOROVICH | F5: +998944030317 SMS O’ZI, 998930373963 SMS AYOLI, 998934181414 SMS O’G’LI, 998992522252 SMS O’G’LI, | G5: Markaz MFY, Navro’z ko’chasi, 25-uy | H5: 3 | I5: 3427129.7 | K5: 15 gacha tolaydi
A6: АНДИЖОН ВИЛОЯТИ | B6: BOSH OFIS | C6: Обещали | D6: Кр-99041164-1 | E6: MAXKAMBOYEV SALIMJON JUMABOYEVICH | F6: 998937768805 SMS OZI, 998979768805 SMS AYOLI, 998940738805 SMS ONASI, 998944428589 SMS UAKSI, | G6: ANDIJON VILOYATI XO’JAOBOD TUMANI XIDRSHA MFY, BOG’BONLAR KO’CHASI 64-UY | H6: 3 | I6: 3102788.1 | K6: bugun hal qiladi
A7: АНДИЖОН ВИЛОЯТИ | B7: BOSH OFIS | C7: Ko'tardi | D7: Кр-99041539-1 | E7: SHERALIYEV SARDORBEK SODIQJON O’G’LI | F7: 998914845776 SMS OZI, 998996325251 SMS AYOLI, 998992425251 SMS ONASI Begona, +998914845776 Primary phone from road24, 998948642717 SMS O’ZI2, | G7: Андижон вилояти Андижон шахар Бунёдкор (9-сон) МФЙ, Қўш ариқ дахаси, 46-уй, 15-хонадон | H7: 3 | I7: 2330035.9 | K7: 15 gacha tolaydi
A8: АНДИЖОН ВИЛОЯТИ | B8: BOSH OFIS | C8: Ko'tardi | D8: Кр-99040988-1 | E8: ISAQJONOV PAXLAVONJON XUSNIDDIN O’G’LI | F8: +998888008486 SMS O’ZI, 998770009233 SMS UKASI, 998991498699 SMS AYOLI, | G8: ТОПТИҚ МФЙ, ТОПТИҚ КЎЧАСИ, uy:Р/С | H8: 6 | I8: 2153478.4 | K8: dokonda ishlaydi shu hafta hal qiladi
A9: АНДИЖОН ВИЛОЯТИ | B9: BOSH OFIS | C9: Ko'tardi | D9: Кр-99041352-1 | E9: AXMEDOVA UMIDA XOSHIMOVNA | F9: 998950163403 SMS OZI, 998200102787 SMS QIZI, 998907602802 SMS OGLI, 998905287820 SMS KELINI, | G9: ANDIJON VILOYATI BALOQCHI TUMANI BOTIR MFY, D. TOJIBOYEV KO’CHASI 15-UY | H9: 3 | I9: 1893713.7 | K9: qisman toladi
A10: АНДИЖОН ВИЛОЯТИ | B10: SUPER BRANCH | C10: Ko'tardi | D10: Кр-99059626-1 | E10: ABDURAXMONOVA MANZURAXON IBRAGIMDJONOVNA | F10: 998972041812 SMS OZI, 998910530105 SMS OGLI, 998502108587 SMS QIZI, 998883838387 SMS KELINI, | G10: ANDIJON VILOYATI ASAKA TUMANI CHEK MFY XAMDO’STLIK KO’CHASI 157-UY | H10: 64 | I10: 27395326 | K10: boshqa bankdan kredit chiqaryapti
A11: АНДИЖОН ВИЛОЯТИ | B11: SUPER BRANCH | C11: Ko'tardi | D11: Кр-99057085-1 | E11: YULDASHEVA NILUFAR KAMILOVNA | F11: 998872557757 SMS OZI, 998982700122 SMS OGLI, 998772581112 SMS QIZI, 998882331807 SMS JIYANI, | G11: ANDIJON VILOYATI ANDIJON TUMANI ZANGIBOBO MFY PORLOQ KO’CHASI 306-UY | H11: 3 | I11: 9518833.3 | K11: 3-4 kunda yopiladi
A12: АНДИЖОН ВИЛОЯТИ | B12: SUPER BRANCH | C12: Ko'tardi | D12: Кр-99047889-1 | E12: SHIRMATOV MUXAMMADOZOD QODIRALI O’G’LI | F12: +998911715500 SMS O’ZI, 998772495500 SMS OG’LI, 998972225500 SMS UY, 998998173300 SMS NEVARASI, | G12: ANDIJON VILOYATI ANDIJON SHAHAR ISTIQLOL MFY OBOD 1-TOR KO’CHASI 5-UY | H12: 3 | I12: 7843014.5 | K12: kelasi hafta hal qiladi
A13: АНДИЖОН ВИЛОЯТИ | B13: SUPER BRANCH | C13: Ko'tardi | D13: Кр-99058489-1 | E13: UZOQOVA IRODA IBROYIMJONOVNA | F13: 998976388885 SMS OZI, 998882215555 SMS XOJAYINI, 998366944492 SMS OZI 2, | G13: ANDIJON VILOYATI ANDIJON TUMANI CHEM MFY ZARQAYNAR KO’CHASI 18-UY | H13: 3 | I13: 7546182.8 | K13: oyni oxirida tolaydi
A14: АНДИЖОН ВИЛОЯТИ | B14: SUPER BRANCH | C14: Ko'tardi | D14: Кр-99057627-1 | E14: ABDUGANIYEVA MATLUBAXON XXX | F14: 998911757604 SMS OZI, 998902011084 SMS OGLI, 998910611084 SMS KELIMI, 998907620065 SMS QUDASI, | G14: ANDIJON VILOYATI ANDIJON SHAHAR QORATUT MFY 5-KICHIK NOXIYA KO’CHASI 17-UY, 78-XONADON | H14: 3 | I14: 7373853.1 | K14: 20 gacha hal qiladi
A15: АНДИЖОН ВИЛОЯТИ | B15: SUPER BRANCH | C15: Ko'tardi | D15: Кр-99049616-1 | E15: DAVIDOV MAMIRJON NEMATJONOVICH | F15: 998883672747 OZI, | G15: IIV3411 | H15: 3 | I15: 6651854.2 | K15: oyni oxirida tolaydi
A16: АНДИЖОН ВИЛОЯТИ | B16: SUPER BRANCH | C16: Ko'tardi | D16: Кр-99050885-1 | E16: TAYLAKOVA MA’MURAXON NEMATJANOVNA | F16: 998501951880 SMS OZI, 998941173187 SMS UAKSI, 998936318477 SMS SINGLISI, 998970174417 SMS KELINI, | G16: ANDIJON VILOYATI ANDIJON SHAHAR BUNYODKOR MFY QO’SH ARIQ DAXASI 46-UY 31-XONADON | H16: 3 | I16: 6311346.9 | K16: ertaga hal qiladi
... A50: АНДИЖОН ВИЛОЯТИ | B50: SUPER BRANCH | C50: Ko'tardi | D50: Кр-99030503-2 | E50: ERGASHEV ZIYOIDDIN GULAMOVICH | F50: 74-226-03-32 SMS UY, 88-964-63-03 SMS JIYANI, 998937807979 SMS new ozi , | G50: ANDIJON VILOYATI ANDIJON SHAHARANDIJON MFY KZU 13 KO’CHASI 1-UY 54-XONADON | H50: 3 | I50: 1286829.3 | K50: juma kuni tolaydi
A51: АНДИЖОН ВИЛОЯТИ | B51: SUPER BRANCH | C51: Оплатил дозвон | D51: Кр-99031618-3 | E51: DJUMAYEV OZODBEK XOSHIMJON O’G’LI | F51: 88-046-01-09 SMS O’ZI , 94-536-25-36 SMS AYOLI, 99-849-09-58 SMS UKASI, 77-072-11-63 SMS DADASI, | G51: ANDIJON VILOYATI ASAKA TUMANI TURON MFY XOJI KO’CHASI 67-UY | H51: 3 | I51: 1246693.6 | J51: 1246693.6
A52: АНДИЖОН ВИЛОЯТИ | B52: SUPER BRANCH | C52: Ko'tardi | D52: Кр-99031828-2 | E52: SOXIBOV SHOXJAXON DIYORBEK O‘G‘LI | F52: 998931042419 SMS O'ZI, 998900174454 SMS O’RTOG’I Begona, 998941087800 SMS AKASI, 998914797800 SMS ONASI, +998943230050 Primary phone from road24 Begona, 998943230050 Primary phone from road24 Begona , | G52: Андижанская область, Пахтаобод тумани, Обод МСГ, ул. Обод, дом 8 | H52: 3 | I52: 1168754.2 | K52: 951188410 ozi yangi nomeri ekan qayta aloqaga chiqadi ekan
A53: АНДИЖОН ВИЛОЯТИ | B53: SUPER BRANCH | C53: Оплатил дозвон | D53: Кр-99056916-1 | E53: BO’RANOVA MARG’UBA TOXIROVNA | F53: 998881102465 SMS OZI, 998939940815 SMS OGLI, 998880052564 SMS XOJAYINI, 998905422591 SMS QZI, | G53: ANDIJON VILOYATI QO’RG’ONTEPA TUMANI UCHQUN MFY OGOXLIK KO’CHASI 1-UY | H53: 3 | I53: 1090321.7 | J53: 1090321.7
A54: АНДИЖОН ВИЛОЯТИ | B54: SUPER BRANCH | C54: Ko'tardi | D54: Кр-99039487-2 | E54: USMANOV RAXMANALI XXX | F54: 998507778257 SMS OZI, 998949595701 SMS AYOLI, 998330880202 SMS OGLI, 998505081800 SMS KELINI, | G54: ANDIJON VILOYATI JALOLQUDUQ TUMANI OLMAZOR MFY OTASHKALB KO’CHASI 26-UY | H54: 3 | I54: 995921.78 | K54: kechga ozi aloqaga chiqadi
A55: АНДИЖОН ВИЛОЯТИ | B55: SUPER BRANCH | C55: Ko'tardi | D55: Кр-99035336-2 | E55: RO’ZIYEVA MUNIRAXON SULTONOVNA | F55: 998936907720 SMS OZI, 998949796867 SMS QIZI, 998504044603 SMS OGLI, 998934446258 SMS ONASI, | G55: ANDIJON VILOYATI BO’Z TUMANI MUSTAQILLIK KO’CHASI 70-UY,11-XONADON | H55: 3 | I55: 884145.4 | K55: xaromi klent oyni oxirida tolaydi
A56: АНДИЖОН ВИЛОЯТИ | B56: SUPER BRANCH | C56: Ko'tardi | D56: Кр-99053610-1 | E56: XUJAMKULOVA AROFAT ALABAROVNA | F56: 998999038464 SMS OZI, 998930767380 SMS XOJAYIN, 998972123141 SMS OGLI, 998503005551 SMS OGLI 2, | G56: ANDIJON VILOYATI BULOQBOSHI TUMANI BARLOS MFY BOZORXIDRSHA KO’CHASI 47-UY | H56: 3 | I56: 706796.66 | K56: 20 chiga tolaydi
A57: АНДИЖОН ВИЛОЯТИ | B57: SUPER BRANCH | C57: Ko'tardi | D57: Кр-99049616-2 | E57: DAVIDOV MAMIRJON NEMATJONOVICH | F57: 998883672747 OZI, | G57: IIV3411 | H57: 3 | I57: 685271.05 | K57: oyni oxirida tolaydi
A58: АНДИЖОН ВИЛОЯТИ | B58: SUPER BRANCH | C58: Ko'tardi | D58: Кр-99037428-2 | E58: TOLIPOV MUHIDDIN AVAZJON O’G’LI | F58: 998505111153 SMS UZI , 998995001004 SMS OZI 2, 998911717258 SMS ISHXONASI, 998998677258 SMS AYOLI, | G58: ANDIJON VILOYATI BULOQBOSHI TUMANI FAROVON MFY OXANGARON KO’CHASI 46-UY | H58: 3 | I58: 497786.7 | K58: 15 kuni oylik oladi yopib beradi osha kuni
A59: АНДИЖОН ВИЛОЯТИ | B59: SUPER BRANCH | C59: Ko'tardi | D59: Кр-99040076-1 | E59: JAMALOV DILSHODBEK KAMALDINOVICH | F59: 998906248003 SMS OZI, 998902540820 SMS AYOLI, 998882511003 SMS OGLI, 998916003767 SMS OGLI 2, | G59: ANDIJON VILOYATI ANDIJON SHAXAR ISLOMOBOD MFY, D.BOLTABOEV KO’CHASI 4-UY | H59: 3 | I59: 492326.99 | K59: kelasi hafta hal qiladi
A60: АНДИЖОН ВИЛОЯТИ | B60: SUPER BRANCH | C60: Ko'tardi | D60: Кр-99027968-2 | E60: MAMADJANOV NOZIMJON ODILJANOVICH | F60: 99 308-73-75 OZI, 88-991-73-75 SMS O'ZI2, 88-324-10-33 SMS AYOLI, 91-290-02-72 SMS AKASI, +998993087375 SMS O’ZI, 998883241033 SMS O’ZI2, 998912900272 SMS AKASI, | G60: ANDIJON VILOYATI OLTINKO’L TUMANI DALVARZIN MFY DALVARZIN KO’CHASI 295-UY | H60: 3 | I60: 343483.81 | K60: kecha bittasini toladi shu hafta hammasini hal qiladi
A61: АНДИЖОН ВИЛОЯТИ | B61: SUPER BRANCH | C61: Ko'tardi | D61: Кр-99037428-3 | E61: TOLIPOV MUHIDDIN AVAZJON O’G’LI | F61: 998505111153 SMS UZI , 998995001004 SMS OZI 2, 998911717258 SMS ISHXONASI, 998998677258 SMS AYOLI, | G61: ANDIJON VILOYATI BULOQBOSHI TUMANI FAROVON MFY OXANGARON KO’CHASI 46-UY | H61: 3 | I61: 274519 | K61: 15 kuni oylik oladi yopib beradi osha kuni
A62: АНДИЖОН ВИЛОЯТИ | B62: SUPER BRANCH | C62: Оплатил дозвон | D62: Кр-99057626-1 | E62: DAVRONOV AXMADBEK ODILOVICH | F62: 998995170264 SMS UZI, 998996940764 SMS AYOLI, 998945170264 SMS UZI 2, 998902174389 SMS JIYAN, | G62: ANDIJON VILOYATI PAXTAOBOD TUMANI ANDIJON MFY, O’RIKZOR KO’CHASI 134-UY | H62: 3 | I62: 44890.31 | J62: 44890.31
A63: АНДИЖОН ВИЛОЯТИ | B63: Андижон филиали | C63: Ko'tardi | D63: Кр-99038343-2 | E63: ABDURAXMANOV XUSNIDDIN IBRAGIMDJANOVICH | F63: 998334020011 SMS OZI, 998994791984 SMS AYOLI, 998500378007 SMS O’G’LI, 998991730207 SMS O’G’LI, | G63: ANDIJON VILOYATI ANDIJON TUMANI, YUKSALISH MFY,YUKSALISH KO’CHASI 1-UY | H63: 3 | I63: 12991799 | K63: ogli bn gaplashdim kelasi hafta tolab beradi
A64: АНДИЖОН ВИЛОЯТИ | B64: Андижон филиали | C64: Ko'tardi | D64: Кр-99049159-1 | E64: RIZAYEV AZIZBEK ABDURAXIMOVICH | F64: +998931283333 SMS O’ZI, 998907657555 SMS AYOLI, 998951107515 SMS O’G’LI, 998977088111 SMS OPASI, | G64: Andijon viloyati Andijon shahar Ishchilar MFY Ishchilar ko’chasi 9-uy | H64: 3 | I64: 12072210 | K64: 15 kuni tolaydi
A65: АНДИЖОН ВИЛОЯТИ | B65: Андижон филиали | C65: Ko'tardi | D65: Кр-99050886-1 | E65: SULAYMANOV DILMUROD ABDUMALIKOVICH | F65: +998940074404 SMS O’ZI, 998773277467 SMS QIZI, 998934143383 SMS AYOLI, | G65: ANDIJON VILOYATI IZBOSKAN TUMANI OBOD MFY UZUN KO’CHA 275-UY | H65: 3 | I65: 8738729 | K65: 1-2 kunda hal qiladi
A66: АНДИЖОН ВИЛОЯТИ | B66: Андижон филиали | C66: Ko'tardi | D66: Кр-99050384-1 | E66: YUSUPOV MANSURBEK ODILJONOVICH | F66: +998914979790 SMS O’ZI, 998500407542 SMS UY, 998945631595 SMS AYOLI, 998974488280 SMS ONASI, | G66: ANDIJON VILOYATI IZBOSKAN TUMANI ROVOT MFY GAVXAR KO’CHASI 45-UY | H66: 3 | I66: 8132397.1 | K66: shu hafta hal qiladi
A67: АНДИЖОН ВИЛОЯТИ | B67: Андижон филиали | C67: Ko'tardi | D67: Кр-99035857-2 | E67: DJIYANOV XURSANBEK TADJIDINOVICH | F67: 998945010782 SMS O’ZI, 998914782277 SMS AYOLI, 998910605424 SMS O’G’LI, 998979837222 SMS QIZI , +998508823382 SMS O’ZI, 998889935007 SMS O’ZI 2, 998951312283 SMS QIZI, | G67: ANDIJON VILOYATI BULOQBOSHI TUMANI ISTIQLOL MFY GULZOR KO’CHASI 133-UY | H67: 3 | I67: 8046768.4 | K67: 15 kunga tolaydi
A68: АНДИЖОН ВИЛОЯТИ | B68: Андижон филиали | C68: Ko'tardi | D68: Кр-99060556-3 | E68: FARXODOVA DILRABO BAXADIRJANOVNA | F68: +998916111541 SMS O’ZI, 998901411541 SMS XO’JAYNI, 998905401541 SMS QIZI, | G68: ANDIJON VILOYATI XOJABOD TUMANI YUKSALISH MFY TADBIRKORLAR KO’CHASI 305-UY | H68: 3 | I68: 7097739 | K68: 15 kuni tolaydi
A69: АНДИЖОН ВИЛОЯТИ | B69: Андижон филиали | C69: Ko'tardi | D69: Кр-99033808-2 | E69: NASIRDINOV MANOPJON PATTAYEVICH | F69: 998931053080 SMS O’ZI meva sotadi , 998900000000 SMS, +998916126328 SMS O’ZI, 998916031864 SMS O’ZI2, 998943877760 SMS O’G’LI, | G69: ANDIJON VILOYATI ANDIJON TUMANI GUMBAZ MFY SHODIYONA KO’CHASI 65-UY | H69: 3 | I69: 6302586.3 | K69: oyni oxirida tolaydi
A70: АНДИЖОН ВИЛОЯТИ | B70: Андижон филиали | C70: Ko'tardi | D70: Кр-99041556-1 | E70: OTAKO’ZIYEV XAMIDILLO ZOKIROVICH | F70: +998932417333 SMS OZI, 998700138053 QIZI, 998934466605 AYOLI, 998950751927 QIZI 2, | G70: ЁЛГИЗБОГ-2 МФЙ, ЁЛГИЗБОГ-2 КЎЧАСИ, 72 uy:Р/С | H70: 3 | I70: 6242781.9 | K70: dushanba kuni tolaydi
A71: АНДИЖОН ВИЛОЯТИ | B71: Андижон филиали | C71: Ko'tardi | D71: Кр-99057092-3 | E71: RUSTAMOVA MOXIDILXON YULDASHBOYEVNA | F71: 998972357072 SMS OZI, 998931021911 SMS OGLI, 998873225757 SMS OGLI 2, 998881771514 SMS OGLI 3, | G71: ANDIJON VILOYATI PAXTAOBOD TUMANI DO’NGQISHLOQ MFY SAMOVIY KO’CHASI 122-UY | H71: 3 | I71: 5900159.2 | K71: dushanba kuni tolaydi
A72: АНДИЖОН ВИЛОЯТИ | B72: Андижон филиали | C72: Ko'tardi | D72: Кр-99044950-1 | E72: MAMAYUNUSOV SOBIRJON YUSUPOVICH | F72: +998903831002 SMS O’ZI, 998500448004 SMS O’ZI2, 998902202308 SMS QIZI, 998910697782 SMS XO’JAYNI, | G72: АНДИЖОН ВИЛОЯТИ МАРХАМАТ ТУМАНИ ГУЛИСТОН МФЙ, ФИДОКОР КЎЧАСИ, uy:Р/С | H72: 3 | I72: 5706766.2 | K72: dushanba kuni tolaydi
A73: АНДИЖОН ВИЛОЯТИ | B73: Андижон филиали | C73: Ko'tardi | D73: Кр-99058901-2 | E73: ABDURASULOVA ARAPATXON ASHURALIYEVNA | F73: +998975727678 SMS O’ZI, 998885737678 SMS KELINI, 998933527678 SMS O’G’LI, 998975831504 SMS O’ZI2, | G73: ANDIJON VILOYATI QO’RG’ONTEPA TUMANI SAVAY BIRLIK MFY ISLOXAT KO’CHASI 37-YU | H73: 3 | I73: 5151377.5 | K73: dushanba kuni tolaydi
A74: АНДИЖОН ВИЛОЯТИ | B74: Андижон филиали | C74: Ko'tardi | D74: Кр-99062778-2 | E74: SODIQOV KOMOLDIN USMONOVICH | F74: +998979727278 SMS O’G’LI TO’LOVCHI, 998772987278 SMS AYOLI, 998930657161 SMS O’ZI, 998947060694 SMS QIZI, | G74: ANDIJON VILOYATI OLTINKO’L TUMANI TEMIRXO’JA MFY TEMIRXO’JA KO’CHASI 638-UY | H74: 3 | I74: 5033250 | K74: uyini sotuvga qoydi sotib yopadi
... A78: АНДИЖОН ВИЛОЯТИ | B78: Андижон филиали | C78: Ko'tardi | D78: Кр-99041217-3 | E78: MAMATQULOVA ARAPAT ABDIRASHIDOVNA | F78: 998951010159 SMS O’ZI, 998940898185 SMS O’G’LI, 998959020123 SMS KELINI, 998998018591 SMS UYI, | G78: ANDIJON VILOYATI IZBOSKAN TUMANI BOTIROBOD MFY, SAXOVAT KO’CHASI 62-UY | H78: 3 | I78: 4795662 | K78: 15 kunga tolaydi
A79: АНДИЖОН ВИЛОЯТИ | B79: Андижон филиали | C79: Оплатил дозвон | D79: Кр-99062635-2 | E79: USMANOVA GULNOZA SHAVKATOVNA | F79: +998914907321 SMS O’ZI, 998500551620 SMS SINGLISI, 998889933833 SMS QIZI, 998946978207 SMS ONASI, 998500231621 SMS Tolovchi O'zi, | G79: Andijon viloyati Xo’jaobod tumani Mustaqillikning 27-yilligi MFY Obod ko’chasi, 67a-yu | H79: 6 | I79: 4359925.6 | J79: 4359925.6
A80: АНДИЖОН ВИЛОЯТИ | B80: Андижон филиали | C80: Ko'tardi | D80: Кр-99042844-1 | E80: NORMATOV OTABEK OLIMJANOVICH | F80: +998975555785 SMS O’ZI, 998930757991 SMS ONASI, 998940767991 SMS UKASI, 998997813005 SMS DADASI, | G80: АНДИЖОН ВИЛОЯТИ АНДИЖОН ШАХРИ А.БАКИРОВ МФЙ, А.БАКИРОВ МФЙ, О.ХУЖАЕВ, uy:5 | H80: 3 | I80: 4343424.2 | K80: shu hafta hal qiladi
A81: АНДИЖОН ВИЛОЯТИ | B81: Андижон филиали | C81: Оплатил дозвон | D81: Кр-99033630-6 | E81: ODAMBOYEVA NAZOKAT QAXRAMON QIZI | F81: 998505729393 SMS O’ZI, 998934349373 SMS KELINOYISI, 998994418804 SMS AKASI, 998940615252 SMS QARINDOSHI, +998501956662 SMS O’ZI, 998934258424 SMS POCHCHASI, 998946653675 SMS XOLASI, | G81: ANDIJON VILOYATI XO’JAOBOD TUMANI MUSTAQILLIKNING 27 YILLIGI MFY OBOD 1-TOR KO’CHASI 9-UY | H81: 3 | I81: 3866352 | J81: 3866352
A82: АНДИЖОН ВИЛОЯТИ | B82: Андижон филиали | C82: Ko'tardi | D82: Кр-99041828-1 | E82: USMANOVA BARCHINOY MARIBDJANOVNA | F82: +998901725077 SMS O’ZI, 998918763778 SMS OPASI, 998932860631 SMS QIZI, 998954801056 SMS QAYNIONASI, | G82: Андижанская область, Ходжаабадский район, Янги фаргона МСГ, ул. Янгифарғона, дом 79 | H82: 3 | I82: 3742396.3 | K82: dushanba kuni tolaydi
A83: АНДИЖОН ВИЛОЯТИ | B83: Андижон филиали | C83: Ko'tardi | D83: Кр-99039414-1 | E83: MIRZAJONOV XAYITBOY ANVAROVICH | F83: +998933404344 SMS O’ZI, 998889870570 SMS AKASI, 998947571189 SMS AYOLI, 998973393911 SMS ONASI, | G83: ANDIJON VILOYATI ASAKA TUMANI BIRLIK MFY SHODLIK KO’CHASI 181-UY | H83: 3 | I83: 3709180.1 | K83: bugun 3 mln toladi qolganini keyingi hafta hal qiladi
A84: АНДИЖОН ВИЛОЯТИ | B84: Андижон филиали | C84: Ko'tardi | D84: Кр-99029097-1 | E84: MAVLANOVA MUXAYYOXON KAXARDJANOVNA | F84: 95-988-30-07 SMS TO’LOVCHI, 90-766-61-62 SMS AYOLI, 99-340-57-54 SMS O’G’LI, 90-763-53-23- SMS O’G’LI, 998772484980 SMS opasi tolovchi new, | G84: ANDIJON VILOYATI ANDIJON SHAHAR OBOD MFY LOYIXAVIY KO’CHASI 3B-UY | H84: 3 | I84: 3629264 | K84: xar doim oyni oxirida tolaydi
A85: АНДИЖОН ВИЛОЯТИ | B85: Андижон филиали | C85: Ko'tardi | D85: Кр-99045554-1 | E85: G’OFUROV ABDULLAJON OMONOVICH | F85: 998934395830 SMS TO’LOVCHI, 998939735040 SMS AYYOLI tel qilinmasin , 998941060696 SMS O’ZI, 998944395830 SMS TO’LOVCHI, | G85: Сегаза МФЙ, Сегаза кучаси, 109-уй | H85: 3 | I85: 3352959.1 | K85: chorshanba kuni oylik oladi
A86: АНДИЖОН ВИЛОЯТИ | B86: Андижон филиали | C86: Оплатил дозвон | D86: Кр-99033630-5 | E86: ODAMBOYEVA NAZOKAT QAXRAMON QIZI | F86: 998505729393 SMS O’ZI, 998934349373 SMS KELINOYISI, 998994418804 SMS AKASI, 998940615252 SMS QARINDOSHI, +998501956662 SMS O’ZI, 998934258424 SMS POCHCHASI, 998946653675 SMS XOLASI, | G86: ANDIJON VILOYATI XO’JAOBOD TUMANI MUSTAQILLIKNING 27 YILLIGI MFY OBOD 1-TOR KO’CHASI 9-UY | H86: 3 | I86: 3247845.4 | J86: 3247845.4
A87: АНДИЖОН ВИЛОЯТИ | B87: Андижон филиали | C87: Ko'tardi | D87: Кр-99029207-1 | E87: SOBIROVA SADOQATOY RAXIMJON QIZI | F87: 94-542-12-54 SMS TOLOVCHI, 93-849-22-52 SMS TOLOVCHI XOJAYINI tanmiman ddi , 94-282-31-32 TOLOVCHI ukasi , 95-022-11-55 TOLOVCHIS OGLI, | G87: ANDIJON VILOYATI PAXTAOBOD TUMANI AXILLIK MFY AXILLIK KO’CHASI 4-UY | H87: 1 | I87: 3245773.2 | K87: 20 gacha hal qiladi
A88: АНДИЖОН ВИЛОЯТИ | B88: Андижон филиали | C88: Ko'tardi | D88: Кр-99064106-1 | E88: NISHANOVA JANONXON XXX | F88: 998880595093 SMS KELINI, 998902589657 SMS O’ZI, 998904775682 SMS QIZI, 998930514263 SMS O’G’LI, | G88: ANDIJON VILOYATI JALAQUDUQ TUMANI NAMUNA MFY MUSTAQILLIK KO’CHASI 16-UY | H88: 3 | I88: 3051857.4 | K88: ertaga ertalab tolaydi
A89: АНДИЖОН ВИЛОЯТИ | B89: Андижон филиали | C89: Ko'tardi | D89: Кр-99048763-2 | E89: ISLOMOV ABRORBEK MAMATAZIZ O’G’LI | F89: +998940981995 SMS O’ZI, 998934103343 SMS DO’STI ISAQJON, 998936130195 SMS AKASI, 998979040713 SMS AYOLI, | G89: ANDIJON VILOYATI BULOQBOSHI TUMANI NEFTCHILAR MFY KONCHILAR KO’CHASI 31-UY | H89: 3 | I89: 2795889.2 | K89: keyingi hafta seshanba kuni
A90: АНДИЖОН ВИЛОЯТИ | B90: Андижон филиали | C90: Обещали | D90: Кр-99012626-3 | E90: ISMOILOVA MUHAYYOXON RUSTAMOVNA | F90: 93-394-73-75 SMS OZI, 99-818-79-36 sms, +998938020802 SMS O’GLI, 998933132236 SMS QIZI, 998933947375 SMS ONASI, 998993132236 SMS QIZI, | G90: ANDIJON VILOYATI QO’RG’ONTEPA TUMANI QORASUV SHAHAR M.ULUG’BEK MFY KAMALAK KO’CHASI 7-UY | H90: 3 | I90: 2788273.9 | K90: erta tolaydi
A91: АНДИЖОН ВИЛОЯТИ | B91: Андижон филиали | C91: Ko'tardi | D91: Кр-99031409-1 | E91: DILMURODOV MANSURBEK DILMUROD O’G’LI | F91: 91-611-00-86 SMS O’ZI, 91-490-57-74 SMS AYOLI, 93-782-37-77 SMS TO’LOVCHI, 90-205-00-50 SMS UKASI, | G91: ANDIJON VILOYATI XO’JAOBOD TUMANI CHIM BULOQ MFY YANGI CHEK KO’CHASI 9-UY | H91: 6 | I91: 2753384 | K91: oyni oxirida tolaydi
A92: АНДИЖОН ВИЛОЯТИ | B92: Андижон филиали | C92: Ko'tardi | D92: Кр-99031551-1 | E92: XOLMIRZAYEVA ORZIXON JURABOY QIZI | F92: 99-794-17-77 SMS O'ZI, 33-253-55-55 SMS XO’JAYNI, 99-431-17-77 SMS ONASI, 90-253-09-99 SMS XO’JAYNI2, | G92: ANDIJON VILOYATI ANDIJON SHAHAR 3-KICHIK DAXA 9-UY 53-XONADON | H92: 2 | I92: 2668953.5 | K92: bugun erta hal qiladi
A93: АНДИЖОН ВИЛОЯТИ | B93: Андижон филиали | C93: Ko'tardi | D93: Кр-99062720-1 | E93: MAMIRJONOV JAXONGIRBEK ULUG’BEK O’G’LI | F93: +998979950099 SMS O’ZI, 998770001047 SMS OPASI, 998881449400 SMS AYOLI, 998934158780 SMS OPASI, | G93: ANDIJON VILOYATI ANDIJON SHAHAR BUYUK IPAK YO’LI MFY Q. NIYOZIY KO’CHASI 11-UY | H93: 6 | I93: 2460094 | K93: shu hafta hal qiladi
A94: АНДИЖОН ВИЛОЯТИ | B94: Андижон филиали | C94: Оплатил дозвон | D94: Кр-99029219-1 | E94: XUSANBOYEVA NARGIZA XOLMUROD QIZI | F94: 998507163988 SMS OZI TULOVCHISI, 93-061-98-00 SMS ERI TULOVCHISI, 94-425-98-92 SMS OZI TULOVCHISI, 93-429-12-09 SMS ONASI, 998507163998 SMS ozi new , | G94: ANDIJON TUMANI MARXAMAT TUMANI DURAFSHON KOCHASI DONISHMAND KOCHASI 8-UY | H94: 1 | I94: 2120319.3 | J94: 2120319.3 | K94: bugun yopadi
A95: АНДИЖОН ВИЛОЯТИ | B95: Андижон филиали | C95: Оплатил дозвон | D95: Кр-99031618-1 | E95: DJUMAYEV OZODBEK XOSHIMJON O’G’LI | F95: 88-046-01-09 SMS O’ZI , 94-536-25-36 SMS AYOLI, 99-849-09-58 SMS UKASI, 77-072-11-63 SMS DADASI, | G95: ANDIJON VILOYATI ASAKA TUMANI TURON MFY XOJI KO’CHASI 67-UY | H95: 2 | I95: 1933119.9 | J95: 1933119.9
A96: АНДИЖОН ВИЛОЯТИ | B96: Андижон филиали | C96: Ko'tardi | D96: Кр-99033888-4 | E96: SULTONOVA MUXARRAMXON YAKUBJONOVNA | F96: 998938172205 SMS O’ZI, 998947761538 SMS O’GLI, 998914889988 SMS JIYANI BOBUR, 988934259689 SMS O’G’LI, +998938172205 SMS O’ZI, 998509706498 SMS O’G’LI, 998934259689 SMS O’G’LI, | G96: ANDIJON VILOYATI ASAKA TUMANI DO’STLIK MFY ISLOMOBOD KO’CHASI 4- TOR 3-UY | H96: 3 | I96: 1907355.2 | K96: 15 ga tolaydi
A97: АНДИЖОН ВИЛОЯТИ | B97: Андижон филиали | C97: Ko'tardi | D97: Кр-99044378-2 | E97: SHOKIROV NURULLO AXMADULLAYEVICH | F97: +998914912216 SMS O’ZI, 998770387887 SMS QIZI tel qilinmasin, 998779630238 SMS AYOLI , 998931144480 SMS O’G’LI, | G97: АНДИЖОН ВИЛОЯТИ АНДИЖОН ШАХРИ МАДАНИЯТ МФЙ, Т.КЕЛДИЕВ, uy:102 | H97: 3 | I97: 1891511.9 | K97: kelasi hafta hal qiladi
A98: АНДИЖОН ВИЛОЯТИ | B98: Андижон филиали | C98: Ko'tardi | D98: Кр-99028633-2 | E98: XOLMATOV DONIYORBEK NABIJONOVICH | F98: 99-153-13-75 SMS O'ZI begona , 93-241-56-41 SMS AYOLI, 95-107-44-45 SMS OGLI, 95-991-96-60 SMS AKASI, +998991717513 SMS O’ZI, 998501703355 SMS O’G’LI, 998932415641 SMS AYOLI, 998959919660 SMS AKASI, | G98: Андижанская область, Алтынкульский район, Шарк юлдузи МСГ, ул. Улугбек, дом 384 | H98: 3 | I98: 1867599.8 | K98: kdushanba kuni yopadi
A99: АНДИЖОН ВИЛОЯТИ | B99: Андижон филиали | C99: Ko'tardi | D99: Кр-99004621-4 | E99: NADIROV MURODJON BAXRAMJON O’G’LI | F99: 90-543-11-01 SMS, 99-327-66-67 sms танимийди, 90-528-19-14 SMS TANIMASAKAN , 91-175-12-12 SMS ortogi, +998905431101 SMS O’ZI, 998887838780 SMS AKASI, 998946398780 SMS JIYANI ASADBEK, 998977268780 SMS UKASI, | G99: Саноат МФЙ, А.Йулдошев 1 тор кучаси, 37-уй | H99: 3 | I99: 1691247 | K99: 17 kuni tolaydi ortogi tolab beryapti ozi kasal avarya bolgan
A100: АНДИЖОН ВИЛОЯТИ | B100: Андижон филиали | C100: Ko'tardi | D100: Кр-99041191-1 | E100: SHOXINAZAROV ABDULLOH AZIZBEK O’G’LI | F100: +998880662277 SMS O’ZI, 998881005751 SMS ONASI, 998931005751 SMS DADASI, 998970272127 SMS DO’STI MUXAMMADSOLIQ, | G100: Экин тикин МФЙ, Шафтолизор кучаси, 252-уй | H100: 3 | I100: 1572715.4 | K100: 20 ga tolab beradi
A101: АНДИЖОН ВИЛОЯТИ | B101: Андижон филиали | C101: Ko'tardi | D101: Кр-99030503-1 | E101: ERGASHEV ZIYOIDDIN GULAMOVICH | F101: 74-226-03-32 SMS UY, 88-964-63-03 SMS JIYANI, 998937807979 SMS new ozi , | G101: ANDIJON VILOYATI ANDIJON SHAHARANDIJON MFY KZU 13 KO’CHASI 1-UY 54-XONADON | H101: 1 | I101: 1404736.9 | K101: 15 gacha tolaydi
A102: АНДИЖОН ВИЛОЯТИ | B102: Андижон филиали | C102: Ko'tardi | D102: Кр-99040518-3 | E102: ERMATOV RAFUK SADIKOVICH | F102: 998958722721 SMS OZI, 998950441777 SMS AYOLI, 998950361777 SMS QIZI, +998958722721 SMS O’ZI, | G102: ANDIJON VILOYATI ANDIJON SHAHAR O’ZBEKISTON MFY, TUKAYEVA KO’CHASI, 51-UY | H102: 3 | I102: 1394151.6 | K102: kelasi hafta chorshanba kuni
A103: АНДИЖОН ВИЛОЯТИ | B103: Андижон филиали | C103: Ko'tardi | D103: Кр-99041939-1 | E103: TEMIROVA SOXIBAXON OTAQO’ZIYEVNA | F103: +998772332063 SMS O’ZI, 998932440758 SMS XO’JAYNI, 998932691121 SMS NEVARASI, 998937615500 SMS O’G’LI, | G103: АНДИЖОН ВИЛОЯТИ БАЛИКЧИ ТУМАНИ ЧАРОҒОН МФЙ, ХАМСА КЎЧАСИ, uy:63 | H103: 3 | I103: 1388566.8 | K103: shu hafta hal qiladi
A104: АНДИЖОН ВИЛОЯТИ | B104: Андижон филиали | C104: Ko'tardi | D104: Кр-99044378-1 | E104: SHOKIROV NURULLO AXMADULLAYEVICH | F104: +998914912216 SMS O’ZI, 998770387887 SMS QIZI tel qilinmasin, 998779630238 SMS AYOLI , 998931144480 SMS O’G’LI, | G104: АНДИЖОН ВИЛОЯТИ АНДИЖОН ШАХРИ МАДАНИЯТ МФЙ, Т.КЕЛДИЕВ, uy:102 | H104: 3 | I104: 1356087.5 | K104: shanba kuni tolaydi
A105: АНДИЖОН ВИЛОЯТИ | B105: Андижон филиали | C105: Ko'tardi | D105: Кр-99040442-1 | E105: ABDULLAYEV XOJIAKBAR KOZIMJON O’G’LI | F105: +998886861313 SMS O’ZI, 998882252727 SMS AKASI, 998882495588 SMS KELINOYISI, 998889682727 SMS ONASI, | G105: Андижанская область, Андижон тумани, Гузар МСГ, ул. Пиллакаш, дом 34 | H105: 3 | I105: 1246306.6 | K105: kelasi hafta hal qiladi
A106: АНДИЖОН ВИЛОЯТИ | B106: Андижон филиали | C106: Оплатил дозвон | D106: Кр-99057395-3 | E106: SOBIROV AXMADULLOX MUXAMMADJON O’G’LI | F106: 998979712424 SMS UZI, 998887527779 AKASI, 998884104045 SMS KELNOYISI, 998972040525 SMS DADASI, +998979712424 SMS O’ZI, 998942493838 SMS AKASI, | G106: ANDIJON VILOYATI OLTINKO’L TUMANI CHO’NTAK MFY, MUSTAQILLIK KO’CHASI 227-UY | H106: 3 | I106: 1240770 | J106: 1240770
A107: АНДИЖОН ВИЛОЯТИ | B107: Андижон филиали | C107: Ko'tardi | D107: Кр-99027653-1 | E107: G’ANIYEV MARDONBEK DILMUROD O’G’LI | F107: 97-834-27-17 SMS O'ZI, 99-402-73-17 SMS ZALOGADATEL, 99-494-13-38 SMS KELINOYISI, 91-481-17-11 SMS DO’STI Begona , | G107: ANDIJON VILOYATI MARXAMAT TUMANI NAVRO’Z MFY CHILONZOR KO’CHASI 114-UY | H107: 3 | I107: 784965.29 | K107: zologatel bn gaplashdim ozi rusda ekan 15 kuni yopadi
A108: АНДИЖОН ВИЛОЯТИ | B108: Андижон филиали | C108: Ko'tardi | D108: Кр-99041539-2 | E108: SHERALIYEV SARDORBEK SODIQJON O’G’LI | F108: 998914845776 SMS OZI, 998996325251 SMS AYOLI, 998992425251 SMS ONASI Begona, +998914845776 Primary phone from road24, 998948642717 SMS O’ZI2, | G108: Андижон вилояти Андижон шахар Бунёдкор (9-сон) МФЙ, Қўш ариқ дахаси, 46-уй, 15-хонадон | H108: 3 | I108: 743423.15 | K108: 15 gacha tolaydi
A109: АНДИЖОН ВИЛОЯТИ | B109: Андижон филиали | C109: Ko'tardi | D109: Кр-99040426-1 | E109: ASHUROV XAYDARJON TOXIROVICH | F109: +998943850661 SMS O’ZI, 998332475047 SMS OPASI, 998906212128 SMS JIYANI, 998952470047 SMS JIYANI, 998906212128 tulovchisi, 998952470047 tulovchisi, | G109: ИСЛОМОБОД МФЙ, НУРЛИ ДИЁР КЎЧАСИ, uy:Р/С | H109: 3 | I109: 441713.97 | K109: 1-2 kunda hal qiladi
A110: АНДИЖОН ВИЛОЯТИ | B110: Андижон филиали | C110: Ko'tardi | D110: Кр-99027968-3 | E110: MAMADJANOV NOZIMJON ODILJANOVICH | F110: 99 308-73-75 OZI, 88-991-73-75 SMS O'ZI2, 88-324-10-33 SMS AYOLI, 91-290-02-72 SMS AKASI, +998993087375 SMS O’ZI, 998883241033 SMS O’ZI2, 998912900272 SMS AKASI, | G110: ANDIJON VILOYATI OLTINKO’L TUMANI DALVARZIN MFY DALVARZIN KO’CHASI 295-UY | H110: 3 | I110: 428677.9 | K110: kecha bittasini toladi shu hafta hammasini hal qiladi
A111: АНДИЖОН ВИЛОЯТИ | B111: Андижон филиали | C111: Ko'tardi | D111: Кр-99028354-1 | E111: QUVVATOV SARDORBEK RUSTAMBEKOVICH | F111: 99-636-90-00 SMS O'ZI, 95-025-72-03 SMS AMAKISI, 99-905-41-51 SMS XOLASI, 94-905-26-50 SMS JIYANI begana , 998993937057 SMS Klenti 2 nomeri, | G111: ANDIJON VILOYATI O’LTINKO’L TUMANI XONDI BOG’I MFY MASH’AL KO’CHASI 44-UY | H111: 2 | I111: 344313.66 | K111: qoshnisi oldi kechga aloqaga chiqib nomerini olib beradi ekan
A112: АНДИЖОН ВИЛОЯТИ | B112: Андижон филиали | C112: Ko'tardi | D112: Кр-99057367-2 | E112: ERGASHEVA DILBARXON XXX | F112: 998955529082 SMS O’ZI TO’LOVCHI, 998935483685 SMS AYOLI, 998950107819 SMS OGLI, 998914993298 SMS QIZI, | G112: ANDIJON VILOYATI BULOQBOSHI TUMANI UCHKO’CHA MFY PESHQADAM KO’CHASI 6-UY | H112: 3 | I112: 248119 | K112: 20 gacha hal qiladi
A113: БУХОРО ВИЛОЯТИ | B113: BOSH OFIS | C113: Обещали | D113: Кр-99039770-2 | E113: SAFAROV SANJAR ADIZ O’G’LI | F113: 998912403939 SMS OZI TO'LOVCHI SHUNGA TEL QILINSIN, 998935133314 SMS AMAKISI, 998918225456 SMS OTASI, 998942432520 SMS ONASI BEGONA , 998500766902 SMS ONASI, | G113: BUXORO VILOYATI BUXORO TUMANI GULSHANOBOD MFY LEYLAK QISHLOG’I 51-UY | H113: 3 | I113: 770472.71 | K113: BUGUNGA | 886
A114: БУХОРО ВИЛОЯТИ | B114: BOSH OFIS | C114: Обещали | D114: Кр-99035259-2 | E114: QODIROVA SHAHINABONU SHAMSIDDIN QIZI | F114: 998902274567 SMS ERI, 998934274567 SMS O’ZI, 998992629989 SMS UKASI бегона , 998883099877 SMS DO’STI, 998944274567 NEW ERI, | G114: BUXORO VILOYATI ROMITAN TUMANI BOG'CHA MFY, BOG'CHA q-q, 138-UY | H114: 3 | I114: 533660.83 | K114: BUGUNGA | 575
A115: БУХОРО ВИЛОЯТИ | B115: SUPER BRANCH | C115: Обещали | D115: Кр-99040567-1 | E115: ACHILOV BOBIR BURONOVICH | F115: 998505155499 SMS ONASI, 998931385554 SMS OGLI, 998936205499 SMS OZI, | G115: BUXORO VILOYATI, BUXORO SHAHAR, MUHAMMAD NARSHAXIY MFY, TOJI KARAYEV KO'CHASI, 86-UY | H115: 185 | I115: 28878875 | K115: 9CHIDA TO'LEMAN DEDILA | 1048
A116: БУХОРО ВИЛОЯТИ | B116: SUPER BRANCH | C116: Обещали | D116: Кр-99063363-1 | E116: KOMILOVA ZEBO NURIDDINOVNA | F116: 998995031288 OZI, 998773127040 JIYANI, 998998621288 ONASI, 998770900005 DOSTI, | G116: BUXORO VILOYATI QORAKUL TUMANI XOJAKON MFY XUNARMANDLAR KO’CHASI 86-UY | H116: 3 | I116: 8915367.8 | K116: TOSHKENTDA WU YERGA KELIB TO;LAYDI 15CHIDA | 2063
A117: БУХОРО ВИЛОЯТИ | B117: SUPER BRANCH | C117: Обещали | D117: Кр-99062671-3 | E117: XAYITOV TO’YMUROT ABDIRAIMOV | F117: 998873310787 SMS NEVARASI, 998889660300 SMS UY, 998941260300 SMS O’ZI, 998997540707 SMS O’G’LI, | G117: BUXORO VILOYATI PASHMON MFY PASHMON KO’CHASI 40-UY | H117: 3 | I117: 8123900.8 | K117: FILIALGA BORDI GAPLASHYABDI BUGUNGA TO'LOV QILIB BERADI EKAN | 1852
A118: БУХОРО ВИЛОЯТИ | B118: SUPER BRANCH | C118: Обещали | D118: Кр-99059934-1 | E118: BOMUROTOVA HALIMA SHOMUROTOVNA | F118: +998937243083 SMS O’ZI begona, 998552258020 SMS O’G’LI, 998943201112 SMS JIYANI, 998996858020 SMS O’G’LI, 998996858020 SMS tulovchi, 998937243083 , | G118: BUXORO VILOYATI CHANDIR MFY, CHELONG’I QISHLOG’I, 101-UY | H118: 6 | I118: 5342203.2 | K118: 8020 BUGUN KECHGACHA TO'LEMAN DEDILA | 1738
A119: БУХОРО ВИЛОЯТИ | B119: SUPER BRANCH | C119: Обещали | D119: Кр-99057401-1 | E119: NASRULLAYEVA GULNORA SAYFULLAYEVNA | F119: 998991338646 SMS UZI, 998992971131 SMS OGLI, 998990799421 SMS KELINI, 998999441525 sms qizi, | G119: BUXORO VILOYATI, JONDOR TUMANI, CHORZONA MFY, CHORZONA KO'CHASI, 18B-UY, 1-KORPUS. | I119: 4139083.3 | K119: PULI KELISHINI KUTYABDI EKAN KELISHI BN KARTAGA TASHAB BERADI EKAN O'G'LI QISMAN | 1641
A120: БУХОРО ВИЛОЯТИ | B120: SUPER BRANCH | C120: Обещали | D120: Кр-99033022-1 | E120: ASKAROV SHOHBOZ ULUG’BEKOVICH | F120: 998944219181 SMS OIZ, 998796441812 SMS OZI 2, 998931971731 SMS AYOLI, | G120: TOSHKENT SHAHAR, YANGIHAYOT TUMANI, YANGI DARXON MFY, NAVRO'Z KOCHASI 16-UY | H120: 3 | I120: 3126925.1 | K120: 15KUNI TO'LOV QILAMAN OYLIGIMDAN DEDI | 462
A121: БУХОРО ВИЛОЯТИ | B121: SUPER BRANCH | C121: Оплатил дозвон | D121: Кр-99018891-5 | E121: FAXILLOYEVA MOXINUR FOZILOVNA | F121: 97-306-16-10 SMS OZI, 90-513-05-03 SMS ERI BEGONA , 97-854-75-48 SMS QAYNONA, 91-411-91-88 SMS QAYNOTA, 50-578-16-10 SMS UZI2, | G121: BUXORO VILOYATI BUXORO TUMANI NOVMETAN QFY | H121: 3 | I121: 2655794.9 | J121: 2655794.9 | K121: BUGUN 2SOATDA | 98
A122: БУХОРО ВИЛОЯТИ | B122: SUPER BRANCH | C122: Обещали | D122: Кр-99019690-5 | E122: HAYDAROV FURQAT RAXMATILLOYEVICH | F122: 97-488-07-66 SMS O'ZI, 88-301-90-93 SMS AKASI, 97-296-06-93 SMS UY, 93-841-53-50 SMS AYOLI, 998505999203 SMS O'ZI2, | G122: BUXORO VILOYAT BUXORO SHAHRI BESHKAPPA KO'CHASI 106 UY | H122: 2 | I122: 2149549.6 | K122: BUGUNGA VADA BERGAN | 106
A123: БУХОРО ВИЛОЯТИ | B123: SUPER BRANCH | C123: Обещали | D123: Кр-99041320-3 | E123: SHODIYEV ULUG’BEK SALIMOVICH | F123: +998914431901 sms o’zi, 998907119935 sms onasi, 998912408206 sms ayoli, 998914471901 sms o’zi 2, | G123: Бухарская область, Гиждуванский район, Соктари МСГ, Соктари, дом 239 | H123: 3 | I123: 2080184.4 | K123: XOTINI BN GAPLASHDIM ERTAGA PULI TUSHADI EKAN TASHAB BERADILA DEDI MALAKA OSHIRISHDA EKAN | 1144
A124: БУХОРО ВИЛОЯТИ | B124: SUPER BRANCH | C124: Обещали | D124: Кр-99037525-1 | E124: ULMASOV RAVSHAN SANJAR O’G’LI | F124: 998940800113 SMS UZI2, 998941274505 SMS UZI O'ZIMIZDA ISHLAYDI , | G124: SHOFIRKON TUMANI | H124: 3 | I124: 1989716.3 | K124: 10KUNI TO'LEMAN DEDILA | 722
A125: БУХОРО ВИЛОЯТИ | B125: SUPER BRANCH | C125: Обещали | D125: Кр-99057620-1 | E125: SADRIDDINOV SAVRIDDIN HUSNIDDIN O’G’LI | F125: 998997027515 SMS UZI, 998906367515 SMS OTASI, 998997077515 SMS ONASI, 998918087515 SMS AKASI, | G125: BUXORO VILOYATI VOBKENT TUMANI KO'LXATIB MFY, NAVOIY KO'CHASI, 4-UY | H125: 3 | I125: 1763856.4 | K125: 20 KUNI TO'LEMAN DEDI DADASI | 1665
A126: БУХОРО ВИЛОЯТИ | B126: SUPER BRANCH | C126: Обещали | D126: Кр-99039770-1 | E126: SAFAROV SANJAR ADIZ O’G’LI | F126: 998912403939 SMS OZI TO'LOVCHI SHUNGA TEL QILINSIN, 998935133314 SMS AMAKISI, 998918225456 SMS OTASI, 998942432520 SMS ONASI BEGONA , 998500766902 SMS ONASI, | G126: BUXORO VILOYATI BUXORO TUMANI GULSHANOBOD MFY LEYLAK QISHLOG’I 51-UY | H126: 3 | I126: 1756556.4 | K126: BUGUNGA | 885
A127: БУХОРО ВИЛОЯТИ | B127: SUPER BRANCH | C127: Обещали | D127: Кр-99047434-2 | E127: UMRZOQOV FAXRIDDIN AXMEDJONOVICH | F127: 998959754272 O`ZI, 998941220757 AYOLI, 998945457562 DO`STI, 998959754272 uzi, 998941220757 ayoli, 998945457562 dosti, | G127: Бухоро шахар коракул тумани Мустакиллик 50 уй | H127: 3 | I127: 1525958.9 | K127: 10 OYLIKDAN FILIALGA TO'LEMAN TELEFON QILISHEZ WARTMAS UNGACHA DEDILA | 1382
A128: БУХОРО ВИЛОЯТИ | B128: SUPER BRANCH | C128: Обещали | D128: Кр-99019690-6 | E128: HAYDAROV FURQAT RAXMATILLOYEVICH | F128: 97-488-07-66 SMS O'ZI, 88-301-90-93 SMS AKASI, 97-296-06-93 SMS UY, 93-841-53-50 SMS AYOLI, 998505999203 SMS O'ZI2, | G128: BUXORO VILOYAT BUXORO SHAHRI BESHKAPPA KO'CHASI 106 UY | H128: 3 | I128: 1119754.7 | K128: BUGUNGA VADA BERGAN | 107
A129: БУХОРО ВИЛОЯТИ | B129: SUPER BRANCH | C129: Обещали | D129: Кр-99049211-1 | E129: ADIZOV AZAMAT SHOYIMOVICH | F129: 998940642993 SMS JIYANI begona , 998942218131 SMS O’ZI, 998978055824 SMS UKASI, 998999767786 SMS AYOLI, 998914412047 SMS OTASI, | G129: GULISTON, DOM 56 | H129: 3 | I129: 713214.59 | K129: ERTAGA BUXOROGA QAYTSA TO'LOV QILADI EKAN | 1438
A130: БУХОРО ВИЛОЯТИ | B130: SUPER BRANCH | C130: Оплатил дозвон | D130: Кр-99041395-2 | E130: G’AYBULLOYEVA LAYLO ABDULLO QIZI | F130: 998950856644 SMS ERI, 998970153002 SMS ERI 2, 998955250119 SMS ERI2, 998400722322 SMS OZI2, 998997015300 SMS ERI NEW, | G130: TOSHKENT SHAHAR YANGIXAYOT TUMANI YANGIDARXON MFY, 8-UY, 36-XONADON | I130: 321272.7 | J130: 321272.7 | K130: KO'TARMAYABDI TELEGRAMDAN YOZDIM BUGUN TO'LASHI KERAK | 1161
A131: БУХОРО ВИЛОЯТИ | B131: Бухоро филиали | C131: Обещали | D131: Кр-99063230-2 | E131: NAVRUZOV SHUXRAT NARZULLOYEVICH | F131: 998931591550 SMS AYOLI, 998936547339 SMS DO’STI, 998940994344 SMS O’ZI, | G131: Бухарская область, Ромитанский район, Шурабад МСГ, Кантале, дом 6 | H131: 6 | I131: 12608581 | K131: O'RTOG'I BN GAPLASHDIM OZI TEL QILADI KLENT BUGUNGA VADA BERGAN ERTAGA | 2036
A132: БУХОРО ВИЛОЯТИ | B132: Бухоро филиали | C132: Оплатил дозвон | D132: Кр-99063805-1 | E132: NASIROVA SANAVAR SHARIFDJANOVNA | F132: +998777630387 SMS O’ZI, 998909710400 SMS O’G’LI, 998996007310 SMS ERI, | G132: BUXORO VILOYATI BUXORO SHAHAR YANGIOBOD MFY YANGIOBOD KO’CHASI 123-UY | H132: 3 | I132: 9936501.7 | J132: 9936501.7 | K132: 2192
A133: БУХОРО ВИЛОЯТИ | B133: Бухоро филиали | C133: Обещали | D133: Кр-99062712-3 | E133: SAFAROVA MASHHURA MUSTAFOYEVNA | F133: +998949157341 SMS O’ZI, 998502707707 SMS O’G’LI, 998938210222 SMS O’G’LI, 998991201874 SMS ERI, | G133: BUXORO VILOYAT BUXORO SHAHAR PRIDASGIR MFY NAVOIY SHOX KO’CHASI 15/1 19-UY | H133: 6 | I133: 8132303.3 | K133: 0222TO'LOVCHI DUWANBADA OYLIGIM TUWADI OWA PAYTI TO'LOV QILAMAN DEDILA | 1870
A134: БУХОРО ВИЛОЯТИ | B134: Бухоро филиали | C134: Обещали | D134: Кр-99063147-1 | E134: YUSUPOV TALGAT RAVILEVICH | F134: +998934589950 SMS O’ZI, 998504052350 SMS AYOLI, 998936202480 SMS QIZI, 998936560151 SMS ONASI, | G134: 5-СОН ГАФУР ГУЛОМ НОМЛИ МФЙ, ИФТИХОР КУЧАСИ, 32-UY | H134: 3 | I134: 4833153.3 | K134: 10CHIGA | 2016
A135: БУХОРО ВИЛОЯТИ | B135: Бухоро филиали | C135: Обещали | D135: Кр-99027605-1 | E135: BARATOVA MAXFUZA TOLIBOVNA | F135: 97-084-88-33 sms O'ZI, 97-080-66-33 sms ERI, 99-775-20-70 sms QAYNI UKASI, 91-441-67-61 sms JIYANI, | G135: BUXORO VILOYATI, KOGON TUMANI, ISTIQBOL MFY, QOTONG'I q-q, 46-UY. | H135: 6 | I135: 3631499.3 | K135: ERI KAPITAL BANKDAN TO'LEMAN DEDI QAYNONASI KO'TARDI TO'LEMIZ OYLIKDAN DEDI | 237
A136: БУХОРО ВИЛОЯТИ | B136: Бухоро филиали | C136: Обещали | D136: Кр-99035221-3 | E136: SHUKUROV YUNUS UMAROVICH | F136: 998990297718 SMS O’ZI, 998996751234 SMS AYOLI, 998992231806 SMS QAYNONASI, 998992947718 SMS ONASI, 998944743193 SMS TO'LOVCHI OPASI , | G136: Хужа Мушкин МФЙ, Алпомиш кучаси, 13/2-уй, 7-хонадон | H136: 3 | I136: 3369616.8 | K136: 944743193 BU OPASI 10KUNI TO'LAYDI | 573
...

Sheet Обещали
A1: ← Вернуться в отчёт
A2: Область | B2: Филиал | C2: Группа | D2: Код клиента | E2: Клиент | F2: Номер телефона | G2: Адрес | H2: Кол-во просроченных дней | I2: Итого просрочка | J2: Оплата | K2: Izoh
A3: АНДИЖОН ВИЛОЯТИ | B3: BOSH OFIS | C3: Обещали | D3: Кр-99041164-1 | E3: MAXKAMBOYEV SALIMJON JUMABOYEVICH | F3: 998937768805 SMS OZI, 998979768805 SMS AYOLI, 998940738805 SMS ONASI, 998944428589 SMS UAKSI, | G3: ANDIJON VILOYATI XO’JAOBOD TUMANI XIDRSHA MFY, BOG’BONLAR KO’CHASI 64-UY | H3: 3 | I3: 3102788.1 | K3: bugun hal qiladi
A4: АНДИЖОН ВИЛОЯТИ | B4: SUPER BRANCH | C4: Обещали | D4: Кр-99033504-1 | E4: NIYAZOV XAYBATULLA BURXANOVICH | F4: 998979926505 SMS OZI, 998501881794 SMS O'G'LI, 998951679511 SMS KELINI, 998507199794 SMS QIZI, | G4: ANDIJON VILOYATI ASAKA TUMANI QADRIYAT MFY HUMO KO’CHASI 39-UY 28- XONADON | H4: 3 | I4: 5646163.7 | K4: bugun qisman tolaydi qolganini ertaga tolaydi
A5: АНДИЖОН ВИЛОЯТИ | B5: Андижон филиали | C5: Обещали | D5: Кр-99012626-3 | E5: ISMOILOVA MUHAYYOXON RUSTAMOVNA | F5: 93-394-73-75 SMS OZI, 99-818-79-36 sms, +998938020802 SMS O’GLI, 998933132236 SMS QIZI, 998933947375 SMS ONASI, 998993132236 SMS QIZI, | G5: ANDIJON VILOYATI QO’RG’ONTEPA TUMANI QORASUV SHAHAR M.ULUG’BEK MFY KAMALAK KO’CHASI 7-UY | H5: 3 | I5: 2788273.9 | K5: erta tolaydi
A6: БУХОРО ВИЛОЯТИ | B6: BOSH OFIS | C6: Обещали | D6: Кр-99039770-2 | E6: SAFAROV SANJAR ADIZ O’G’LI | F6: 998912403939 SMS OZI TO'LOVCHI SHUNGA TEL QILINSIN, 998935133314 SMS AMAKISI, 998918225456 SMS OTASI, 998942432520 SMS ONASI BEGONA , 998500766902 SMS ONASI, | G6: BUXORO VILOYATI BUXORO TUMANI GULSHANOBOD MFY LEYLAK QISHLOG’I 51-UY | H6: 3 | I6: 770472.71 | K6: BUGUNGA | 886
A7: БУХОРО ВИЛОЯТИ | B7: BOSH OFIS | C7: Обещали | D7: Кр-99035259-2 | E7: QODIROVA SHAHINABONU SHAMSIDDIN QIZI | F7: 998902274567 SMS ERI, 998934274567 SMS O’ZI, 998992629989 SMS UKASI бегона , 998883099877 SMS DO’STI, 998944274567 NEW ERI, | G7: BUXORO VILOYATI ROMITAN TUMANI BOG'CHA MFY, BOG'CHA q-q, 138-UY | H7: 3 | I7: 533660.83 | K7: BUGUNGA | 575
A8: БУХОРО ВИЛОЯТИ | B8: SUPER BRANCH | C8: Обещали | D8: Кр-99040567-1 | E8: ACHILOV BOBIR BURONOVICH | F8: 998505155499 SMS ONASI, 998931385554 SMS OGLI, 998936205499 SMS OZI, | G8: BUXORO VILOYATI, BUXORO SHAHAR, MUHAMMAD NARSHAXIY MFY, TOJI KARAYEV KO'CHASI, 86-UY | H8: 185 | I8: 28878875 | K8: 9CHIDA TO'LEMAN DEDILA | 1048
A9: БУХОРО ВИЛОЯТИ | B9: SUPER BRANCH | C9: Обещали | D9: Кр-99063363-1 | E9: KOMILOVA ZEBO NURIDDINOVNA | F9: 998995031288 OZI, 998773127040 JIYANI, 998998621288 ONASI, 998770900005 DOSTI, | G9: BUXORO VILOYATI QORAKUL TUMANI XOJAKON MFY XUNARMANDLAR KO’CHASI 86-UY | H9: 3 | I9: 8915367.8 | K9: TOSHKENTDA WU YERGA KELIB TO;LAYDI 15CHIDA | 2063
A10: БУХОРО ВИЛОЯТИ | B10: SUPER BRANCH | C10: Обещали | D10: Кр-99062671-3 | E10: XAYITOV TO’YMUROT ABDIRAIMOV | F10: 998873310787 SMS NEVARASI, 998889660300 SMS UY, 998941260300 SMS O’ZI, 998997540707 SMS O’G’LI, | G10: BUXORO VILOYATI PASHMON MFY PASHMON KO’CHASI 40-UY | H10: 3 | I10: 8123900.8 | K10: FILIALGA BORDI GAPLASHYABDI BUGUNGA TO'LOV QILIB BERADI EKAN | 1852
A11: БУХОРО ВИЛОЯТИ | B11: SUPER BRANCH | C11: Обещали | D11: Кр-99059934-1 | E11: BOMUROTOVA HALIMA SHOMUROTOVNA | F11: +998937243083 SMS O’ZI begona, 998552258020 SMS O’G’LI, 998943201112 SMS JIYANI, 998996858020 SMS O’G’LI, 998996858020 SMS tulovchi, 998937243083 , | G11: BUXORO VILOYATI CHANDIR MFY, CHELONG’I QISHLOG’I, 101-UY | H11: 6 | I11: 5342203.2 | K11: 8020 BUGUN KECHGACHA TO'LEMAN DEDILA | 1738
A12: БУХОРО ВИЛОЯТИ | B12: SUPER BRANCH | C12: Обещали | D12: Кр-99057401-1 | E12: NASRULLAYEVA GULNORA SAYFULLAYEVNA | F12: 998991338646 SMS UZI, 998992971131 SMS OGLI, 998990799421 SMS KELINI, 998999441525 sms qizi, | G12: BUXORO VILOYATI, JONDOR TUMANI, CHORZONA MFY, CHORZONA KO'CHASI, 18B-UY, 1-KORPUS. | I12: 4139083.3 | K12: PULI KELISHINI KUTYABDI EKAN KELISHI BN KARTAGA TASHAB BERADI EKAN O'G'LI QISMAN | 1641
A13: БУХОРО ВИЛОЯТИ | B13: SUPER BRANCH | C13: Обещали | D13: Кр-99033022-1 | E13: ASKAROV SHOHBOZ ULUG’BEKOVICH | F13: 998944219181 SMS OIZ, 998796441812 SMS OZI 2, 998931971731 SMS AYOLI, | G13: TOSHKENT SHAHAR, YANGIHAYOT TUMANI, YANGI DARXON MFY, NAVRO'Z KOCHASI 16-UY | H13: 3 | I13: 3126925.1 | K13: 15KUNI TO'LOV QILAMAN OYLIGIMDAN DEDI | 462
A14: БУХОРО ВИЛОЯТИ | B14: SUPER BRANCH | C14: Обещали | D14: Кр-99019690-5 | E14: HAYDAROV FURQAT RAXMATILLOYEVICH | F14: 97-488-07-66 SMS O'ZI, 88-301-90-93 SMS AKASI, 97-296-06-93 SMS UY, 93-841-53-50 SMS AYOLI, 998505999203 SMS O'ZI2, | G14: BUXORO VILOYAT BUXORO SHAHRI BESHKAPPA KO'CHASI 106 UY | H14: 2 | I14: 2149549.6 | K14: BUGUNGA VADA BERGAN | 106
A15: БУХОРО ВИЛОЯТИ | B15: SUPER BRANCH | C15: Обещали | D15: Кр-99041320-3 | E15: SHODIYEV ULUG’BEK SALIMOVICH | F15: +998914431901 sms o’zi, 998907119935 sms onasi, 998912408206 sms ayoli, 998914471901 sms o’zi 2, | G15: Бухарская область, Гиждуванский район, Соктари МСГ, Соктари, дом 239 | H15: 3 | I15: 2080184.4 | K15: XOTINI BN GAPLASHDIM ERTAGA PULI TUSHADI EKAN TASHAB BERADILA DEDI MALAKA OSHIRISHDA EKAN | 1144
A16: БУХОРО ВИЛОЯТИ | B16: SUPER BRANCH | C16: Обещали | D16: Кр-99037525-1 | E16: ULMASOV RAVSHAN SANJAR O’G’LI | F16: 998940800113 SMS UZI2, 998941274505 SMS UZI O'ZIMIZDA ISHLAYDI , | G16: SHOFIRKON TUMANI | H16: 3 | I16: 1989716.3 | K16: 10KUNI TO'LEMAN DEDILA | 722
A17: БУХОРО ВИЛОЯТИ | B17: SUPER BRANCH | C17: Обещали | D17: Кр-99057620-1 | E17: SADRIDDINOV SAVRIDDIN HUSNIDDIN O’G’LI | F17: 998997027515 SMS UZI, 998906367515 SMS OTASI, 998997077515 SMS ONASI, 998918087515 SMS AKASI, | G17: BUXORO VILOYATI VOBKENT TUMANI KO'LXATIB MFY, NAVOIY KO'CHASI, 4-UY | H17: 3 | I17: 1763856.4 | K17: 20 KUNI TO'LEMAN DEDI DADASI | 1665
A18: БУХОРО ВИЛОЯТИ | B18: SUPER BRANCH | C18: Обещали | D18: Кр-99039770-1 | E18: SAFAROV SANJAR ADIZ O’G’LI | F18: 998912403939 SMS OZI TO'LOVCHI SHUNGA TEL QILINSIN, 998935133314 SMS AMAKISI, 998918225456 SMS OTASI, 998942432520 SMS ONASI BEGONA , 998500766902 SMS ONASI, | G18: BUXORO VILOYATI BUXORO TUMANI GULSHANOBOD MFY LEYLAK QISHLOG’I 51-UY | H18: 3 | I18: 1756556.4 | K18: BUGUNGA | 885
A19: БУХОРО ВИЛОЯТИ | B19: SUPER BRANCH | C19: Обещали | D19: Кр-99047434-2 | E19: UMRZOQOV FAXRIDDIN AXMEDJONOVICH | F19: 998959754272 O`ZI, 998941220757 AYOLI, 998945457562 DO`STI, 998959754272 uzi, 998941220757 ayoli, 998945457562 dosti, | G19: Бухоро шахар коракул тумани Мустакиллик 50 уй | H19: 3 | I19: 1525958.9 | K19: 10 OYLIKDAN FILIALGA TO'LEMAN TELEFON QILISHEZ WARTMAS UNGACHA DEDILA | 1382
A20: БУХОРО ВИЛОЯТИ | B20: SUPER BRANCH | C20: Обещали | D20: Кр-99019690-6 | E20: HAYDAROV FURQAT RAXMATILLOYEVICH | F20: 97-488-07-66 SMS O'ZI, 88-301-90-93 SMS AKASI, 97-296-06-93 SMS UY, 93-841-53-50 SMS AYOLI, 998505999203 SMS O'ZI2, | G20: BUXORO VILOYAT BUXORO SHAHRI BESHKAPPA KO'CHASI 106 UY | H20: 3 | I20: 1119754.7 | K20: BUGUNGA VADA BERGAN | 107
A21: БУХОРО ВИЛОЯТИ | B21: SUPER BRANCH | C21: Обещали | D21: Кр-99049211-1 | E21: ADIZOV AZAMAT SHOYIMOVICH | F21: 998940642993 SMS JIYANI begona , 998942218131 SMS O’ZI, 998978055824 SMS UKASI, 998999767786 SMS AYOLI, 998914412047 SMS OTASI, | G21: GULISTON, DOM 56 | H21: 3 | I21: 713214.59 | K21: ERTAGA BUXOROGA QAYTSA TO'LOV QILADI EKAN | 1438
A22: БУХОРО ВИЛОЯТИ | B22: Бухоро филиали | C22: Обещали | D22: Кр-99063230-2 | E22: NAVRUZOV SHUXRAT NARZULLOYEVICH | F22: 998931591550 SMS AYOLI, 998936547339 SMS DO’STI, 998940994344 SMS O’ZI, | G22: Бухарская область, Ромитанский район, Шурабад МСГ, Кантале, дом 6 | H22: 6 | I22: 12608581 | K22: O'RTOG'I BN GAPLASHDIM OZI TEL QILADI KLENT BUGUNGA VADA BERGAN ERTAGA | 2036
A23: БУХОРО ВИЛОЯТИ | B23: Бухоро филиали | C23: Обещали | D23: Кр-99062712-3 | E23: SAFAROVA MASHHURA MUSTAFOYEVNA | F23: +998949157341 SMS O’ZI, 998502707707 SMS O’G’LI, 998938210222 SMS O’G’LI, 998991201874 SMS ERI, | G23: BUXORO VILOYAT BUXORO SHAHAR PRIDASGIR MFY NAVOIY SHOX KO’CHASI 15/1 19-UY | H23: 6 | I23: 8132303.3 | K23: 0222TO'LOVCHI DUWANBADA OYLIGIM TUWADI OWA PAYTI TO'LOV QILAMAN DEDILA | 1870
A24: БУХОРО ВИЛОЯТИ | B24: Бухоро филиали | C24: Обещали | D24: Кр-99063147-1 | E24: YUSUPOV TALGAT RAVILEVICH | F24: +998934589950 SMS O’ZI, 998504052350 SMS AYOLI, 998936202480 SMS QIZI, 998936560151 SMS ONASI, | G24: 5-СОН ГАФУР ГУЛОМ НОМЛИ МФЙ, ИФТИХОР КУЧАСИ, 32-UY | H24: 3 | I24: 4833153.3 | K24: 10CHIGA | 2016
... A51: ЖИЗЗАХ ВИЛОЯТИ | B51: SUPER BRANCH | C51: Обещали | D51: Кр-99045795-1 | E51: YULDASHEV ASATULLO TO’YCHIYEVICH | F51: 998945767778 SMS OZI, 998945141978 SMS AYOLI, 998971601711 SMS OGLI, | G51: JIZZAX VILOYATI ZOMIN TUMANI NURLIKENT MFY POLVONLAR KO'CHASI 25-UY | H51: 3 | I51: 6241634 | K51: wanbagaca tolaydi
A52: ЖИЗЗАХ ВИЛОЯТИ | B52: SUPER BRANCH | C52: Обещали | D52: Кр-99053193-1 | E52: TURAYEV OYBEK ULUGBEKOVICH | F52: 998905162754 SMS OZI, 998904868707 SMS AYOLI, 998990282014 SMS OGLI, +998905162754 , | G52: JIZZAX VILOYATI JIZZAX SHAHRI UCHARIQ MFY FIRDAVSIY KUCHASI 19-UY | I52: 6183054 | K52: oylik tuwgandan tolaydi wu hafta
A53: ЖИЗЗАХ ВИЛОЯТИ | B53: SUPER BRANCH | C53: Обещали | D53: Кр-99041938-2 | E53: MURODIMOV ALIJON YO’LDOSH O’G’LI | F53: 998881271595 SMS OZINI 2, 998977949990 SMS AKASI, 998995709128 SMS OZI, 998995719128 SMS AKASI 2, | G53: КУКБУЛОК КФЙ, КУКБУЛОК КФЙ, КИЗИЛТУТ КИШЛОГИ, uy:Р/С | H53: 3 | I53: 5914262.6 | K53: kecgaca tolaydi
A54: ЖИЗЗАХ ВИЛОЯТИ | B54: SUPER BRANCH | C54: Обещали | D54: Кр-99040233-1 | E54: BERDIYEVA MAVLYUDA INOMOVNA | F54: 998915691963 SMS OZI, 998905151229 SMS SINGLSI, 998905398865 SMS KELINI, | G54: JIZZAX VILOYATI JIZZAX SHAHRI DUSTLIK MFY DUSTLIK KUCHASI 11-UY | H54: 3 | I54: 4725308 | K54: kecgaca tolaydi
A55: ЖИЗЗАХ ВИЛОЯТИ | B55: SUPER BRANCH | C55: Обещали | D55: Кр-99028709-2 | E55: ABDUJABBOROV SARVAR ASLIDDIN O’G’LI | F55: 88-208-15-45 SMS O'ZI, 88-128-22-02 X SMS TULOVCHI , 88-296-26-29 SMS UZI , | G55: JIZZAX VILOYATI BAXMAL TUMANI O’RMONCHI QFY | H55: 3 | I55: 4452639.5 | K55: duwanbagaca tolaydi
A56: ЖИЗЗАХ ВИЛОЯТИ | B56: SUPER BRANCH | C56: Обещали | D56: Кр-99040359-1 | E56: KOMOLJONOV IXTIYOR BAXTIYOROVICH | F56: 998999434941 SMS OZI, 998194149412 SMS OZI2, 998901828688 SMS AYOLI, | G56: JIZZAX VILOYATI JIZZAX TUMANI ZIYOKOR MFY ABDUQAHHOR KUCHASI 42-UY | H56: 3 | I56: 4228019.9 | K56: ertaga tolaydi
A57: ЖИЗЗАХ ВИЛОЯТИ | B57: SUPER BRANCH | C57: Обещали | D57: Кр-99040635-1 | E57: JURAYEVA ZULAYXA LUTFULLAYEVNA | F57: 998915641958 SMS begona, 998938592525 SMS O`G`LI tolovchisi, 998943543086 SMS O`G`LI 2, 998931940082 SMS O`G`LI 3, 998943174556 SMS ONASI, 998932926008 Tolovchisini xotini, | G57: JIZZAX VILOYATI, DO’STLIK TUMANI, NAVRUZ MFY, IFTIXOR KUCHASI, 11-2 UY | H57: 3 | I57: 4102129.2
A58: ЖИЗЗАХ ВИЛОЯТИ | B58: SUPER BRANCH | C58: Обещали | D58: Кр-99063114-1 | E58: BOZOROV SAFARBOY XXX | F58: 998931775315 OZI, 998995544018 OGLI, 998933008159 OGLI, | G58: JIZZAX VILOYATI JIZZAX SHAHAR BUNYODKOR MFY QURUVCHILAR KUCHASI 1-UY | H58: 3 | I58: 4033438.1 | K58: 1 2 kunda tolaydi
A59: ЖИЗЗАХ ВИЛОЯТИ | B59: SUPER BRANCH | C59: Обещали | D59: Кр-99057340-1 | E59: SUYUNOVA UMIDA ILHOM QIZI | F59: 998995542023 SMS ERI, 998930913798 SMS UZI, 998943461045 SMS UY, 998901020807 SMS Akasi, | G59: JIZZAX VILOYATI MIRZACHO'L TUMANI IPAK YULI QFY YANGI XAYOT KUCHASI 29-UY | H59: 3 | I59: 3719528.4 | K59: 2 3 kunda tolaydi
A60: ЖИЗЗАХ ВИЛОЯТИ | B60: SUPER BRANCH | C60: Обещали | D60: Кр-99052995-1 | E60: JUMANOVA SHAYDO JONIQUL QIZI | F60: 998505100392 SMS ERI, 998933016150 SMS QAYNIONASI, | G60: JIZZAX VILOYATI SHAROF RASHIDOV TUMANI UMAR MAHALLASI KITOBXONLAR KUCHASI 59-UY | H60: 3 | I60: 3440681.4 | K60: 15gca tolaydi oylik kutyapti
A61: ЖИЗЗАХ ВИЛОЯТИ | B61: SUPER BRANCH | C61: Обещали | D61: Кр-99028709-3 | E61: ABDUJABBOROV SARVAR ASLIDDIN O’G’LI | F61: 88-208-15-45 SMS O'ZI, 88-128-22-02 X SMS TULOVCHI , 88-296-26-29 SMS UZI , | G61: JIZZAX VILOYATI BAXMAL TUMANI O’RMONCHI QFY | H61: 3 | I61: 3251991.1 | K61: duwanbagaca tolaydi
A62: ЖИЗЗАХ ВИЛОЯТИ | B62: SUPER BRANCH | C62: Обещали | D62: Кр-99039978-1 | E62: ABDUG’AFFOROV SHAHZOD FARXOD O’G’LI | F62: 998978467171 SMS OZI, 998970797177 SMS AYOLI, 998996860929 SMS UKASI, 998940131831 SMS JORASI, 998700459666 sms uzi, 998775240110 sms uzi, | G62: JIZZAX VILOYATI JIZZAX TUMANI QANGLI MFY MARHAMAT KUCHASI 92-UY | H62: 3 | I62: 3151021.8 | K62: eri cetda wu hafta tolaydi
A63: ЖИЗЗАХ ВИЛОЯТИ | B63: SUPER BRANCH | C63: Обещали | D63: Кр-99036491-1 | E63: XAYDAROVA KOMILA ZAYNIDDINOVNA | F63: 998973462688 SMS OZI , 998936507904 SMS AYOLI , 998944740513 SMS QIZI, 998338990215 SMS SINGLISI , 998943462688 SMS NEW, | G63: JIZZAX VILOYATI SH.RASHIDOV TUMANI SOVUNGARLIK MFY 11-UY | H63: 3 | I63: 2834476.3 | K63: ertaga tolaydi
A64: ЖИЗЗАХ ВИЛОЯТИ | B64: SUPER BRANCH | C64: Обещали | D64: Кр-99039288-1 | E64: YAKUBOV BUNYOD NEMATILLAYEVICH | F64: 998904878684 SMS OZI, 998886441986 SMS AYOLI, 998932988684 SMS OZI, 998773450986 SMS SINGLISI, | G64: JIZZAX VILOYATI DUSTLIK TUMANI MEVAZOR QFY LOLAZOR KUCHASI 35-UY | H64: 6 | I64: 2794702.6 | K64: kecgaca tolaydi
A65: ЖИЗЗАХ ВИЛОЯТИ | B65: SUPER BRANCH | C65: Обещали | D65: Кр-99057656-1 | E65: KASIMOVA LOLA NARBAYEVNA | F65: 998938238558 SMS UZI, 998934072545 SMS KUYOVI, 998941540825 SMS QIZI, | G65: JIZZAX VILOYATI G'ALLAOROL TUMANI OLIMLAR MFY LALMIKOR KUCHASI 41-UY | H65: 3 | I65: 2523823.7 | K65: 10gaca tolaydi
A66: ЖИЗЗАХ ВИЛОЯТИ | B66: SUPER BRANCH | C66: Обещали | D66: Кр-99039314-1 | E66: IZBOSAROV BUNYODBEK BEHZOD O’G’LI | F66: 998919400878 SMS UZI, 998886647070 SMS AKASI, 998991900011 SMS KATTA AKASI, 998996100011 SMS ADASI, | G66: JIZZAX VILOYATI PAXTAKOR TUMANI TOSHKENT MFY NURAFSHON KUCHASI 7/1-UY | H66: 3 | I66: 2452046.6 | K66: 15gaca tolaydi
A67: ЖИЗЗАХ ВИЛОЯТИ | B67: SUPER BRANCH | C67: Обещали | D67: Кр-99054993-1 | E67: ABDULLAYEV MUROD ABDUGANIYEVICH | F67: 998937227050 SMS UZI, 998976474656 SMS ONASI, 998880288020 SMS UKASSI, | G67: JIZZAX VILOYATI ZOMIN TUMANI OQTEPA MAHALLASI IQTISODIYOT KUCHASI 15-UY | H67: 3 | I67: 2162389.7 | K67: duwanbagaca tolaydi
A68: ЖИЗЗАХ ВИЛОЯТИ | B68: SUPER BRANCH | C68: Обещали | D68: Кр-99058348-1 | E68: KOBILOV OYBEKJON PULAT O’G’LI | F68: 998943410777 SMS OZI, 998930730033 SMS ZALOGATEL, 998932259206 SMS OPASI, 998880325577 SMS UYI, | G68: JIZZAX VILOYATI SHAROF RASHIDOV TUMANI ISTIQLOL MFY PAXTAKOR KUCHASI 98-UY | H68: 3 | I68: 2089493.9 | K68: bugun tolaydi
A69: ЖИЗЗАХ ВИЛОЯТИ | B69: SUPER BRANCH | C69: Обещали | D69: Кр-99052894-1 | E69: SUVONQULOV SHAXRIYOR MIRZABEK O’G’LI | F69: 998943079900 SMS OZI, 998932800094 SMS AKASI, 998938265665 SMS AKASI 2, 999839712506 SMS UKASI, | G69: JIZZAX VILOYATI SHAROF RASHIDOV TUMANI QANG'LI QFY NURAFSHON MFY OBOD KUCHASI 9-UY | H69: 3 | I69: 1856328.3 | K69: ertaga abetgaca tolaydi
... A72: ЖИЗЗАХ ВИЛОЯТИ | B72: SUPER BRANCH | C72: Обещали | D72: Кр-99058157-1 | E72: SHODMONQULOVA GULNORA BOSIMOVNA | F72: 998943401779 O`ZI, 998500512300 ERI, 998939291202 O`G`LI, | G72: ZOMIN TUMANI | H72: 3 | I72: 651259.32 | K72: bugun yo erta tolaydi
A73: ЖИЗЗАХ ВИЛОЯТИ | B73: SUPER BRANCH | C73: Обещали | D73: Кр-99028616-3 | E73: MALLAYEV SHUXRAT BOSIMOVICH | F73: 93-301-00-66 SMS O'ZI, 93-301-07-54 SMS AYOLI, 93-301-06-96 SMS SIN, 99-245-90-99 SMS SIN 2, 998945450550 Eldor ogli , 998992169079 tulovchi, 998997563446 tulovchi, | G73: JIZZAX VILOYATI JIZZAX TUMANI QANGLI MFY TARAQLI KUCHASI 13-UY | I73: 555763.05 | K73: wanbagaca tolaydi
A74: ЖИЗЗАХ ВИЛОЯТИ | B74: SUPER BRANCH | C74: Обещали | D74: Кр-99030864-2 | E74: MAMATQULOV UMIDJON XOLBO’TA O’G’LI | F74: 93-301-01-51 SMS O’ZI, 94-690-37-61 SMS ONASI, 93-386-96-92 SMS AYOLI, 95-828-82-90 SMS KELINOYISI, | G74: JIZZAX VILOYATI ZOMIN TUMANI CHORVADOR QFY 10-UY | H74: 3 | I74: 476428.65 | K74: ayoli iwdan keb tolaydi dedi
A75: ЖИЗЗАХ ВИЛОЯТИ | B75: Жиззах филиали | C75: Обещали | D75: Кр-99063548-4 | E75: XOLMATOV TOIR MAXKAMOVICH | F75: 998883290075 UZI, 998918949450 AKASI, 998993290075 UY, | G75: JIZZAXLIK KUCHASI 27-UY | H75: 3 | I75: 9330579.6 | K75: kecgaca tolaydi
A76: ЖИЗЗАХ ВИЛОЯТИ | B76: Жиззах филиали | C76: Обещали | D76: Кр-99028616-4 | E76: MALLAYEV SHUXRAT BOSIMOVICH | F76: 93-301-00-66 SMS O'ZI, 93-301-07-54 SMS AYOLI, 93-301-06-96 SMS SIN, 99-245-90-99 SMS SIN 2, 998945450550 Eldor ogli , 998992169079 tulovchi, 998997563446 tulovchi, | G76: JIZZAX VILOYATI JIZZAX TUMANI QANGLI MFY TARAQLI KUCHASI 13-UY | H76: 3 | I76: 6540577.8 | K76: wanbagaca tolaydi
A77: ЖИЗЗАХ ВИЛОЯТИ | B77: Жиззах филиали | C77: Обещали | D77: Кр-99033328-1 | E77: XOLBUTAYEV DILMUROD ABDUMALIKOVICH | F77: 998915680048 SMS O’ZI, 998994280048 SMS UKASI, 998990280048 SMS AYOLI BEGONA, 998900265356 SMS ONASI, | G77: JIZZAX VILOYATI ZOMIN TUMANI DASHTOBOD SHAXAR QORATEPA MFY SHIRIN KUCHASI | H77: 3 | I77: 6429679 | K77: erta kecgaca tolaydi
A78: ЖИЗЗАХ ВИЛОЯТИ | B78: Жиззах филиали | C78: Обещали | D78: Кр-99042640-1 | E78: XO’JAQULOV FURQAT JAYNAROVICH | F78: +998771070575 SMS, 998932920870 SMS, 998990343029 SMS, | G78: JIZZAX VILOYATI ZAFAROBOD TUMANI BIRLIK QFY RUDAKIY KUCHASI 4-A UY | H78: 3 | I78: 4648326.9 | K78: kecgaca tolaydi
A79: ЖИЗЗАХ ВИЛОЯТИ | B79: Жиззах филиали | C79: Обещали | D79: Кр-99029158-6 | E79: MELIYEV ISKANDARJON ABDULLAYEVICH | F79: 90-494-77-70 SMS ISNGLIS, 95-013-77-07 SMS OZI, 93-303-77-07 SMS AYOLI, 90-498-77-70 SMS UY, 998904947770 SMS O'G'LI TO'LOVCHI, | G79: ХАЙРАБОД, ХАЙРАБОД БУЮК-ИПАК ЙУЛИ КЎЧАСИ, uy:Р/С | H79: 3 | I79: 4527654.3 | K79: ertaga tulaydi
A80: ЖИЗЗАХ ВИЛОЯТИ | B80: Жиззах филиали | C80: Обещали | D80: Кр-99063773-1 | E80: MUHAMADIYEVA GULNORA QIZILOVNA | F80: 998911950663 UZI, 998977947748 O’G’LI, 998995406039 O’G’LI, | G80: Жиззахлик МФЙ, ул.Ш.Рашидов , 24-уй | H80: 3 | I80: 4499738 | K80: hafta ohirgaca tolaydi
A81: ЖИЗЗАХ ВИЛОЯТИ | B81: Жиззах филиали | C81: Обещали | D81: Кр-99042115-1 | E81: MIRZAYEV OYBEK SUNATILLAYEVICH | F81: +998902659695 SMS, 998915909006 SMS, 998974559695 SMS, | G81: JIZZAX VILOYATI SH.RASHIDOV TUMANI TOKCHILIK MFY ZARGARLIK KUCHASI 2-UY | H81: 3 | I81: 4391641 | K81: duwanbagaca tolaydi
A82: ЖИЗЗАХ ВИЛОЯТИ | B82: Жиззах филиали | C82: Обещали | D82: Кр-99063504-1 | E82: MIRZAYEVA LOBARXON ERGASHEVNA | F82: 998933556974 UZI, 998934026974 ERI, 998958832266 TO’LOVCHI, | G82: ТОШКЕСГАН КФЙ, ЛОЙИХАДАГИ КЎЧА, uy:РАКАМСИЗ | H82: 3 | I82: 4378801.2 | K82: erta kecgaca tolaydi
A83: ЖИЗЗАХ ВИЛОЯТИ | B83: Жиззах филиали | C83: Обещали | D83: Кр-99044956-1 | E83: NORMATOVA XADIYA ELIBOYEVNA | F83: +998995746440 SMS, 998947411990 SMS, 998990497371 SMS, | G83: JIZZAX VILOYATI JIZZAX TUMANI GANDUMTOSH MFY TOXIR MALIK KUCHASI 12-UY | H83: 3 | I83: 4111024 | K83: wu haftagaca tolaydi
A84: ЖИЗЗАХ ВИЛОЯТИ | B84: Жиззах филиали | C84: Обещали | D84: Кр-99063618-1 | E84: NISHANOV MUHRIDDIN ERKIN O’G’LI | F84: 998701179797 UY, 998933010033 AKASI, 998939960597 UZI, | G84: Маржонбулок ГСГ, Маржонбулок шахри кучаси, 16-уй, 8-хонадон | H84: 3 | I84: 3912554.5 | K84: oylik kutyapti kecgaca tolaydi
A85: ЖИЗЗАХ ВИЛОЯТИ | B85: Жиззах филиали | C85: Обещали | D85: Кр-99064135-1 | E85: ALIMOV O’TKIR ZOKIR O’G’LI | F85: 998885132332 JURASI, 998972169992 AYOLI, 998992266612 UZI, | G85: МАДАНИЯТ КФЙ, МАДАНИЯТ КФЙ, БАХМАЛСОЙ КИШЛОГИ, uy:Р/С | H85: 3 | I85: 3723496.1 | K85: ertaga abetgaca tolaydi
... A108: ЖИЗЗАХ ВИЛОЯТИ | B108: Жиззах филиали | C108: Обещали | D108: Кр-99045797-2 | E108: QARSHIBAYEV RUSLAN QAXRAMON O’G’LI | F108: +998900251515 SMS, 998902978487 SMS, 998992408778 SMS, | G108: JIZZAX VILOYATI SH.RASHIDOV TUMANI TOSHKENTLIK MFY QATORTOL KUCHASI 7-UY | H108: 3 | I108: 858191.78 | K108: duwanbagaca tolaydi
A109: ЖИЗЗАХ ВИЛОЯТИ | B109: Жиззах филиали | C109: Обещали | D109: Кр-99040635-3 | E109: JURAYEVA ZULAYXA LUTFULLAYEVNA | F109: 998915641958 SMS begona, 998938592525 SMS O`G`LI tolovchisi, 998943543086 SMS O`G`LI 2, 998931940082 SMS O`G`LI 3, 998943174556 SMS ONASI, 998932926008 Tolovchisini xotini, | G109: JIZZAX VILOYATI, DO’STLIK TUMANI, NAVRUZ MFY, IFTIXOR KUCHASI, 11-2 UY | H109: 3 | I109: 649845
A110: ЖИЗЗАХ ВИЛОЯТИ | B110: Жиззах филиали | C110: Обещали | D110: Кр-99064576-1 | E110: GAYBULLAYEV XOLMUMIN ABDURAXIMOVICH | F110: 998934022324 UY, 998941959210 AYOLI, 998973272324 UZI, | G110: Аламли МФЙ, Аламли МФЙ, Юнусобод, дом р/с | H110: 3 | I110: 507939.95 | K110: kecgaca tolaydi
A111: КАШКАДАРЁ ВИЛОЯТИ | B111: BOSH OFIS | C111: Обещали | D111: Кр-99039364-2 | E111: AZIMOV TURG’UN TUFLIYEVICH | F111: 998946868512 SMS OZI, 998786757278 SMS AYOLI, 998505792187 SMS DADSI, 998973168020 SMS ONASI, | G111: QASHQADARYO VILOYATI QAMASHI TUMANI JONBUZSOY MFY UMID NIXOLI KUCHASI 46-UY | H111: 3 | I111: 0 | K111: bugun kechgacha bittasi yopiladi bittasini hoz yopadi | 848 | 1355105.81
A112: КАШКАДАРЁ ВИЛОЯТИ | B112: SUPER BRANCH | C112: Обещали | D112: Кр-99062633-1 | E112: TO’RAQULOV SARVAR XAYRULLA O’G’LI | F112: 999885771248 SMS OZI, 998990783770 SMS AYOLI BEGONA, 998900190048 SMS DADASI, 998875260010 SMS ONASI, | G112: QASHQADARYO VILOYATI KOSON TUMANI SHERBEK MFY SHERBEK KUCHASI 34-UY | H112: 3 | I112: 699653.7 | K112: xodim jo'natdim
A113: КАШКАДАРЁ ВИЛОЯТИ | B113: SUPER BRANCH | C113: Обещали | D113: Кр-99037107-1 | E113: ZOYIROV JAMSHID JO’RAYEVICH | F113: 998942143767 SMS OZI, 998943331929 SMS AYOLI begona, 998990448122 SMS DADASI, 998994308122 SMS ONASI, | G113: QASHQADARYO VILOYATI KASBI TUMANI XO’JA XAYRON MFY XO’JA XAYRON QISHLOG’I | H113: 6 | I113: 484846.5 | K113: bugun yopadi 5 gaha
A114: КАШКАДАРЁ ВИЛОЯТИ | B114: SUPER BRANCH | C114: Обещали | D114: Кр-99057087-1 | E114: XAYITOV ZIKIR SHERKULOVICH | F114: 998992669600 SMS OZI, 998934260277 SMS AYOLI, 998932305610 SMS UKASI, 998944826069 OG'LI TULOVCHI SHU, | G114: QASHQADARYO VILOYATI KOSON TUMANI MULALI MFY KORABAYIR KUCHASI 11-UY | H114: 3 | I114: 171378.63 | K114: 4 da yopiladi
A115: КАШКАДАРЁ ВИЛОЯТИ | B115: SUPER BRANCH | C115: Обещали | D115: Кр-99058931-1 | E115: NEKBOYEV IKROM TASHPULATOVICH | F115: 998992752065 SMS UZII (BEGONA))), 998949229666 SMS OILASI , 998987773151 SMS UZIII, 998996724888 UZI NEWW, | G115: KITOB TUMANI | H115: 3 | I115: 57514.09 | K115: xoz yopadi
A116: КАШКАДАРЁ ВИЛОЯТИ | B116: SUPER BRANCH | C116: Обещали | D116: Кр-99020517-11 | E116: PRIMOV TOLMASBEK SHERMATOVICH | F116: 97-229-20-44 SMS ruslan ukasi , 97-311-44-40 SMS BEGONA EKAN, 97-001-20-44 SMS OGLI, 88-200-20-78 SMS TULOVCHI TOLMASBEK, | G116: QASHQADARYO VILOYATI KOSON TUMANI DARCHA MFY PO’LATI QISHLOG’I 5-UY | H116: 3 | I116: 0 | K116: BUGUN ABETTAN KEN BITTASINI HAL QILIAMAN DDI IILOIJI BORICHA 2078 | 115 | 1423353.62 | kechgacha to'liman dedi
A117: КАШКАДАРЁ ВИЛОЯТИ | B117: SUPER BRANCH | C117: Обещали | D117: Кр-99029108-2 | E117: ESHIMOV SHAROF NAMOZOVICH | F117: 91-638-07-71 SMS O'ZI., 88-672-07-71 SMS O'ZI 2, 90-615-87-86 SMS JIYANI, 90-669-19-82 SMS OILASI, 998910204404 maxmut oli, 998952192932 UZI NEW, 998701101982 SMS O'zi tolovchi, | G117: QASHQADARYO VILOYATI QARSHI TUMANI O’ZBEK FAYZABOD QISHLOG’I KAMOLAT KO’CHASI 56-UY | H117: 3 | I117: 0 | K117: BUGUN KECHGACHA ILOJINI QILAMAN JUMA KUNI POLNI YOPAMAN DILER TOPGANMAN DDI 1982 | 302 | 724395.35 | bugun yopiladi bu
A118: КАШКАДАРЁ ВИЛОЯТИ | B118: SUPER BRANCH | C118: Обещали | D118: Кр-99033487-2 | E118: SHODMONOVA BAXTIGUL ABDIQAYUM QIZI | F118: 998908957040 SMS O’ZI, 998908797040 SMS OILASI, 998935250601 SMS, 998995719343 SMS, 998955556474 SMS TO'LOVCHI FAQAT SHUNGA QILINSIN, 998973102809 SMS Eldor tolovchi, | G118: QASHQADARYO VILOYATI QARSHI TUMANI PATRON MFY PATRON QISHLOG’I 112-UY | I118: 0 | K118: 16:00 GACHA ILOJINI QILAMAN DDI BITTA JOYDAN PUL KELISHI KK EDI DDI | 491 | 1397272.43
A119: КАШКАДАРЁ ВИЛОЯТИ | B119: SUPER BRANCH | C119: Обещали | D119: Кр-99033487-3 | E119: SHODMONOVA BAXTIGUL ABDIQAYUM QIZI | F119: 998908957040 SMS O’ZI, 998908797040 SMS OILASI, 998935250601 SMS, 998995719343 SMS, 998955556474 SMS TO'LOVCHI FAQAT SHUNGA QILINSIN, 998973102809 SMS Eldor tolovchi, | G119: QASHQADARYO VILOYATI QARSHI TUMANI PATRON MFY PATRON QISHLOG’I 112-UY | H119: 3 | I119: 0 | K119: 16:00 GACHA ILOJINI QILAMAN DDI BITTA JOYDAN PUL KELISHI KK EDI DDI | 492 | 1474588.31
A120: КАШКАДАРЁ ВИЛОЯТИ | B120: SUPER BRANCH | C120: Обещали | D120: Кр-99033706-3 | E120: ABDIYEV KOMILJON MAHMATQOBILOVICH | F120: 998992820474 SMS O’ZI, 998919647414 SMS UY, 998992040294 SMS OILASI, 998919647404 SMS , | G120: QASHQADARYO VILOYATI QAMASHI TUMANI YANGI XAYOT MFY TEMIRYO’LCHILAR KO’CHASI 98-UY | H120: 3 | I120: 0 | K120: 17:00 gachja ilojini qilaman ddi tolovchi boshqa | 504 | 959108.49
A121: КАШКАДАРЁ ВИЛОЯТИ | B121: SUPER BRANCH | C121: Обещали | D121: Кр-99037597-3 | E121: OTAMURODOV SALOXIDDIN TURA O’G’LI | F121: 998938839097 SMS OZI, 998972222957 SMS AYOLI, 998974440277 SMS AKASI, 998972644555 SMS UKASI, 998878357171 UZI NEW, | G121: КАШКАДАРЁ ВИЛОЯТИ КОСОН ТУМАНИ ПИСТАЛИ МФЙ, ПИСТАЛИ, uy:Р/С 119 | H121: 3 | I121: 0 | K121: 15:00 gacha kartadan yopaman ddi 7171 | 728 | 700358.13
A122: КАШКАДАРЁ ВИЛОЯТИ | B122: SUPER BRANCH | C122: Обещали | D122: Кр-99038002-1 | E122: BOYMAXMADOV BAXTOVAR DADAJONZODA | F122: 998912155553 SMS OZI, 998906760702 SMS DOSTI, 998904435652 SMS DOSTI, 998913200065 SMS UKASI, +998912155553 Primary phone from road24, | G122: КУЙИОКБОЙ КФЙ, ДЕНОВ, uy:Р/З | H122: 1 | I122: 0 | K122: juma kuni aniq yopaman pul kelishi kk ddi | 747 | 1883846.34
A123: КАШКАДАРЁ ВИЛОЯТИ | B123: SUPER BRANCH | C123: Обещали | D123: Кр-99039701-1 | E123: AXMADOV RAXMATJON ISKANDAR O’G’LI | F123: 999886758088 SMS OZI, 998973140057 SMS AKASI, 998973160057 SMS AKASI 2, 998886788088 SMS UZI NEW TO'LOVCHI , 998992130365 SMS AKASI Shahriyor, | G123: QASHQADARYO VILOYATI MIRISHKOR TUMANI GULISTON MFY XAMZA KUCHASI 34-UY | H123: 3 | I123: 0 | K123: bugun kechgacha ilojini qilaman bolmasa 15 gacha yopaman ddi | 877 | 5278548.67
A124: КАШКАДАРЁ ВИЛОЯТИ | B124: SUPER BRANCH | C124: Обещали | D124: Кр-99040100-1 | E124: KUDRATOV SANJAR DJURAYEVICH | F124: 998880634212 SMS OZI, 998970700407 SMS OILASI (BEGONA), 998972000300 SMS UKASI, 998996750200 SMS AKASI, 998972000300 uzi, | G124: QASHQADARYO VILOYATI QARSHI TUMANI TINCHLIK MFY, PARMITON QISHLOG’I 33-UY | H124: 3 | I124: 0 | K124: dushanba kuni polni yopaman ddi | 946 | 10231700.83
A125: КАШКАДАРЁ ВИЛОЯТИ | B125: Қарши филиали | C125: Обещали | D125: Кр-99063288-3 | E125: ODIROV BAHRON SADULLOYEVICH | F125: +998972948022 SMS O'ZI, 998951745628 SMS, 998979540008 SMS, | G125: КАШКАДАРЁ ВИЛОЯТИ КОСОН ТУМАНИ ЭСАБОЙ МФЙ ОБОД КУЧАСИ 11-УЙ | H125: 3 | I125: 196062.05 | K125: bugun to'lavoradi
A126: КАШКАДАРЁ ВИЛОЯТИ | B126: Қарши филиали | C126: Обещали | D126: Кр-99040917-2 | E126: KAROMATOV OYBEK OBIDOVICH | F126: +998934232825 sms uzi, 998902444140 sms , 998919523244 sms, | G126: МАШЪАЛ МФЙ, НИЛУФАР КЎЧАСИ, uy:Р/С | I126: 149805 | K126: bugun to'latamn
A127: КАШКАДАРЁ ВИЛОЯТИ | B127: Қарши филиали | C127: Обещали | D127: Кр-99016127-6 | E127: MURODOV BEKZOD ZIYADULLAYEVICH | F127: 912161309 SMS UZI, 974494979 SMS AKASU, 919543908 SMS OILASI, 972001104 SMS DADASI, 998917239933 new uz, | G127: КАШКАДАРЁ ВИЛОЯТИ КАРШИ ШАХРИ Хужа-хиёл MFY QO’RG’ON KUCHASI 57-UY | H127: 3 | I127: 0 | K127: BUGUN YOPADII | 80 | 126744.46 | yopadi bugun
A128: КАШКАДАРЁ ВИЛОЯТИ | B128: Қарши филиали | C128: Обещали | D128: Кр-99020517-12 | E128: PRIMOV TOLMASBEK SHERMATOVICH | F128: 97-229-20-44 SMS ruslan ukasi , 97-311-44-40 SMS BEGONA EKAN, 97-001-20-44 SMS OGLI, 88-200-20-78 SMS TULOVCHI TOLMASBEK, | G128: QASHQADARYO VILOYATI KOSON TUMANI DARCHA MFY PO’LATI QISHLOG’I 5-UY | H128: 3 | I128: 0 | K128: BUGUN ABETTAN KEN BITTASINI HAL QILIAMAN DDI IILOIJI BORICHA 2078 | 116 | 1151107.14
A129: КАШКАДАРЁ ВИЛОЯТИ | B129: Қарши филиали | C129: Обещали | D129: Кр-99020544-2 | E129: TOJIYEV TO’XTAMUROD AMIRKULOVICH | F129: 88-677-12-52 SMS UZI, 998885881999 SMS O’GLI, 88-316-76-80 SMS OILASI, 77-777-28-40 SMS O’G’LI begana , 998885881999 katta ug`li , | G129: QASHQADARYO VILOYATI NISHON TUMANI OQOLTIN MFY TINCHLIK KO’CHASI 12-UY | H129: 3 | I129: 0 | K129: JUMA JUNI ANIQ YOPAMAN DDI | 117 | 3656584.91 | ertaga to'lo bo'ladi
A130: КАШКАДАРЁ ВИЛОЯТИ | B130: Қарши филиали | C130: Обещали | D130: Кр-99036611-1 | E130: NAZAROV DILSHOD SHAMSHODOVICH | G130: КАШКАДАРЁ ВИЛОЯТИ КОСОН ТУМАНИ АРАЛИК МФЙ ЭСКИ ШАХАР КУЧАСИ 11-УЙ | H130: 3 | I130: 0 | K130: bugun kechgacha harakat qiladiiloji boricha yopadi bolmasa dushanba kuni yopaman ddi 88 883 5600 | 667 | 7080395
A131: КАШКАДАРЁ ВИЛОЯТИ | B131: Қарши филиали | C131: Обещали | D131: Кр-99037597-2 | E131: OTAMURODOV SALOXIDDIN TURA O’G’LI | F131: 998938839097 SMS OZI, 998972222957 SMS AYOLI, 998974440277 SMS AKASI, 998972644555 SMS UKASI, 998878357171 UZI NEW, | G131: КАШКАДАРЁ ВИЛОЯТИ КОСОН ТУМАНИ ПИСТАЛИ МФЙ, ПИСТАЛИ, uy:Р/С 119 | H131: 3 | I131: 0 | K131: 15:00 gacha kartadan yopaman ddi 7171 | 727 | 932357.73
A132: КОРАКАЛПОГИСТОН РЕСПУБЛИКАСИ | B132: BOSH OFIS | C132: Обещали | D132: Кр-99041431-1 | E132: BAYNAZAROVA AMANGUL KALIBAYEVNA | F132: 998906536610 SMS OZI, 998919359599 SMS QIZI, 998913918821 SMS OGLI, 998913810499 SMS KELINI, 998933029514 SMS UKASI WU RAQAM ISHLAYDI, | G132: QARAQALPOGISTON RES NUKUS SHAHAR XAUA JOLI MFY DAWLET BAQSI KUSHASI 21 UY | H132: 3 | I132: 3206455.3 | K132: 16chida yopadi
A133: КОРАКАЛПОГИСТОН РЕСПУБЛИКАСИ | B133: SUPER BRANCH | C133: Обещали | D133: Кр-99063846-2 | E133: SABUROV OG’ABEK RAXAT O’G’LI | F133: 998500878236 SMS UZI, 998919397304 SMS DOSTI, 998930479829 SMS KELINI, 998933932316 SMS OPASI, | G133: Республика Каракалпакстан, Берунийский район, Найман ССГ, ул. Дахо, дом 5 | H133: 3 | I133: 5170842 | K133: SHANBI TO'LIDI
A134: КОРАКАЛПОГИСТОН РЕСПУБЛИКАСИ | B134: SUPER BRANCH | C134: Обещали | D134: Кр-99048733-1 | E134: MAMBETNAZAROV ILXAMBEK BEKMURZAEVICH | F134: 998907070002 SMS UZI, 998912670007 SMS UZI 2 BEGONA , 998907090003 xotini newww, | G134: NUKUS SHAHAR | H134: 3 | I134: 3148072.1 | K134: 15chida bolib bolib to'lidi
A135: КОРАКАЛПОГИСТОН РЕСПУБЛИКАСИ | B135: SUPER BRANCH | C135: Обещали | D135: Кр-99020763-4 | E135: IBROHIMOV ISLOM GULMIRZA O‘G‘LI | F135: 998997409800 SMS tolovchi, 88-500-38-03 SMS AKASI, 97-358-01-99 SMS AYOLI, 998976593110 uzi (iwlamidi), 998336593110 Uzi NEW, +998959693100 Primary phone from road24, 998959693100 Primary phone from road24, 998959693100 ozi newww, | G135: БОБУР ҚФЙ, ЖУМУР ОВУЛ МФЙ, uy:Р/С | H135: 3 | I135: 2073439 | K135: 11chida yopadi
A136: КОРАКАЛПОГИСТОН РЕСПУБЛИКАСИ | B136: Нукус филиали | C136: Обещали | D136: Кр-99042377-1 | E136: DJEKSENBAEVA IRINA DJANBIRAEVNA | F136: 998882145959 OZI, 998904244011 OGLI, 998919332729 QIZI, | G136: QARAQALPOGISTON RESPUBLIKASI NUKUS SHAHAR Nauriz MFY, Minar ko’chasi, 8-uy | H136: 3 | I136: 6311148 | K136: bo'lib bo'lib to'lidi
A137: КОРАКАЛПОГИСТОН РЕСПУБЛИКАСИ | B137: Нукус филиали | C137: Обещали | D137: Кр-99042637-1 | E137: ASKAROVA ULZADA DJAKSIMURATOVNA | F137: 998332704595 KELINI, 998913068791 QIZI, 998913906944 OZI, | G137: Кун нуры МФЙ, Мархамат кучаси, 10-уй | H137: 3 | I137: 4496084.2 | K137: bo'lib bo'lib to'lidi
A138: КОРАКАЛПОГИСТОН РЕСПУБЛИКАСИ | B138: Нукус филиали | C138: Обещали | D138: Кр-99064496-2 | E138: KAYPNAZAROV TOLIBAY KALKNAZAROVICH | F138: 998990981264 OZI, 998997340035 OGLI, 998998411898 KELINI, | G138: QORAQALPOGISTON RES KEGIYLI TUMANI ABAT MAKAN MFY BOZATAW JOLI KUSHASI 51 UY | H138: 3 | I138: 2722291 | K138: 11sanada oylik op tolidi
A139: КОРАКАЛПОГИСТОН РЕСПУБЛИКАСИ | B139: Нукус филиали | C139: Обещали | D139: Кр-99033360-1 | E139: ABDURAHIMOV ALIJON RUSTAM O’G’LI | F139: 998975601991 SMS O’ZI toshkent nukus taxi qladi , 998992371291 SMS DADASI, 998997784500 SMS AKASI, 998886502663 SMS ONASI, 998974742886 SMS akasi tolovchi bic , 998773559112 SMS ayoli xurshida , | G139: QARAQALPOGISTON RES AMUDARYO TUMANI TOLQIN OFY MARIFATSHILAR KUSHASI 27 UY | H139: 2 | I139: 1846947.1 | K139: 1-2kunda to'lidi
A140: КОРАКАЛПОГИСТОН РЕСПУБЛИКАСИ | B140: Нукус филиали | C140: Обещали | D140: Кр-99064376-1 | E140: SAGIDULLAEVA SHARBANU ORALBAEVNA | F140: 998507828856 QIZI, 998913904453 OZI, 998937104843 OGLI, | G140: КОРАКАЛПОГИСТОН РЕС КАНЛИКОЛ ТУМАНИ ДОСЛЫК МФЙ, ГАРЕЗСИЗЛИК КЎЧАСИ, uy:8 | H140: 3 | I140: 1626267.8 | K140: 11sanada oylik op tolidi
A141: НАМАНГАН ВИЛОЯТИ | B141: SUPER BRANCH | C141: Обещали | D141: Кр-99059632-1 | E141: RAXMANOV OTABEK MAXMUDJONOVICH | F141: 998908088300 Узи, 998996937053 отаси, 998997835572 аёли, | G141: Манзил: NAMANGAN VILOYATI NORIN TUMANI KATTA YAYDOQ MFY KO’XNADIYOR KO’CHASI 20 UY | H141: 64 | I141: 21548551 | K141: bugun yo ertaga yoparkan | Плохой
A142: НАМАНГАН ВИЛОЯТИ | B142: SUPER BRANCH | C142: Обещали | D142: Кр-99040105-1 | E142: OLIMJONOV XUSANBOY IMINJON O’G’LI | F142: 998943404032 SMS OZI, 998932637202 SMS ONASI, 998934225602 SMS UKASI, 998930085477 SMS DADASI, | G142: NAMANGAN VILOYATI NORIN TUMANI QO'RG'ONCHA MFY DODHOH KO'CHASI 83-UY | H142: 3 | I142: 1553961.6 | K142: puli undruvchida | Хороший
... A162: САМАРКАНД ВИЛОЯТИ | B162: SUPER BRANCH | C162: Обещали | D162: Кр-99036281-2 | E162: ALLAYAROVA TULGAN JALILOVNA | F162: 998953784737 SMS O’ZI, 998994473241 SMS O’G’LI, 998906008941 SMS KICHINA O’G’LI, 998991600587 SMS UYI, | G162: SAMARQAND VILOYATI SAMARQAND SHAHAR DARG'OM MFY ISTIQLOL KUCHASI 18-DOM 28-KVARTERA | H162: 3 | I162: 194398.35 | K162: 645
A163: САМАРКАНД ВИЛОЯТИ | B163: SUPER BRANCH | C163: Обещали | D163: Кр-99037173-1 | E163: IBODULLAYEVA ZUMRAD IBODULLAYEVNA | F163: 998882891707 SMS OZI, 998500025447 SMS UKASI, 998904775447 SMS UKASI 2, 998933036841 SMS UZI 2 begona, | G163: SAMARQAND VILOYATI SAMARQAND SHAHRI QARSHI YULI MFY JAR ARIQ KUCHASI 43/35 | I163: 125425.5 | K163: bugun polniy yopadi | 700
A164: САМАРКАНД ВИЛОЯТИ | B164: Самарқанд филиали | C164: Обещали | D164: Кр-99064318-1 | E164: BEKTEMIROV JURABOY ESIRGANOVICH | F164: 998913162326 SMS O’G’LI, 998930957026 SMS OZI, 998951747026 SMS AYOLI, | G164: SAMARQAND VILOYATI TAYLOQ TUMANI UZBEKISTON MFY QURG’ON QISHLOG’I | H164: 3 | I164: 6296310 | K164: ertaga kechgacha | 2337
A165: САМАРКАНД ВИЛОЯТИ | B165: Самарқанд филиали | C165: Обещали | D165: Кр-99064277-1 | E165: ABDURAXMONOV BOBUR ABDURAXMONOVICH | F165: 998932179000 SMS AYOLI, 998934362121 SMS UYI, 998979071717 SMS OZI, | G165: SAMARQAND VILOYATI QO’SHRABOT TUMANI QORATOSH MFY QORATOSH QISHLOG’I 22-UY | H165: 3 | I165: 6052083 | K165: 16 kungacha yopadi | 2331
A166: САМАРКАНД ВИЛОЯТИ | B166: Самарқанд филиали | C166: Обещали | D166: Кр-99063830-1 | E166: XAMIDOVA MARHABO RAHMANOVNA | F166: +998915268657 SMS OZI, 998955268657 SMS UYI, 998975268657 SMS DADASI, | G166: SAMARQAND VILOYATI OQDARYO TUMANI PAXTAOBOD MFY PAXTAOBOD KUCHASI 44-UY | H166: 3 | I166: 4326687.7 | K166: 10 kuni tolaydi | 2202
A167: САМАРКАНД ВИЛОЯТИ | B167: Самарқанд филиали | C167: Обещали | D167: Кр-99063168-1 | E167: HASANOV IXTIYOR MELIKULOVICH | F167: +998990095985 SMS OZI, 998944485565 SMS AYOLI, 998994160907 SMS UKASI, | G167: SAMARQAND VILOYATI TAYLOQ TUMANI YASTEPA MFY | H167: 3 | I167: 3132648.2 | K167: dushanba tolaydi | 2023
A168: САМАРКАНД ВИЛОЯТИ | B168: Самарқанд филиали | C168: Обещали | D168: Кр-99063767-1 | E168: SAIDOV DILSHOD ISLOMKULOVICH | F168: +998995294743 SMS OZI, 998889335662 SMS AKASI, 998972767712 SMS TULOVCHI, 998990706947 SMS SINGLISI, | G168: SAMARQAND VILOYATI SAMARQAND SHAHAR DO’STLIK MFY | H168: 3 | I168: 2792832.7 | K168: 11-12 kuni tolov qiladi | 2183
A169: САМАРКАНД ВИЛОЯТИ | B169: Самарқанд филиали | C169: Обещали | D169: Кр-99063701-1 | E169: XUJAMURODOV ULFAT QURBONQULOVICH | F169: +998915441976 OZI SMS, 998915226604 SMS AYOLI, 998934434402 SMS KUYOVI, 998949410350 SMS OGLI, | G169: SAMARQAND VILOYATI URGUT TUMANI KATTA KAMANGARON MFY KAMON KUCHASI 107- UY | H169: 3 | I169: 2647090.8 | K169: juma kuni xudoyor akaga beradi | 2166
...

Sheet Ko'tarmadi
A1: ← Вернуться в отчёт
A2: Область | B2: Филиал | C2: Группа | D2: Код клиента | E2: Клиент | F2: Номер телефона | G2: Адрес | H2: Кол-во просроченных дней | I2: Итого просрочка | J2: Оплата | K2: Izoh
A3: АНДИЖОН ВИЛОЯТИ | B3: SUPER BRANCH | C3: Ko'tarmadi | D3: Кр-99050899-1 | E3: ERGASHOV ELYORBEK NE’MATJONOVICH | F3: 998774544221 SMS OZI, 998902062924 SMS AYOLI, 998022181812 SMS OZI, 998902533553 SMS AKASI, 998902218181 SMS O'zi new, | G3: ANDIJON VILOYATI BO’Z TUMANI GUZAR MFY, O’ZBEKISTON KO’CHASI 489-UY | H3: 125 | I3: 37784865 | K3: ishi sudda yurist opa shugillanyapti
A4: АНДИЖОН ВИЛОЯТИ | B4: SUPER BRANCH | C4: Ko'tarmadi | D4: Кр-99063829-1 | E4: MIRZAYEV ABDULAZIZ RUSTAMOVICH | F4: 998773674777 SMS ONASI, 998940207105 SMS UZI, 998970610099 SSM AKASI, 998990723095 SMS DOSTI, | G4: Quvvatmurod MFY, Dilkushod ko’chasi, 139-uy | H4: 24 | I4: 3340780.8 | K4: umuman yoq bu klent
A5: АНДИЖОН ВИЛОЯТИ | B5: SUPER BRANCH | C5: Ko'tarmadi | D5: Кр-99020905-2 | E5: QOBILOV BAYOZBEK MAXAMADSOLI O’G’LI | F5: 33-615-57-57 SMS OZI, 99-194-20-20 SMS ZALOGADATEL, 50-075-07-47 SMS ZALOGADATEL, 91-483-70-00 SMS OZI, | G5: ANDIJON VILOYATI ANDIJON TUMANI XARTUM QFY YANGI TO’LQIN MFY YANGI TO’LQIN KO’CHASI 78-UY | H5: 3 | I5: 3112486.5 | K5: oilaviy rusda faqat tg orqali gaplashamiz 15 gacha yopib beradi
A6: АНДИЖОН ВИЛОЯТИ | B6: SUPER BRANCH | C6: Ko'tarmadi | D6: Кр-99063829-2 | E6: MIRZAYEV ABDULAZIZ RUSTAMOVICH | F6: 998773674777 SMS ONASI, 998940207105 SMS UZI, 998970610099 SSM AKASI, 998990723095 SMS DOSTI, | G6: Quvvatmurod MFY, Dilkushod ko’chasi, 139-uy | H6: 24 | I6: 2672624 | K6: umuman yoq bu klent
A7: АНДИЖОН ВИЛОЯТИ | B7: SUPER BRANCH | C7: Ko'tarmadi | D7: Кр-99020905-3 | E7: QOBILOV BAYOZBEK MAXAMADSOLI O’G’LI | F7: 33-615-57-57 SMS OZI, 99-194-20-20 SMS ZALOGADATEL, 50-075-07-47 SMS ZALOGADATEL, 91-483-70-00 SMS OZI, | G7: ANDIJON VILOYATI ANDIJON TUMANI XARTUM QFY YANGI TO’LQIN MFY YANGI TO’LQIN KO’CHASI 78-UY | H7: 3 | I7: 1867127.8 | K7: oilaviy rusda faqat tg orqali gaplashamiz 15 gacha yopib beradi
A8: БУХОРО ВИЛОЯТИ | B8: SUPER BRANCH | C8: Ko'tarmadi | D8: Кр-99039543-1 | E8: DJUMAYEV ZAVQIY LATIPOVICH | F8: 998901180010 SMS OZI , 998770240926 SMS UKASI, +998901180010 Primary phone from road24, 998950000118 SMS asilbek o'g'li, | G8: Богча МФЙ, Гараншоҳ қишлоғи, 52-C-уй | H8: 149 | I8: 45153274 | K8: BUNI ISHI SUDDA AUKSIONGA QO'YIB SOTISH KERAK | 871
A9: БУХОРО ВИЛОЯТИ | B9: SUPER BRANCH | C9: Ko'tarmadi | D9: Кр-99052919-1 | E9: RO’ZIYEVA NAFISA ILXOMOVNA | F9: 998938875127 SMS узи, 998941275006 SMSэри, 998884747005 SMS угли, 998938865006 узи2, 998508787766 eri 2, | G9: IIV6242 | H9: 3 | I9: 8401531.9 | K9: 7766 BUGUNGA DEGANDI BUGUN KO'TARMADI | 1502
A10: БУХОРО ВИЛОЯТИ | B10: SUPER BRANCH | C10: Ko'tarmadi | D10: Кр-99039939-1 | E10: TUXTAYEVA NARGIZA JURAYEVNA | F10: 998918365488 SMS OZI, 998903407973 SMS ONASI, 998331951802 SMS ERI, 998994452534 SMS UY, | G10: BUXORO VILOYATI BUXORO SHAHAR FOSHUN MFY ALPOMISH KO'CHASI, 17/3 UY, 10-XONADON | H10: 3 | I10: 2508756.4 | K10: RAQAMLARI ISHLAMADI | 917
A11: БУХОРО ВИЛОЯТИ | B11: SUPER BRANCH | C11: Ko'tarmadi | D11: Кр-99033006-2 | E11: AMIRQULOV AZIZBEK FARXOD O’G’LI | F11: 998943206655 SMS O’ZI , 998930065166 SMS AKASI, 998940514494 SMS UKASI, | G11: BUXORO VILOYATI KORAKO’L TUMANI DARG’ALI MFY OQG’UN QISHLOG’I 22-UY | H11: 6 | I11: 2272195.6 | K11: KO'TARMADI | 460
A12: БУХОРО ВИЛОЯТИ | B12: SUPER BRANCH | C12: Ko'tarmadi | D12: Кр-99063054-1 | E12: JAXONOV RUSLANBEK VALIJON O’G’LI | F12: 998978556508 OZI, 998887822252 DOSTI TO'LOVCHI , 998930055804 DOSTI, 998978611976 ONASI, | G12: BUXORO VILOYATI QORAKO'L TUMANI DURMAN MFY KATTA DURMAN | H12: 3 | I12: 1369060.8 | K12: KO'TARMADI | 1984
A13: БУХОРО ВИЛОЯТИ | B13: SUPER BRANCH | C13: Ko'tarmadi | D13: Кр-99057614-1 | E13: RASULOV XAKIM RO’ZIYEVICH | F13: 998914413241 SMS UZI, 998943434898 SMS UGLI, 998914158714 SMS TURMUSH O'RTOG'I, 998919256826 ozi2, | G13: NAVOIY VILOYATI,KOMNIMEX TUMANI,YUKSALISH MFY,CHORDARA QISHLOG'I,37 UY | H13: 3 | I13: 1139235.8 | K13: KO'TARMADI | 1663
A14: БУХОРО ВИЛОЯТИ | B14: Бухоро филиали | C14: Ko'tarmadi | D14: Кр-99031012-1 | E14: FARMONOVA GULCHEHRA MUSLIDDINOVNA | F14: 33-524-05-05 SMS O'ZI, 91-240-39-39 SMS ERI, 90-635-09-93 SMS ONASI, 50-884-90-24 SMS AKASI, 998914483333 SMS ELDOR , 998908702747 SMS O'ZI, | G14: BUXORO VILOYATI G'IJDUVON TUMANI HAVZAK MFY, QATAG'AN KO'CHASI, 36-UY | H14: 41 | I14: 26767665 | K14: QAYNONASI KO'TARDI MANGA SHARTNOMA TAWAB BERSELA MAN AYTAMAN DEYABDI TO'LOV | 369
A15: ЖИЗЗАХ ВИЛОЯТИ | B15: BOSH OFIS | C15: Ko'tarmadi | D15: Кр-99039915-1 | E15: SAYDIAXMATOVA ZILOLA SHADMANOVNA | F15: 998881298980 SMS OZII, 998941959566 SMS DADASI, 998995738980 SMS ERI, 998941939385 SMS ONASI, 998945719566 SMS TO’LOVCHI DADASI, | G15: JIZZAX VILOYATI PAXTAKOR TUMANI DO’STLIK MFY JABBOROV KUCHASI 18/3-UY / JIZZAX VILOYATI PAXTAKOR TUMANI CHAMANZOR MFY YANGI MASSIV KO'CHASI 20-UY | H15: 3 | I15: 3906815.1
A16: ЖИЗЗАХ ВИЛОЯТИ | B16: SUPER BRANCH | C16: Ko'tarmadi | D16: Кр-99034935-2 | E16: ABDULLAYEVA SHAHNOZA USMANALIYEVNA | F16: 998938563666 SMS O’ZI, 998991831234 SMS ERI, 998932954000 SMS SHOGIRDI, 998992987070 SMS HAMKASBI, | G16: JIZZAX VILOYATI BAXMAL TUMANI NOVQA MFY KURBULOQ QISHLOG’I 27-UY | H16: 6 | I16: 13173602
A17: ЖИЗЗАХ ВИЛОЯТИ | B17: SUPER BRANCH | C17: Ko'tarmadi | D17: Кр-99040190-1 | E17: XODJIMURATOV MAMARAXIM USKANOVICH | F17: 998994798433 SMS OZI, 998992780316 SMS OZI NEW, 998773162199 SMS SINGLISI, 998990301519 SMS QIZI , 998773479799 SMS TO’LOVCHI, | G17: JIZZAX VILOYATI ZOMIN TUMANI NIHOL MFY YANGI OVUL QISHLOG’I 70-UY | H17: 3 | I17: 5745754.5
A18: ЖИЗЗАХ ВИЛОЯТИ | B18: SUPER BRANCH | C18: Ko'tarmadi | D18: Кр-99039291-1 | E18: ASHUROV AVAZ UCHKUNOVICH | F18: 998935875040 SMS O’ZI, 998975223757 SMS AYOLI, 998971270108 SMS SINGLISI, 998880707901 SMS O'ZI , | G18: JIZZAX VILOYATI FORISH TUMANI XONBANDI MFY XONBANDI SHAXARCHASI 452-UY | H18: 6 | I18: 4502799.1
A19: ЖИЗЗАХ ВИЛОЯТИ | B19: SUPER BRANCH | C19: Ko'tarmadi | D19: Кр-99040996-1 | E19: BOBAQULOV JASUR INOMOVICH | F19: 998959118222 SMS OZI, 998888481114 SMS AYOLI, 998956311666 SMS UY, 998915935501 SMS SINGLISI, | G19: JIZZAX VILOYATI SH.RASHIDOV TUMANI UCHTEPA MFY BESHQAYRAGOCH KUCHASI 168-UY | H19: 3 | I19: 2984934.3
A20: ЖИЗЗАХ ВИЛОЯТИ | B20: SUPER BRANCH | C20: Ko'tarmadi | D20: Кр-99039896-1 | E20: UMMATOV JAVLON MAVLONOVICH | F20: 998959172024 SMS OZI, 998957701676 SMS UKASI, 998957741676 SMS SINGLIASI, 998911956219 SMS DADASI, 998995247977 sms uzi mew, 998995247977 sms uzi new, | G20: JIZZAX VILOYATI SH.RASHIDOV TUMANI UCH TEPA MFY GUNCHA KUCHASI 97-UY | H20: 3 | I20: 2851933
A21: ЖИЗЗАХ ВИЛОЯТИ | B21: SUPER BRANCH | C21: Ko'tarmadi | D21: Кр-99060382-1 | E21: XONIMKULOV XURSHID UMARKUL O’G’LI | F21: 998991027333 узи, 998915900150 аели, 998911968898 шериги, | G21: JIZZAX VILOYATI JIZZAX TUMANI BUNYODKOR MFY LOLAZOR KUCHASI 1A-UY | H21: 3 | I21: 2831889.3 | K21: qisman tolov qildi qoganini 10gaca tolaydi oylik tuwsa
A22: ЖИЗЗАХ ВИЛОЯТИ | B22: SUPER BRANCH | C22: Ko'tarmadi | D22: Кр-99039815-1 | E22: MAMAYUSUPOVA MAHLIYO FAXRIDDIN QIZI | F22: 998905381611 SMSAKASI, 998931008231 SMS AKASI 2, 998919406665 SMS UKASI, 998945792828 SMS ERI, | G22: JIZZAX VILOYATI G’ALLAOROL TUMANI BERUNIY MFY BERUNIY KUCHASI 54-UY | H22: 3 | I22: 2606254.8
A23: ЖИЗЗАХ ВИЛОЯТИ | B23: SUPER BRANCH | C23: Ko'tarmadi | D23: Кр-99039412-1 | E23: NORQULOV SULTON ABDUSALOMOVICH | F23: 998995290861 SMS OZI, 998881011263 SMS AYOLI, 998993392325 SMS SINGLISI, 998943499552 SMS KELINI, | G23: JIZZAX VILOYATI BAXMAL TUMANI FIDOKOR MFY ALAMLI QISHLOG'I | H23: 1 | I23: 2168641.1
A24: ЖИЗЗАХ ВИЛОЯТИ | B24: SUPER BRANCH | C24: Ko'tarmadi | D24: Кр-99033705-2 | E24: ABDIYEV IBRAIM RAXMONOVICH | F24: 998937753867 SMS O’ZI, 998937723867 SMS AYOLI, 998931210076 SMS UKASI, 998948762276 SMS OVSINI, | G24: JIZZAX VILOYATI ZAFAROBOD TUMANI UZUN QFY MUSTAQILLIK KUCHASI 24-UY | H24: 3 | I24: 1739172.9
A25: ЖИЗЗАХ ВИЛОЯТИ | B25: SUPER BRANCH | C25: Ko'tarmadi | D25: Кр-99063888-2 | E25: SULTONOV OTAJON KOMIL O’G’LI | F25: 998700561007 SMS JIYANI, 998952124508 SMS UZI2, 998972930722 SMS UZI, | G25: Джизакская область, Джизак г., Маданият, Бауман, дом 27, кв. 7 | H25: 3 | I25: 1701597.9 | K25: ucgan hamma nomerr
A26: ЖИЗЗАХ ВИЛОЯТИ | B26: SUPER BRANCH | C26: Ko'tarmadi | D26: Кр-99039157-2 | E26: NORMATOV NORMUROD RAXMONOVICH | F26: 998886454883 SMS OZI, 998945843236 SMS AKASI, 998971390201 SMS SIN, 998882152232 SMS KATTA SINI, | G26: JIZZAX VILOYATI JIZZAX TUMANI OLMACHI MFY ADOLAT KUCHASI | H26: 3 | I26: 1641020.2 | K26: hamma nomer ucgan
A27: ЖИЗЗАХ ВИЛОЯТИ | B27: SUPER BRANCH | C27: Ko'tarmadi | D27: Кр-99052917-1 | E27: ABDUALIMOV OZODJON ABDURAXIM O’G’LI | F27: 998911972123 SMS OZI, 998915681200 SMS AYOLI, 999156813002 SMS OZI 2, | G27: JIZZAX VILOYATI JIZZAX SHAHRI OQQURG'ONLIK MAHALLASI YU SALIMOV KUCHASI 70-UY | H27: 3 | I27: 1440479.6 | K27: ucgan
A28: ЖИЗЗАХ ВИЛОЯТИ | B28: SUPER BRANCH | C28: Ko'tarmadi | D28: Кр-99046629-2 | E28: UMAROV VAXOB VALIYEVICH | F28: +998904908890 SMS, 998940358890 SMS, 998999968799 SMS, 998993662364 SMS, | G28: Джизакская область, Джизак г., Хамзаобод, Ойбек, дом 23 | H28: 3 | I28: 1397405 | K28: ertaga tolaydi
A29: ЖИЗЗАХ ВИЛОЯТИ | B29: SUPER BRANCH | C29: Ko'tarmadi | D29: Кр-99029361-2 | E29: ERGASHEV ERALI RAXMON O’G’LI | F29: 88-645-03-15 SMS UZI, 97-707-57-18 SMS AKASI, 97-911-72-80 SMS DADASI, 998978987280 SMS ONASI, 998770525718 SMS ukasi tolovchi , | G29: JIZZAX VILOYATI BAXMAL TUMANI MADANIYAT MFY UZUN BULOQ QYF | H29: 3 | I29: 1369755.3
A30: ЖИЗЗАХ ВИЛОЯТИ | B30: SUPER BRANCH | C30: Ko'tarmadi | D30: Кр-99039305-1 | E30: G’ANIYEV LAZIZ G’ULOM O’G’LI | F30: 998952401313 SMS OZI, 998975682026 SMS ONASI, 998915682026 SMS DADASI, 998950895353 SMS UKASI, | G30: JIZZAX VILOYATI SH.RASHIDOV TUMANI SOVUNGARLIK MFY MAROQAND KUCHASI 52-UY | H30: 6 | I30: 1325931.9
A31: ЖИЗЗАХ ВИЛОЯТИ | B31: SUPER BRANCH | C31: Ko'tarmadi | D31: Кр-99057414-1 | E31: KARSHIBAYEV SHUXRAT URALOVICH | F31: 998991231880 SMS UZI, 998958914146 SMS UZI 2, 998938265151 SMS AKASI, | G31: JIZZAX VILOYATI ARNASOY TUMANI BO'STON MFY A.QARSHIYEV KUCHASI 30/2-UY | H31: 3 | I31: 593350.54
A32: ЖИЗЗАХ ВИЛОЯТИ | B32: Жиззах филиали | C32: Ko'tarmadi | D32: Кр-99062963-2 | E32: RAJABOV BAXODIR BOZARBOYEVICH | F32: 998941996644 AYOLI, | G32: Саройлик МФЙ, Эркинлик кучаси, 45-уй | H32: 3 | I32: 12443922
A33: ЖИЗЗАХ ВИЛОЯТИ | B33: Жиззах филиали | C33: Ko'tarmadi | D33: Кр-99063460-1 | E33: AXMEDOV ALISHER KAMALOVICH | F33: 998991041481 AYOLI, 998993573881 UKASI, | G33: ШИРИН ҚФЙ, ШИРИН ҚФЙ, ҚУДУҚЧА ҚИШЛОҒИ, uy:Р.С | H33: 3 | I33: 8492612.2 | K33: ucrilgan
A34: ЖИЗЗАХ ВИЛОЯТИ | B34: Жиззах филиали | C34: Ko'tarmadi | D34: Кр-99052135-1 | E34: TURAKULOV SIROJIDDIN SUNNAT O’G’LI | F34: 998919421111 UY, 998993447700 sms new uz, | G34: ЗИЛОЛ, ЗИЛОЛ, ЯНГИОБОД, uy:30 | H34: 3 | I34: 6342586.5
A35: ЖИЗЗАХ ВИЛОЯТИ | B35: Жиззах филиали | C35: Ko'tarmadi | D35: Кр-99063392-1 | E35: BERDIYAROV TO’RAMUROD XUDOYKULOVICH | F35: 998501568064 UZI, 998939931883 AYOLI, 998943438583 ONAS, | G35: БОГИШАМОЛ КФЙ, БОГИШАМОЛ КФЙ, МУГОЛ КИШЛОГИ, uy:РАКАМСИЗ | H35: 3 | I35: 6257551.6
A36: ЖИЗЗАХ ВИЛОЯТИ | B36: Жиззах филиали | C36: Ko'tarmadi | D36: Кр-99038849-3 | E36: XASANOV INOMJON USMONOVICH | F36: 998977931100 SMS SINGLISI, 998916262046 SMS OZI, 998976831100 SMS SINGLISI 2, 998915665348 SMS AYOLI, | G36: ДУСТЛИК, ДУСТЛИК, Э.АШИРМАТОВ, uy:Р/С | H36: 3 | I36: 4956280.9
A37: ЖИЗЗАХ ВИЛОЯТИ | B37: Жиззах филиали | C37: Ko'tarmadi | D37: Кр-99063375-1 | E37: AG’LAMOV AZIMXON AKRAM O’G’LI | F37: 998881511212 AKASI, 998915981212 AKASI, 998970105070 UZI, | G37: УЧАРИК МФЙ, ХАМЗАОБОД, ФИРДАВСИЙ, uy:9 | H37: 3 | I37: 4489348.9
A38: ЖИЗЗАХ ВИЛОЯТИ | B38: Жиззах филиали | C38: Ko'tarmadi | D38: Кр-99042221-2 | E38: MAMATQOSIMOV DOSTONJON YUSUF O’G’LI | F38: +998919420024 SMS, 998911963666 SMS, 998919430024 SMS, | G38: JIZZAX VILOYATI JIZZAX SHAHRI ULUG’BEK MFY SHIRIN KUCHASI 16/2-UY | H38: 3 | I38: 4388296
A39: ЖИЗЗАХ ВИЛОЯТИ | B39: Жиззах филиали | C39: Ko'tarmadi | D39: Кр-99044129-2 | E39: ANORBOYEV RABBIM QURBONOVICH | F39: +998911993133 SMS, 998915963134 SMS, 998918038686 SMS, | G39: JIZZAX VILOYATI JIZZAX SHAHRI ITTIFOQ MFY ITTIFOQ KUCHASI 36/30 - UY | H39: 3 | I39: 3930709
A40: ЖИЗЗАХ ВИЛОЯТИ | B40: Жиззах филиали | C40: Ko'tarmadi | D40: Кр-99038849-2 | E40: XASANOV INOMJON USMONOVICH | F40: 998977931100 SMS SINGLISI, 998916262046 SMS OZI, 998976831100 SMS SINGLISI 2, 998915665348 SMS AYOLI, | G40: ДУСТЛИК, ДУСТЛИК, Э.АШИРМАТОВ, uy:Р/С | H40: 3 | I40: 3632073.9
A41: ЖИЗЗАХ ВИЛОЯТИ | B41: Жиззах филиали | C41: Ko'tarmadi | D41: Кр-99063845-1 | E41: ISMAILOV O’KTAM MANSUROVICH | F41: 998958900049 UG’LI, 998991435960 UZI, 998996254284 ONASI, | G41: КОРАОБДОЛ ҚФЙ, КОРАОБДОЛ ҚФЙ, ШОХ УСМОН КИШЛОГИ, uy:РАКАМСИЗ | H41: 3 | I41: 2786182.5
A42: ЖИЗЗАХ ВИЛОЯТИ | B42: Жиззах филиали | C42: Ko'tarmadi | D42: Кр-99041692-1 | E42: XAYDAROVA MUHABBAT KAMOL QIZI | F42: +998871055002 SMS OZI, 998879530070 SMS AYOLI, 998918910095 SMS AKASI, 998918910095 SMS UKASI, | G42: JIZZAX VILOYATI JIZZAX TUMANI QANGLI MFY FAROVON KUCHASI 36-UY | H42: 3 | I42: 2390875.7
A43: ЖИЗЗАХ ВИЛОЯТИ | B43: Жиззах филиали | C43: Ko'tarmadi | D43: Кр-99046629-1 | E43: UMAROV VAXOB VALIYEVICH | F43: +998904908890 SMS, 998940358890 SMS, 998999968799 SMS, 998993662364 SMS, | G43: Джизакская область, Джизак г., Хамзаобод, Ойбек, дом 23 | H43: 3 | I43: 2339566.6 | K43: ertaga tolaydi
A44: ЖИЗЗАХ ВИЛОЯТИ | B44: Жиззах филиали | C44: Ko'tarmadi | D44: Кр-99038618-4 | E44: QO’SHBOQOV FAXRIDDIN SHAVKAT O’G’LI | F44: 998902961330 SMS OZI, 998995573434 SMS OZI 2, 998902653331 SMS AYOLI, 998995504525 SMS AKASI, 998882221330 UZI, +998882221330 UZI, | G44: JIZZAX VILOYATI SH.RASHIDOV TUMANI OLMACHI MFY BOGBON KUCHASI 111-UY | H44: 3 | I44: 2210649.4
A45: ЖИЗЗАХ ВИЛОЯТИ | B45: Жиззах филиали | C45: Ko'tarmadi | D45: Кр-99044722-1 | E45: BERDIYEVA GULNORA KENJAYEVNA | F45: +998931257179 SMS, 998932347179 SMS, 998946894222 SMS Nomer xato, | G45: JIZZAX VILOYATI ARNASOY TUMANI G’OFUR G’ULOM MFY G’OFUR G’ULOM KUCHASI 15/1-UY | H45: 3 | I45: 1874121.6
A46: ЖИЗЗАХ ВИЛОЯТИ | B46: Жиззах филиали | C46: Ko'tarmadi | D46: Кр-99045574-1 | E46: CHORIYEV ANVAR SHODI O’G’LI | F46: +998979349212 SMS, 998937710271 SMS, 998993009308 SMS, | G46: JIZZAX VILOYATI JIZZAX SHAHRI OLMAZOR MFY OLMAZOR KUCHASI 30/1-UY | H46: 6 | I46: 1763802.4
A47: ЖИЗЗАХ ВИЛОЯТИ | B47: Жиззах филиали | C47: Ko'tarmadi | D47: Кр-99031804-2 | E47: USMANOV GAYRAT IMAMOVICH | F47: 998974360075 SMS O’ZI , 998995299620 SMS SHERIGI, 998911969620 SMS AYOLI, 998990360075 SMS ozi new, 998992408008 SMS tolovchi new, 998931444446 SMS TO’LOVCHI NEW, 998770367771 SMS NEW UZI, 998990367771 SMS Tolovchi new, | G47: JIZZAX VILOYATI SH.RASHIDOV TUMANI QO’SHBARMOQ QFY UCHARIQ MAHALLASI ROHAT KUCHASI 15-UY | H47: 3 | I47: 1591321.4 | K47: 8008 tolovci
A48: ЖИЗЗАХ ВИЛОЯТИ | B48: Жиззах филиали | C48: Ko'tarmadi | D48: Кр-99046629-4 | E48: UMAROV VAXOB VALIYEVICH | F48: +998904908890 SMS, 998940358890 SMS, 998999968799 SMS, 998993662364 SMS, | G48: Джизакская область, Джизак г., Хамзаобод, Ойбек, дом 23 | H48: 3 | I48: 1400415.3 | K48: ertaga tolaydi
A49: ЖИЗЗАХ ВИЛОЯТИ | B49: Жиззах филиали | C49: Ko'tarmadi | D49: Кр-99041954-1 | E49: G’ANIYEV XUSANBEK XONIMQUL O’G’LI | F49: +998770667202 SMS OZI, 998779760777 SMS AYOLI, 998937670670 SMS OGLI, | G49: JIZZAX VILOYATI BAXMAL TUMANI BOGISHAMOL QFY NAVRUZ QISHLOGI | I49: 1383261.3
A50: ЖИЗЗАХ ВИЛОЯТИ | B50: Жиззах филиали | C50: Ko'tarmadi | D50: Кр-99063407-1 | E50: DUSBAYEV FARXOD G’AFFAROVICH | F50: 998903111601 TULOVCHI, 998909868228 TULOVCHINI ERI, 998945772444 UZI, | G50: КАНГЛИ КФЙ, ЯНГИОБОД МАХАЛЛАСИ, ТАРАХЛИ КУЧАСИ 10-УЙ | H50: 3 | I50: 248154.54
A51: ЖИЗЗАХ ВИЛОЯТИ | B51: Жиззах филиали | C51: Ko'tarmadi | D51: Кр-99041710-1 | E51: MAMARAJABOVA ZULOYXA ABDUMALIK QIZI | F51: 998339269697 SMS, 998931049616 SMS, | G51: JIZZAX VILOYATI BAXMAL TUMANI TONGOTAR MFY QUSHTEPA QISHLOGI 65-UY | H51: 3 | I51: 215838.24 | K51: ucrilgan
A52: ЖИЗЗАХ ВИЛОЯТИ | B52: Жиззах филиали | C52: Ko'tarmadi | D52: Кр-99063760-1 | E52: KAXAROV ASROR BAXRAMOVICH | F52: 998500016485 JIYANI, 998915646485 UZI, 998939646485 O’G’LI, | G52: Уратепалик МФЙ, А.Мелиев кучаси, 38-уй | I52: 35231.88
A53: КАШКАДАРЁ ВИЛОЯТИ | B53: SUPER BRANCH | C53: Ko'tarmadi | D53: Кр-99034348-3 | E53: MURATOV AKTAM ABDIRAZZAQOVICH | F53: 998919517995 SMS O’ZI, 998939311300 SMS QO'SHNISI, 998908814003 SMS JO’RASI UZIIII, 998932703285 SMS AKASI (BEGONAAA), 998500217995 SMS ZALOG EGASI TO'LOVCHI, | G53: QASHQADARYO VILOYATI KO’KDALA MANGU YURUR MFY QILBURUN QISHLOG’I | H53: 3 | I53: 0 | K53: raqamlari ishlamidi | 534 | 4871713.58
A54: КАШКАДАРЁ ВИЛОЯТИ | B54: SUPER BRANCH | C54: Ko'tarmadi | D54: Кр-99036325-4 | E54: AVLOKULOVA OZODA SUNNATILLOYEVNA | F54: 998993739998 SMS O’ZI, 998975886080 SMS AKASI , 998883810758 SMS ONASI , 998977817878 SMS O’ZI 2, | G54: TOSHKENT SHAHRI MIRZOULUG’BEK TUMANI, BUZBOZOR,7- TOR KOCHASI ,36-UY,65-XONADON | H54: 3 | I54: 0 | K54: kotarmadi | 648 | 6199480
A55: КАШКАДАРЁ ВИЛОЯТИ | B55: SUPER BRANCH | C55: Ko'tarmadi | D55: Кр-99036546-1 | E55: YULDASHEV RUSTAM QURBONAZAR O’G’LI | F55: 998976711771 SMS OZI, 998987770193 SMS OZI 2, 998904252808 SMS OILASI , 998880062055 SMS AKASI , | G55: QASHQADARYO VILOYATI G’UZOR TUMANI ERKIN KUCHASI 27-UY | I55: 0 | K55: kotarmayapti umuman | 664 | 911947.45
A56: КАШКАДАРЁ ВИЛОЯТИ | B56: SUPER BRANCH | C56: Ko'tarmadi | D56: Кр-99037055-2 | E56: ISKANDAROV NURIDDIN NIZOMIDDIN O’G’LI | F56: 998881202280 SMS O’ZI, 998507104532 SMS OZI 2, 998880485080 SMS OSHNASI, 998200030241 SMS OSHNASI (begona), | G56: QASHQADARYO VILOYATI SHAHRISABZ TUMANI QUTCHI MFY,GULZOR KO’CHASI 80-UY | H56: 3 | I56: 0 | K56: raqami ishlamidi | 682 | 1295764.05
A57: КАШКАДАРЁ ВИЛОЯТИ | B57: SUPER BRANCH | C57: Ko'tarmadi | D57: Кр-99037164-1 | E57: IMOMOV FAYZULLA PARDAYEVICH | F57: 998919553110 SMS OZI, 998807931102 SMS OZI 2, 998906672203 SMS OILASI, 998889883110 SMS O’G’LI, | G57: QASHQADARYO VILOYATI YAKKABOG’ TUMANI SEROB MFY MINJIR QISHLOQI | H57: 3 | I57: 0 | K57: ishlamidi raqamlari | 695 | 1795376.05
A58: КАШКАДАРЁ ВИЛОЯТИ | B58: SUPER BRANCH | C58: Ko'tarmadi | D58: Кр-99037316-2 | E58: XAMROYEVA DILRABO KUYLIYEVNA | F58: 998908819972 SMS OZI, 998906606361 SMS ONASI BEGONA QIZCHA, 998906851166 SMS OTASI, 998906831166 SMS AKASI (UZIII), | G58: QASHQADARYO VILOYATI QARSHI TUMANI NAVRUZ MFY BOBUR KUCHASI 16-UY | H58: 3 | I58: 0 | K58: 707 | 1247032.03
A59: КАШКАДАРЁ ВИЛОЯТИ | B59: SUPER BRANCH | C59: Ko'tarmadi | D59: Кр-99037785-1 | E59: ESHBAYEV ADXAM JOVLI O’G’LI | F59: 998976703494 SMS OZI, 998884860002 SMS AKASI, 998886792168 SMS UKASI, 998771091102 SMS ALISHER AKA OZIMIZI XODIM, | G59: QASHQADARYO VILOYATI NISHON TUMANI UMR BUNYODKORI MFY MUSTAQILLIK KUCHASI 20-UY | H59: 2 | I59: 0 | K59: 735 | 1445169.12
A60: КАШКАДАРЁ ВИЛОЯТИ | B60: SUPER BRANCH | C60: Ko'tarmadi | D60: Кр-99039397-1 | E60: YO’LDOSHEV G’AYRAT BEKMURODOVICH | F60: 998770392787 SMS OZI, 998992423608 SMS AYOLI, 998991070648 SMS DADASI, 998886661004 SMS ONASI, | G60: QASHQADARYO VILOYATI KASBI TUMANI MESIT MFY MESIT QISHLOG’I OBOD TEPA KUCHASI | I60: 0 | K60: ishlamayapti | 854 | 358186.1 | birorta nomeri ishlamayapti mahallasiga chiqish kk
A61: КАШКАДАРЁ ВИЛОЯТИ | B61: SUPER BRANCH | C61: Ko'tarmadi | D61: Кр-99040060-1 | E61: XAMROKULOV ASILBEK QAHHOR O’G’LI | F61: 998957769119 SMS OZI, 998887169119 SMS OPASI, 998886169119 SMS DADASI, 998907169119 SMS OZI, | G61: QASHQADARYO VILOYATI NISHON TUMANI NAVBAXOR MFY ZAKOVAT KUCHASI 3/1 UY | H61: 3 | I61: 0 | K61: 937 | 4346831.46
A62: КАШКАДАРЁ ВИЛОЯТИ | B62: SUPER BRANCH | C62: Ko'tarmadi | D62: Кр-99040396-1 | E62: KENJAYEV OTABEK ABDIRAXIM O’G’LI | F62: 998975897577 SMS OZI (BEGONA), 998990482034 SMS UKASI, 998770612003 SMS DADASI, | G62: QASHQADARYO VILOYATI SHAXRISABZ TUMANI OQ OLTIN MFY ANDAY KUCHASI 62-UY | H62: 3 | I62: 0 | K62: raqami ishlamayapti | 1009 | 774785.18
A63: КАШКАДАРЁ ВИЛОЯТИ | B63: Қарши филиали | C63: Ko'tarmadi | D63: Кр-99029105-1 | E63: MAHMUDOV OLIM OTAQULOVICH | F63: 95-178-02-25 SMS OZI TULOVCHISI, 99-152-62-55 SMS ONASI, 97-803-97-77 SMS AYOLI, 97-743-33-66 SMS ZALOGADATEL, 98-366-82-72 SMS ZALOGADATEL, 998777420100 UZI NEWW, | G63: QASHQADARYO VILOYATI QARSHI TUMANI CHAROG'ON QFY 33-UY | H63: 3 | I63: 0 | K63: 301 | 1185882.06 | yibanni ishi mibda moshinasi
A64: КАШКАДАРЁ ВИЛОЯТИ | B64: Қарши филиали | C64: Ko'tarmadi | D64: Кр-99032971-3 | E64: SHODIYEV NAMOZ ERKIN O’G’LI | F64: 998900111050 SMS O’ZI, 998332232320 SMS UY, 998882911130 SMS BEGONA, 998990400306 SMS Ozi, 998973125615 SMS AMAKISINI O'G'LI, | G64: QASHQADARYO VILOYATI MUBORAK TUMANI PAXTAKOR MFY QARLIQ QISHLOG’I 7-UY | H64: 3 | I64: 0 | K64: 454 | 2241875.41 | bu yiban oyni oxirida to'laydi
A65: КАШКАДАРЁ ВИЛОЯТИ | B65: Қарши филиали | C65: Ko'tarmadi | D65: Кр-99033221-1 | E65: XAYDAROVA DILSHODA XOLBOYEVNA | F65: 998908248676 SMS O’ZI, 998904645959 SMS UKASI( BEGONA), 998980603836 SMS O'zi , 998918192079 SMS O'ZI, 998906737970 SMS new ozi , | G65: QASHQADARYO VILOYATI QARSHI SHAHAR | H65: 3 | I65: 0 | K65: 465 | 1281226.29
A66: КАШКАДАРЁ ВИЛОЯТИ | B66: Қарши филиали | C66: Ko'tarmadi | D66: Кр-99035313-4 | E66: OMONOV RO’YIDDIN ADASH O’G’LI | F66: 998906167214 SMS OILASI, 998913830559 SMS AKASI UZIII TO'LOVCHI, 998993830559 SMS OILASI, 998914682525 SMS UKASI (POCHCHASI), | G66: QASHQADARYO VILOYATI QARSHI TUMANI TINCHLIK MFY PARMITON QISHLOG’I 13-UY | H66: 3 | I66: 0 | K66: teli ishlamayapti | 575 | 2862542.72
A67: КАШКАДАРЁ ВИЛОЯТИ | B67: Қарши филиали | C67: Ko'tarmadi | D67: Кр-99037441-4 | E67: KOSIMOV ABROR ABDISALOMOVICH | F67: 998887417117 SMS OZI, 998905175558 SMS AKASI BEGONA, 998941729897 SMS JURASI, | G67: QASHQADARYO VILOYATI G’UZOR TUMANI TINCHLIK MFY YANGI TONG KO’CHASI 765-UY | H67: 3 | I67: 0 | K67: raqamlari ioshlamayapti | 713 | 6165206.87
A68: КАШКАДАРЁ ВИЛОЯТИ | B68: Қарши филиали | C68: Ko'tarmadi | D68: Кр-99037758-2 | E68: QURBANOVA HURRIYAT JALILOVNA | F68: 998883134545 SMS O’ZI, 998907211508 SMS ONASI, 998943380255 SMS AKASI, 998912278600 SMS SINGLISI, | G68: QASHQADARYO VILOYATI G’UZOR TUMANI QORAKO’L MFY MASH’AL SHAHARCHASI 01-UY | H68: 3 | I68: 0 | K68: 943380255 dadasi singlisi aytaman ddi | 732 | 6076103.46
A69: КАШКАДАРЁ ВИЛОЯТИ | B69: Қарши филиали | C69: Ko'tarmadi | D69: Кр-99038371-4 | E69: NAMOZOVA SOHIBA SAYFULLAYEVNA | F69: 998889498189 SMS OZI, 998767391002 SMS OZI 2, 998888029100 SMS AYOLI, 998770306991 uzi neww, | G69: QASHQADARYO VILOYATI KOSON TUMANI BOYGUNDI MFY BOYGUNDI QISHLOGI | H69: 3 | I69: 0 | K69: 767 | 3875184.6
A70: КОРАКАЛПОГИСТОН РЕСПУБЛИКАСИ | B70: SUPER BRANCH | C70: Ko'tarmadi | D70: Кр-99035767-1 | E70: DJUMANIYAZOV XUJAAXMAD BERDIBAYEVICH | F70: 998974749400 SMS OZI(Begona), 998336771006 SMS UY, 998975056865 SMS DOSTI(begona), 998331240571 SMS DOSTI, | G70: XORAZM VILOYATI ELLIKQALA TUMANI KASHKURA MAXALLASI YOSH KUCH KUCHASI 2 UY | H70: 6 | I70: 2120990
A71: КОРАКАЛПОГИСТОН РЕСПУБЛИКАСИ | B71: Нукус филиали | C71: Ko'tarmadi | D71: Кр-99063824-1 | E71: BISENOV NURATDIN KDIRBAEVICH | F71: 998905949096 OZI, 998913949096 OYALI, 998932028814 OPASI, | G71: QORAQALPOGISTON RES NUKUS SHAHAR KUM AWIL MFY BELEWKI KUSHASI 2 UY | H71: 3 | I71: 3563984.1
A72: КОРАКАЛПОГИСТОН РЕСПУБЛИКАСИ | B72: Нукус филиали | C72: Ko'tarmadi | D72: Кр-99063812-1 | E72: PRIMBAEV ALLAYAR JOLDASBAEVICH | F72: 998505070888 OZI, 998505151715 OYALI, 998913000209 ONASI, | G72: Qoraqalpogiston res Nukus shahar Shimbay chayxana MFY, Islom Karimov shoh ko’chasi, 151-uy | H72: 3 | I72: 3099150.6
A73: КОРАКАЛПОГИСТОН РЕСПУБЛИКАСИ | B73: Урганч филиали | C73: Ko'tarmadi | D73: Кр-99062856-1 | E73: EGAMBERDIYEVA UMIDA KASIMOVNA | F73: +998883582424 SMS UZI 79858567159 WAT SAP NOMERI, 998885005655 SMS QAYNONASI, 998996814160 SMS QAYNOPASI, | G73: КОРАКАЛПОГИСТОН РЕСПУБЛИКАСИ ТУРТКУЛ ТУМАНИ ТИНЧЛИК МФЙ, ЭРКИН КЎЧАСИ, uy:49 | H73: 31 | I73: 11688398 | K73: muammo
A74: НАВОИЙ ВИЛОЯТИ | B74: Навоий филиали | C74: Ko'tarmadi | D74: Кр-99063463-1 | E74: TO’RAYEVA MARXABO SHOYIMOVNA | F74: 998505258778 TURMUSH O’RTOG’I, 998933187578 O’ZI, 998938601701 QIZI, 998997349060 O’G’LI, | G74: NAVOIY VILOYATI,ZARAFSHON SHAXRI,YANGI ZARAFSHON MFY,BARCHINOY KO’CHASI,56 A UY | H74: 3 | I74: 2810986.4
A75: НАМАНГАН ВИЛОЯТИ | B75: BOSH OFIS | C75: Ko'tarmadi | D75: Кр-99021267-4 | E75: TOXIROV AZIZBEK AVAZBEK O’G’LI | F75: 97-758-02-02 SMS BEGONA EKAN, 94-611-46-45 SMS OZI, 99-879-56-56 SMS ADASI, 88-700-75-74 SMS UKASI, 998772100909 SMS TOLOV QILISH BO, | G75: NAMANGAN VILOYATI NORIN TUMANI YANGI FARG’NA KO’CHASI 3 UY | H75: 3 | I75: 2746385.2 | K75: umuman kotarmayabdi | Стандартрый
A76: НАМАНГАН ВИЛОЯТИ | B76: BOSH OFIS | C76: Ko'tarmadi | D76: Кр-99039926-2 | E76: AZIZOV RAVSHANJON XAKIMJON O’G’LI | F76: 998931731298 SMS OZI, 998931545616 SMS AKASI, 998932119301 SMS AKASI, 998939246202 SMS OTASI, | G76: NAMANGAN VILOYATI NORIN TUMANI SUZOQOVUL MFY TOSHQO'RG'ON KO'CHASI 52-UY | H76: 3 | I76: 1009794.2 | K76: umuman kotarmayabdi | Стандартрый
A77: НАМАНГАН ВИЛОЯТИ | B77: SUPER BRANCH | C77: Ko'tarmadi | D77: Кр-99036518-2 | E77: XADJIMIRZAYEVA NAZOKAT MAXMUDOVNA | F77: 998902793272 SMS OZI TO’LQIN AKANI SINGLI BU, 998905545758 SMS AKASI, 998880501317 SMS QIZI, 998972503003 SMS AKASI, 998907415736 SMS ERI NAZOKATNI , | G77: NAMANGAN VILOYATI NAMANGAN SHAHAR TUKUVCHI MFY AEROPORT KO’CHASI 3 A UY | H77: 125 | I77: 1.1412083e+08 | K77: filial xal qiladi | Плохой
A78: НАМАНГАН ВИЛОЯТИ | B78: SUPER BRANCH | C78: Ko'tarmadi | D78: Кр-99035789-2 | E78: MAVLONOVA MUQADDAM BOQIYEVNA | F78: 998943491849 SMS O’ZI, 998930587200 SMS BEGONA EKAN , 998993907200 SMS O’G’LI , 998505005495 SMS O’G’LI 2, 998947452200 O'G'LI WU ISHLAYDI, | G78: NAMANGAN VILOYATI NORIN TUMANI QOZOQOVUL MFY LOXHIN KO’CHA 248 UY | H78: 153 | I78: 44020739 | K78: filial xal qiladi | Плохой
A79: НАМАНГАН ВИЛОЯТИ | B79: SUPER BRANCH | C79: Ko'tarmadi | D79: Кр-99035342-1 | E79: QORABOYEVA INOYATXON SHERTOYEVNA | F79: 998950780375 SMS O’ZI, 998332577277 SMS ERI, 998932577277 SMS ERI, 998944049919 SMS O’G’LI, | G79: ANDIQJON VILOYATI BALIQCHI TUMANI GO’ROVON MFY GO’ROVON KO’CHA 20 UY | H79: 175 | I79: 20202829 | K79: filial xal qiladi | Плохой
A80: НАМАНГАН ВИЛОЯТИ | B80: SUPER BRANCH | C80: Ko'tarmadi | D80: Кр-99039848-1 | E80: ABDURAXMONOV ABRORBEK ODILJON O’G’LI | F80: 998931910095 SMS OZI, 998946730089 SMS AYOLI, 998938523989 SMS DADASI, 998938471965 SMS ONASI, | G80: NAMANGAN VILOYATI NORIN TUMANI QORATERI MFY GULZOR KOCHASI 42-UYNI | H80: 3 | I80: 9406764.5 | K80: umuman kotarmayabdi | Стандартрый
A81: НАМАНГАН ВИЛОЯТИ | B81: SUPER BRANCH | C81: Ko'tarmadi | D81: Кр-99039132-1 | E81: AZIMOV MUXAMMADAZIM ABDUG’OPUR O’G’LI | F81: 998332090009 SMS OZI, 998995240770 SMS AKASI, 998996466206 SMS DADASI, 998913602980 SMS ONASI уртогини онаси, 998934068282 SMS QIZI , | G81: NAMANGAN VILOYATI NAMANGAN SHAHAR ISHONCH MFY YANGI QURG’ON KO’CHASI 44-XONADON | H81: 171 | I81: 8442308.6 | K81: filial xal qiladi | Плохой
A82: НАМАНГАН ВИЛОЯТИ | B82: SUPER BRANCH | C82: Ko'tarmadi | D82: Кр-99025455-6 | E82: XALBEKOV ULUGBEK NURMAMATOVICH | F82: 90-215-47-43 SMS OZI, 93-677-72-02 SMS OZI 2, 93-495-27-03 SMS ONASI (BEGONA), | G82: NAMANGAN SHAHAR DASHTBOG’ MFY 3-PROEZD G’IRVONSOY KO’CHA 18 UY | H82: 3 | I82: 5231528 | K82: umuman kotarmayabdi | Стандартрый
A83: НАМАНГАН ВИЛОЯТИ | B83: SUPER BRANCH | C83: Ko'tarmadi | D83: Кр-99021020-4 | E83: ABDULLAYEV RAXMATULLOX MUXSIN O‘G‘LI | F83: 93-816-22-22 SMS UZI BEGONA, 90-792-00-77 SMS UZI 2, 88-250-00-05 SMS AKASI, 88-254-00-05 SMS ISHXONA begona, | G83: NAMANGAN SHAHRI G‘UNCHA MFY G‘UNCHA TOR KO‘CHASI 2 UY | H83: 6 | I83: 4938578.4 | K83: umuman kotarmayabdi | Стандартрый
A84: НАМАНГАН ВИЛОЯТИ | B84: SUPER BRANCH | C84: Ko'tarmadi | D84: Кр-99040215-1 | E84: TURSINOV ISROIL IBRAXIMOVICH | F84: 998946169088 SMS OZI, 998931272590 SMS AYOLI, 998943002955 SMS DADASI, 998333633339 SMS Orifjon begona, | G84: NAMANGAN VILOYATI KOSONSOY TUMANI CHAK MFY MO'YNOQ KO'CHASI | H84: 3 | I84: 3787838.7 | K84: umuman kotarmayabdi | Стандартрый
A85: НАМАНГАН ВИЛОЯТИ | B85: SUPER BRANCH | C85: Ko'tarmadi | D85: Кр-99039958-1 | E85: MUSABOYEVA MASHHURAXON BOYMIRZA QIZI | F85: 998504005151 SMS OZI, 998947580220 SMS MOSHINANI SOTGAN ODAM, 998942701133 SMS OZI, | G85: NAMANGAN VILOYATI YANGIQO’RG’ON TUMANI QIZILYOZI MFY TEMURIYLAR KO’CHASI 41 UY | H85: 3 | I85: 3302501.6 | K85: umuman kotarmayabdi | Стандартрый
A86: НАМАНГАН ВИЛОЯТИ | B86: SUPER BRANCH | C86: Ko'tarmadi | D86: Кр-99027270-3 | E86: ISLOMOV MAMADALIXON TOLIBXON O’G’LI | F86: 95-000-22-92 SMS O'ZI, 99-398-23-92 SMS OZ'I 2, 91-365-08-04 SMS AYOLI, 91-355-24-41 SMS UKASI, 93-490-51-33 ozi , 913552441 SMS UKASI, 913650804 SMS AYOLI, 934905133 ozi, 950002292 SMS O’ZI, 993982392 SMS OZ’I 2, | G86: ЧИНДОВУЛ ҚФЙ, ЧИНДОВУЛ МФЙ, ЯНГИ АВЛОД КЎЧАСИ, uy:Р/С | H86: 3 | I86: 2789623 | K86: umuman kotarmayabdi | Хороший
... A119: НАМАНГАН ВИЛОЯТИ | B119: Наманган филиали | C119: Ko'tarmadi | D119: Кр-99038674-2 | E119: UMAROV JASURBEK SHOKIRJON O’G’LI | F119: 998888253113 SMS OZI, 998911831310 SMS ONASI, 998956242252 SMS AYOLI, 998956242242 SMS ONASI, | G119: NAMANGAN VILOYATI DAVLATOBOD TUMANI YANGI TONG MFY 5-KICHIK NOXIYA 5 UY 16 XONADON | H119: 3 | I119: 662684.26 | K119: umuman kotarmayabdi | Хороший
A120: НАМАНГАН ВИЛОЯТИ | B120: Наманган филиали | C120: Ko'tarmadi | D120: Кр-99035006-1 | E120: TO’LASHEV BUNYOD QODIROVICH | F120: 998938747687 SMS OZI, 998946748720 SMS AYOLI, 998947031969 SMS ONASI, 998975748727 SMS OSHNASI, | G120: NAMANGAN VILOYATI UYCHI TUMANI BO’STON MFY SHAFTOLI KO’CHA 58 UY | I120: 399429.51 | K120: umuman kotarmayabdi | Отличный
A121: НАМАНГАН ВИЛОЯТИ | B121: Наманган филиали | C121: Ko'tarmadi | D121: Кр-99030304-1 | E121: TOSHBOLTIYEV JASURBEK XOLMAMATOVICH | F121: 99-516-37-47 SMS O’ZI, 99-147-05-86 SMS AYOLI, 94-309-20-05 SMS BEGONA, 998941883747 SMS O’ZI, | G121: NAMANGAN VILOYATI YANGIQO’RG’ON TUMANI NAVKENT MFY TUTZOR KO’CHASI 45 UY | I121: 201414.72 | K121: umuman kotarmayabdi | Стандартрый
A122: САМАРКАНД ВИЛОЯТИ | B122: SUPER BRANCH | C122: Ko'tarmadi | D122: Кр-99063884-1 | E122: ABDURASHIDOV AKOBIR VASLIDDIN O’G’LI | F122: 998777162444 SMS DOSTI, 998943414303 SMS UZI, 998993961270 SMS TOLOVCHI, 998339154303 SMS, | G122: ДУРБЕШ ҚФЙ, ЯНГИРАВОТ МФЙ, ДУРБЕШ ҚИШЛОҒИ, uy:Р/С | H122: 31 | I122: 4782948.9 | K122: 2226
A123: САМАРКАНД ВИЛОЯТИ | B123: Навоий филиали | C123: Ko'tarmadi | D123: Кр-99064059-2 | E123: NUNNAYEV RAXIM MAMAREJABOVICH | F123: 998930982612 SUNGLISI, 998944839282 O’ZI, 998950515155 UKASI, | G123: SAMARQAND VILOYATI PAXTACHI TUMANI QORATEPA MFYETIQOD KO’CHASI 57 UY | H123: 3 | I123: 2288775.8 | K123: 2279
A124: САМАРКАНД ВИЛОЯТИ | B124: Самарқанд филиали | C124: Ko'tarmadi | D124: Кр-99004970-4 | E124: MAVLANOV ABRORBEK UTKIROVICH | F124: 99-567-66-69 SMS, 99-952-22-57 SMS JURASI, 90-193-84-85 SMS UKASI, 98-808-81-86 AKASI tanimiman, 97-599-95-95 sms akasi, 975767717 YANGI, +998200023117 SMS OZI, 998901938485 SMS UYI, 998991319994 SMS AKASI, 998998653127 SMS UKASI, | G124: SAMARQAND VILOYATI PAYARIQ SHAHRI MUSTAQILLIK MFY SHIRIN KUCHASI 25-XONODON | H124: 3 | I124: 17397475 | K124: 13
A125: САМАРКАНД ВИЛОЯТИ | B125: Самарқанд филиали | C125: Ko'tarmadi | D125: Кр-99004970-5 | E125: MAVLANOV ABRORBEK UTKIROVICH | F125: 99-567-66-69 SMS, 99-952-22-57 SMS JURASI, 90-193-84-85 SMS UKASI, 98-808-81-86 AKASI tanimiman, 97-599-95-95 sms akasi, 975767717 YANGI, +998200023117 SMS OZI, 998901938485 SMS UYI, 998991319994 SMS AKASI, 998998653127 SMS UKASI, | G125: SAMARQAND VILOYATI PAYARIQ SHAHRI MUSTAQILLIK MFY SHIRIN KUCHASI 25-XONODON | H125: 3 | I125: 7391226.9 | K125: 14
A126: САМАРКАНД ВИЛОЯТИ | B126: Самарқанд филиали | C126: Ko'tarmadi | D126: Кр-99063880-1 | E126: NABIYEV IKROM BAXTIYOROVICH | F126: +998970933337 SMS OZI, 998883911900 SMS AYOLI, 998976043333 SMS UKASI, 998979070010 SMS OZI 2, | G126: XAMID OLIMJOM KUCHASI 28-UY | H126: 3 | I126: 6209608.8 | K126: 2224
A127: САМАРКАНД ВИЛОЯТИ | B127: Самарқанд филиали | C127: Ko'tarmadi | D127: Кр-99064168-1 | E127: XUSINOV SHUXRAT ABDUSAMATOVICH | F127: 998915256141 SMS SINGLISI, 998933322925 SMS UKASI, 998975775460 SMS OZI, | G127: SAMARQAND VILOYATI SAMARQAND TUMANI PULIMUG’OB MFY PULIMUG’OV KUCHASI 19-UY | H127: 3 | I127: 5317043 | K127: 2304
A128: САМАРКАНД ВИЛОЯТИ | B128: Самарқанд филиали | C128: Ko'tarmadi | D128: Кр-99064046-1 | E128: BERDIYEV DAMIR ILXOMOVICH | F128: 998871942323 SMS OZI, 998905055476 SMS ONASI, 998933458727 SMS DADASI, | G128: SAMARQAND VILOYATI SAMARQAND SHAHAR TOJMAXAL MFY ABU BAKR ROZI 10 DOM 40 KVARTERA | H128: 3 | I128: 3278356.4 | K128: 2275
A129: САМАРКАНД ВИЛОЯТИ | B129: Самарқанд филиали | C129: Ko'tarmadi | D129: Кр-99064204-1 | E129: HAYDAROV SAIDJON ASHRAF O’G’LI | F129: 998701703698 SMS OZI, 998901911594 SMS XOLASI, 998903134020 SMS UKASI, 998915203518 SMS ONASI, | G129: SAMARQAND VILOYATI SAMARQAND TUMANI CHORSHANBA MFY | H129: 3 | I129: 2356207.4 | K129: 2309
A130: САМАРКАНД ВИЛОЯТИ | B130: Самарқанд филиали | C130: Ko'tarmadi | D130: Кр-99063208-1 | E130: AZIZOV G’IYOSBEK ABDIMURODOVICH | F130: 998771229933 SMS UYI, 998889229933 SMS OZI, 998982220922 SMS OZI 2, | G130: SAMARQAND VILOYATI PASTDARG’OM TUMANI GALATUT MFY YUQORI QISHLOG’I 124-UY | I130: 1343585.6 | K130: 2033
A131: САМАРКАНД ВИЛОЯТИ | B131: Самарқанд филиали | C131: Ko'tarmadi | D131: Кр-99064250-1 | E131: OTABEKOV DIYORBEK OTABEK O’G’LI | F131: 998933277002 SMS OZI, 998505005950 SMS AKASI, 998888912429 SMS AYASI, | G131: SAMARQAND VILOYATI URGUT TUMANI JARTEPA MFY 96-UY | H131: 3 | I131: 1119348 | K131: 2322
A132: САМАРКАНД ВИЛОЯТИ | B132: Самарқанд филиали | C132: Ko'tarmadi | D132: Кр-99063793-2 | E132: ISMAILOVA ZAYNAB XXX | F132: +998915364039 SMS OZI, 998902129909 SMS SINGLISI, 998916290180 SMS OPASI, 998952321587 SMS JIYANI, | G132: SAMARQAND VILOYATI PASTDARG’OM TUMANI MIRZATUP MAHALLASI NARPAY KUCHASI 88-UY | H132: 3 | I132: 819543.15 | K132: 2188
...

Sheet Объезд
A1: ← Вернуться в отчёт
A2: Область | B2: Филиал | C2: Группа | D2: Код клиента | E2: Клиент | F2: Номер телефона | G2: Адрес | H2: Кол-во просроченных дней | I2: Итого просрочка | J2: Оплата | K2: Izoh
A3: АНДИЖОН ВИЛОЯТИ | B3: SUPER BRANCH | C3: Объезд | D3: Кр-99063020-2 | E3: XALIMOV ILXOMJON DJALILOVICH | F3: 998979950022 OZI, 998941030105 ONASI, 998945616463 JIYANI Begona, 998993478909 KELINI begona , | G3: ANDIJON VILOYATI ASAKA TUMANI BOBUR MFY KARVONSAROY KO’CHASI 135 UY | H3: 3 | I3: 7603998.2
A4: АНДИЖОН ВИЛОЯТИ | B4: SUPER BRANCH | C4: Объезд | D4: Кр-99057460-1 | E4: ONORBOY O’G’LI PULATJON XXX | F4: 998953135155 SMS UZI, 998954616995 SMS AYOLI, 998902025254 SMS AKASI Begona, 998772639874 SMS OPASI, | G4: ANDIJON VILOYATI QO’RG’ONTEPA TUMANI DARDOK, NAVOIY MFY YANGI OBOD KO’CHASI 334-UY | H4: 3 | I4: 6326912.3
A5: АНДИЖОН ВИЛОЯТИ | B5: SUPER BRANCH | C5: Объезд | D5: Кр-99061829-1 | E5: JO’RAYEV BAXTIYAR BAZAROVICH | F5: 998994380553 ozi, 998944172190 ayoli, 998500450753 ogli, | G5: Манзил: ANDIJON VILOYATI ASAKA TUMANI FAROVON MFY UZUN KO’CHASI 64-UY | H5: 3 | I5: 6320702.6
A6: АНДИЖОН ВИЛОЯТИ | B6: SUPER BRANCH | C6: Объезд | D6: Кр-99061813-1 | E6: AXMEDOVA LOLAXON XASANOVNA | F6: 998939680860 узи, 998948093111 угли, 998772093139 угли, 998990300805 угли, | G6: ANDIJON VILOYATI IZBOSKAN TUMANI CHEKYO MFY ABU ALI IBN SINO KO’CHASI 27-UY | H6: 3 | I6: 5689271
A7: АНДИЖОН ВИЛОЯТИ | B7: SUPER BRANCH | C7: Объезд | D7: Кр-99052625-1 | E7: SHAMATOVA MAXMUDAXON UMIDJON QIZI | F7: 998916120121 SMS OZI, 998885937444 SMS ONASI, 998889680010 SMS OTASI, 998907585855 SMS OPASI, | G7: ANDIJON VILOYATI ANDIJON TUMANI SADDATAGI MFY CHEK KO’CHASI 87-UY | H7: 3 | I7: 5067127.6
A8: АНДИЖОН ВИЛОЯТИ | B8: SUPER BRANCH | C8: Объезд | D8: Кр-99040471-1 | E8: ABDULLAYEVA FERUZAXON RAPIKOVNA | F8: 998958551476 SMS OZI, | G8: ANDIJON VILOYATI XO’JAOBOD TUMANI KO’PRIKBOSHI MFY, KO’CHAK KO’CHASI 64-UY | H8: 3 | I8: 4454025.4
A9: АНДИЖОН ВИЛОЯТИ | B9: SUPER BRANCH | C9: Объезд | D9: Кр-99034299-2 | E9: MAMADALIYEVA ZUXRAXON BAXROMOVNA | F9: 998979939062 SMS TOLOVCHI, 998889990036 SMS OGLI, 998889991060 SMS OGLI, 998999722052 SMS OZI, | G9: ANDIJON VILOYATI ASAKA TUMANI CHEK MFY, FARG’ONA KATTA YO’LI KO’CHASI | H9: 3 | I9: 4176578.4
A10: АНДИЖОН ВИЛОЯТИ | B10: SUPER BRANCH | C10: Объезд | D10: Кр-99036805-2 | E10: BESHBAYEVA OYAT KASIMOVA | F10: 998979805801 SMS ozi , 998950012711 SMS ogli , 998501114027 SMS kelini , 998938252911 SMS ukasi , 998979805801 SMS ozi , | G10: ANDIJON SHAHRI | H10: 3 | I10: 857160.13
A11: АНДИЖОН ВИЛОЯТИ | B11: SUPER BRANCH | C11: Объезд | D11: Кр-99038275-3 | E11: KARIMOVA XAMROXON MO’YDINOVNA | F11: 998508831410 SMS OZI, 998948881410 SMS OGLI, 998916012492 SMS KELINI, 998937359892 SMS AKASI, | G11: ANDIJON VILOYATI SHAXRIXON TUMANI YANGIMAXALLA MFY, OBOD KO’CHASI 75/1-UY | H11: 3 | I11: 661666.93
A12: АНДИЖОН ВИЛОЯТИ | B12: SUPER BRANCH | C12: Объезд | D12: Кр-99038275-2 | E12: KARIMOVA XAMROXON MO’YDINOVNA | F12: 998508831410 SMS OZI, 998948881410 SMS OGLI, 998916012492 SMS KELINI, 998937359892 SMS AKASI, | G12: ANDIJON VILOYATI SHAXRIXON TUMANI YANGIMAXALLA MFY, OBOD KO’CHASI 75/1-UY | H12: 3 | I12: 620943.56
A13: АНДИЖОН ВИЛОЯТИ | B13: Андижон филиали | C13: Объезд | D13: Кр-99062881-1 | E13: DJALILOVA SAXIBAXON XAMIDJANOVNA | F13: +998945131961 SMS O’ZI, 998933171152 SMS KELINI, 998934373105 SMS XO’JAYNI, 998998439222 SMS O’G’LI, | G13: ANDIJON VILOYATI OLTINKO’L TUMANI ITTIFOQ MFY QO’RG’ONCHA KO’CH ASI 32-UY | H13: 3 | I13: 9270849
A14: АНДИЖОН ВИЛОЯТИ | B14: Андижон филиали | C14: Объезд | D14: Кр-99062903-1 | E14: BAZARBAYEV ISMOILJON IBRAXIMOVICH | F14: +998902581505 SMS O’ZI, 998774300260 SMS AYOLI, 998932477040 SMS UY, 998943338444 SMS O’ZI 2 Begona , | G14: ANDIJON VILOYATI ANDIJON SHAHAR XAMDO’STLIK MFY IFTIXOR KO’CHASI 64-UY | H14: 3 | I14: 7524699.7
... A19: АНДИЖОН ВИЛОЯТИ | B19: Андижон филиали | C19: Объезд | D19: Кр-99057395-2 | E19: SOBIROV AXMADULLOX MUXAMMADJON O’G’LI | F19: 998979712424 SMS UZI, 998887527779 AKASI, 998884104045 SMS KELNOYISI, 998972040525 SMS DADASI, +998979712424 SMS O’ZI, 998942493838 SMS AKASI, | G19: ANDIJON VILOYATI OLTINKO’L TUMANI CHO’NTAK MFY, MUSTAQILLIK KO’CHASI 227-UY | H19: 6 | I19: 916555.64
A20: БУХОРО ВИЛОЯТИ | B20: SUPER BRANCH | C20: Объезд | D20: Кр-99030177-2 | E20: RAXMATOV YO’LDOSH ZOYIR O’G’LI | G20: BUXORO VILOYATI VOBKENT TUMANI QURUVCHI MFY, O'ZBEKISTON KO'CHASI, 196-UY | H20: 3 | I20: 1820966 | K20: BUNI UYIGA BORILDI BU 20CHIDAGI TO'LOVI BN BITTA QILIB TO'LARKAN | 336
A21: КАШКАДАРЁ ВИЛОЯТИ | B21: SUPER BRANCH | C21: Объезд | D21: Кр-99040255-1 | E21: TO’RAYEVA INTIZOR HUSAN QIZI | F21: 998991985752 SMS OZI, 998976701098 SMS AYOLI, 998995078900 SMS DADASI, 998915004348 узи , | G21: QASHQADARYO VILOYATI KASBI TUMANI MIRZO ULUG’BEK MFY BAYDOQCHI QISHLOG’I ABDULLA ORIPOV KUCHASI 5-UY | I21: 1120087.3
A22: КАШКАДАРЁ ВИЛОЯТИ | B22: Қарши филиали | C22: Объезд | D22: Кр-99049163-1 | E22: PULATOV ALISHER YULDASHKULOVICH | F22: +998972410500 UZIII, 998333191148 dadasi, 998973811370 onasi, | G22: КАШКАДАРЁ ВИЛОЯТИ ШАХРИСАБЗ ШАХРИ Навруз МФЙ Навруз кучаси 4-уй | H22: 3 | I22: 4599588.3
A23: КАШКАДАРЁ ВИЛОЯТИ | B23: Қарши филиали | C23: Объезд | D23: Кр-99040472-1 | E23: SHAXAROVA SHAXRIZODA FARXOD QIZI | F23: 998886727122 SMS OZI BEGONA, 998970809786 SMS AKASI, 998995850151 SMS OZI , 998945228482 SMS ZALOGADATEL , 998912120151 SMS NEW UZI , | G23: ЧУМИЧЛИ МФЙ, ЧУМИЧЛИ КИШЛОГИ, uy:Р/С | H23: 204 | I23: 0 | K23: auksion | 1027 | 47747641.76
A24: НАМАНГАН ВИЛОЯТИ | B24: SUPER BRANCH | C24: Объезд | D24: Кр-99040115-1 | E24: SIDDIKOV JAMOLIDDIN BOTIRALIYEVICH | F24: 998931704442 SMS OZI, 998505892915 SMS OGLI, 998936998187 SMS AYOLI, 998932162300 SMS JIYANI, | G24: NAMANGAN VILOYATI NAMANGAN TUMANI ELATAN MFY ELATAN KO'CHASI 83-UY | H24: 3 | I24: 1279577.3 | K24: yopildi | Хороший
A25: НАМАНГАН ВИЛОЯТИ | B25: Наманган филиали | C25: Объезд | D25: Кр-99064601-1 | E25: INAMOV XABIBILLA ABDUMAJIDOVICH | F25: 998500542166 SMS O’ZI, 998505991966 SMS AYOLI, 998885250506 SMS O’G’LI, | G25: NAMANGAN VILOYATI NAMANGAN TUMANI MALLAXOVUZ MFY ALISHER NAVOIY KO’CHASI 32-UY | H25: 3 | I25: 3071438.8 | K25: yopildi | Хороший
A26: НАМАНГАН ВИЛОЯТИ | B26: Наманган филиали | C26: Объезд | D26: Кр-99064363-1 | E26: XOLMATOV FARXOD AXMADALIYEVICH | F26: 998950860626 SMS O’ZI, 998946520122 SMS SINGLISI, 998992268606 SMS UKASI, | G26: НАМАНГАН ВИЛОЯТИ УЙЧИ ТУМАНИ ЯНГИХАЁТ МФЙ АДИБЛАР КЎЧАСИ 1-УЙ | H26: 3 | I26: 984668.81 | K26: yopildi | Хороший
A27: СУРХОНДАРЁ ВИЛОЯТИ | B27: BOSH OFIS | C27: Объезд | D27: Кр-99041744-1 | E27: KARIMOVA MADINA SOTTOR QIZI | F27: 998975527101 SMS OZI, 998881927101 SMS UY, 999872010159 SMS OILASI, 998785510044 SMS UKASI, 998957737555 SMS ERI, | G27: SURXONDARYO VILOYATI DENOV TUMANI BUYUKIPAK YULI MFY I.KARIMOV 70-UY | H27: 3 | I27: 1024654.7 | K27: 2-3 kunda tolo qlad | 1201
A28: СУРХОНДАРЁ ВИЛОЯТИ | B28: SUPER BRANCH | C28: Объезд | D28: Кр-99007175-2 | E28: KOHAROV USMON ERGASHOVICH | F28: 91-580-94-59 SMS, 90-747-47-68 SMS XOTINI NILUFDAR OPA, 91-513-87-87 SMS O’G’LI MIROLIM, 99-979-13-85 SMS UY, | G28: SURXONDARYO VILOYATI QUMQO’RG’ON TUMANI NAVBAHOR MFY AT-TERMIZIY KO’CHASI 7-UY | H28: 3 | I28: 5873438.7 | K28: usmon bn gaplawdm oglmga etaman tolo qlad dd | 28
A29: СУРХОНДАРЁ ВИЛОЯТИ | B29: SUPER BRANCH | C29: Объезд | D29: Кр-99053658-1 | E29: MUROTALIV BEKMUROD XAITMUROT O’G’LI | F29: 998773737223 SMS OZI, 998200295964 SMS OZI, 998954405859 SMS OANSI, 998915833844 SMS AKASI, 998950199165 SMS ozi new, | G29: SURXONDARYO VILOYAT QUMQURG’ON TUMAN GULTEPA MFY BOYQISHLOQ KO’CHASI 252-UY | H29: 31 | I29: 5099952.1 | K29: oy oxrgaca tolo qlad | 1544
A30: СУРХОНДАРЁ ВИЛОЯТИ | B30: SUPER BRANCH | C30: Объезд | D30: Кр-99038658-1 | E30: XO’JAMURODOV ORZUBEK AHMAD O’G’LI | F30: 998919050123 SMS OZI, 998904804646 SMS OZI 2, 998915128040 SMS AKASI, 998998179399 SMS UYI, | G30: SURXONDARYO VILOYATI SHO’RCHI TUMANI BOBUR MFYAT-TERMIZI 14-UY | H30: 3 | I30: 3503608.3 | K30: bugun tolo qlad | 789
A31: СУРХОНДАРЁ ВИЛОЯТИ | B31: SUPER BRANCH | C31: Объезд | D31: Кр-99009967-4 | E31: SANGILOVA MOXIRA RAXIMOVNA | F31: 97-807-77-97 SMS, 99-678-23-45 SMS O’ZI, 99-360-50-13 SMS JIYANI MIRVALI, 88-808-97-02 SMS UY, 998915163497 SMS UY, | G31: ҚИЗИЛЖАР ҚФЙ, БУЮК ИПАК ЙЎЛИ МФЙ, ҚИЗИЛЖАР ҚФЙ, БУЮК ИПАК ЙЎЛИ МФЙ, БУЮК ИПАК ЙЎЛИ, uy:Б/Н | H31: 3 | I31: 2599124.1 | K31: abetan kyn ofisga otad | 45
A32: СУРХОНДАРЁ ВИЛОЯТИ | B32: SUPER BRANCH | C32: Объезд | D32: Кр-99034163-2 | E32: XOLMATOV BEKZOD NORTOJIYEVICH | F32: 998910790909 SMS O’ZI, 998951755754 SMS UY, 998919012266 SMS DADASI, 998952757552 SMS UKASI, 998954370777 ozi new new, | G32: SURXONDARYO VILOYATI DENOV TUMANI ZARAFSHON MFY FIDOKAR K’OCHASI 6- UY | H32: 6 | I32: 2339584.8 | K32: bugun erte tolo qlad | 521
A33: СУРХОНДАРЁ ВИЛОЯТИ | B33: SUPER BRANCH | C33: Объезд | D33: Кр-99011132-5 | E33: XUDOYQULOV SHOHZOD ODILOVICH | F33: 99-304-62-77 SMS, 99-021-77-78 SMS SHERIGI OTABEK, 33-000-90-79 SMS UY, 33-037-07-00 SMS O’ZI tanimas ekan, 998702178219 OZI YANGI NOMERI, 998880768206 ONASI, 998887079807 UY, 998971511204 DO’STI, 998977778209 O’ZI, | G33: SURXONDARYO VILOYATI SHO’RCHI TUMANI DALVARZIN QFY EGARCHI MFY ADIR KO’CHASI 6-UY | H33: 3 | I33: 1188918 | K33: bugun tolo qlad | 51
A34: СУРХОНДАРЁ ВИЛОЯТИ | B34: SUPER BRANCH | C34: Объезд | D34: Кр-99011383-5 | E34: BURONOV ESHMAMAT KENJAYEVICH | F34: 99-179-87-70 SMS OZI FERMER , 33-707-44-94 SMS O’G’LI FAXRIDDIN, 91-517-57-59 SMS SO’G’LI BAXROM, 90-378-57-59 SMS ZALOGADATEL, 998953169515 SMS ugli QUVONCHBEK TOSHDA YURIDIKDA UQIDI , 998955545759 OGLI BAXROM, 998952380056 SMS O'ZI, 998883510272 MAHALLA RAISI, 998994551664 RUSTAM AKA QOSHNISI , | G34: SURXONDARYO VILOYATI DENOV TUMANI BINOKOR QFY OZOD MFY TERAKZOR KO’CHASI 89-UY | H34: 3 | I34: 1140969.8 | K34: kyng xafta tolo qlad | 53
... A42: СУРХОНДАРЁ ВИЛОЯТИ | B42: Денов филиали | C42: Объезд | D42: Кр-99041744-2 | E42: KARIMOVA MADINA SOTTOR QIZI | F42: 998975527101 SMS OZI, 998881927101 SMS UY, 999872010159 SMS OILASI, 998785510044 SMS UKASI, 998957737555 SMS ERI, | G42: SURXONDARYO VILOYATI DENOV TUMANI BUYUKIPAK YULI MFY I.KARIMOV 70-UY | H42: 3 | I42: 659652.09 | K42: 2-3 kunda tolo qlad | 1202
A43: ТОШКЕНТ ШАХРИ | B43: BOSH OFIS | C43: Объезд | D43: Кр-99053309-2 | E43: SULTANOV OYBEK KARIMDJANOVICH | F43: +998938440445 Primary phone from road24, 998938440445 Primary phone from road24, 998712923966 sms uy, 998998440441 sms ayoli, 998998440445 sms uzi, | G43: Тошкент шахри Бектемир тумани Musaffo МФЙ, Хислат кучаси, 311-uy | H43: 3 | I43: 2480862.5
A44: ТОШКЕНТ ШАХРИ | B44: BOSH OFIS | C44: Объезд | D44: Кр-99039458-2 | E44: SHARIPOV BAXODIR ATAXANOVICH | F44: 998333930802 SMS QIZI, 998889964445 SMS OZI, 998914237477 SMS AYOLI, | G44: г. Ташкент, Чиланзарский район, кв. 19, Шухрат МСГ, 29- Дом, 49- Квартира | H44: 3 | I44: 1268967.4 | K44: 846 | 20000000 | 474533.2
A45: ТОШКЕНТ ШАХРИ | B45: SUPER BRANCH | C45: Объезд | D45: Кр-99040408-4 | E45: XODIYEV FARRUX FURQAT O’G’LI | F45: 998995705902 SMS OZI, 998977357760 SMS SHERIGI, 998817877602 SMS SHERIGI 2, | G45: TOSHKENT SHAHAR YUNUSOBOD TUMANI 11 KVARTAL,57-UY,46-XONADON | H45: 3 | I45: 13858285
A46: ТОШКЕНТ ШАХРИ | B46: SUPER BRANCH | C46: Объезд | D46: Кр-99042127-1 | E46: ABDULLAYEVA SHAXLO SHARIFJONOVNA | F46: 998953205678 SMS OZI begona , 998909813239 SMS ozi , 998946449886 SMS ogli , 998917829977 SMS eri , | G46: TOSHKENT SHAHAR YUNUSOBOD TUMANI TIKLANISH MFY TIKLANISH PROEZD 6 KOCHASI 2-UY | H46: 31 | I46: 12146083
A47: ТОШКЕНТ ШАХРИ | B47: SUPER BRANCH | C47: Объезд | D47: Кр-99037797-1 | E47: MUXTAROV BAXODIR SUNATOVICH | F47: 998934231010 SMS OZI, 998997061818 SMS AKAASI, 998917178280 SMS OGLI (begona), | G47: TOSHKENT SHAHAR SHAYXONTOXUR TUMANI CHORSU MAYDONI CHAKAR MFY 4-UY, 9-XONADON | H47: 13 | I47: 8416532.3
A48: ТОШКЕНТ ШАХРИ | B48: SUPER BRANCH | C48: Объезд | D48: Кр-99046637-1 | E48: KURBANOVA SHAXLO XALNAZAROVNA | F48: 998974145451 SMS SINGLISI, 998977164240 SMS OZI, 998977508351 SMS ONASI, | G48: YUNUSOBOD 4 87-UY.64-XONADON | H48: 3 | I48: 7149862.5
A49: ТОШКЕНТ ШАХРИ | B49: SUPER BRANCH | C49: Объезд | D49: Кр-99011499-53 | E49: SHODIYEVA ZIYODAJON SADULLAYEVNA | F49: 90-326-00-94 SMS BEGZOD AKA SHEF TEL QLNMASIN , +998903260094 , | G49: TOSHKENT SHAHAR MIRZO ULUGBEK TUMANI ALI ISAMUXAMEDOV 31 | H49: 3 | I49: 5726223.2
A50: ТОШКЕНТ ШАХРИ | B50: SUPER BRANCH | C50: Объезд | D50: Кр-99038147-3 | E50: NAJMITDINOVA BUSTON KAMALOVNA | F50: 998338958507 SMS OZI, 998900261575 SMS KUYOVI, 998949594075 SMS QIZI, | G50: TOSHKENT SHAHAR MIRZO ULUG’BEK TUMANI, 1-PILLA KO’CHASI,115-UY | H50: 3 | I50: 5676169.7
A51: ТОШКЕНТ ШАХРИ | B51: SUPER BRANCH | C51: Объезд | D51: Кр-99037552-2 | E51: UMAROV MUZAFFAR YULDOSHEVICH | F51: 998998254660 SMS OZI "ASEPTICA" MAS'ULIYATI CHEKLANGAN JAMIYAT / Қўриқлаш (ҳарбийлашган, ёнғиндан сақланиш, қоровуллик) бошлиғи, 998998154660 SMS AYOLI, 998338954660 SMS QIZI, 998945548830 SMS OGLI, | G51: TOSHKENT SHAHAR YUNUSOBOD TUMANI TURKISTON MFY,6-MAVZE,30-UY,6-XONADON | H51: 3 | I51: 5002771.7
A52: ТОШКЕНТ ШАХРИ | B52: SUPER BRANCH | C52: Объезд | D52: Кр-99017798-7 | E52: MAVLYANOVA NARGIZA TAGIROVNA | F52: 90-139-55-44 SMS, 90-941-24-91 SMS, 90-808-36-11 SMS, 93-504-22-04 SMS Ozi 2, | G52: Тошкент шахар Юнусобод тумани 14-мавзе 53-уй 55-хонадон | H52: 2 | I52: 3885049.4 | K52: 10 kun tolab beradi
A53: ТОШКЕНТ ШАХРИ | B53: SUPER BRANCH | C53: Объезд | D53: Кр-99028345-4 | E53: KASIMOV MIRJAMOL MIRAZIZOVICH | F53: 998991983322 SMS OZI, 998991303000 SMS OGLI SARDOR, 998971704411 SMS OZI 2, | G53: TOSHKENT SHAHAR SHAYXONTOXUR TUMANI OBINAZIR MFY GULOBOD MAVZESI 23-UY 12-XONADON | H53: 6 | I53: 3482613.5
A54: ТОШКЕНТ ШАХРИ | B54: SUPER BRANCH | C54: Объезд | D54: Кр-99039501-2 | E54: QORIYEV SARVAR NOSIRJONOVICH | F54: +998936474400 SMS OZI, 998941373443 SMS DOSTI 2, 998951142949 SMS DOSTI, | G54: г. Ташкент, Юнусабадский район, кв. 6, Туркистон МСГ, 15- Дом, 34- Квартира | H54: 3 | I54: 2844307.6
A55: ТОШКЕНТ ШАХРИ | B55: SUPER BRANCH | C55: Объезд | D55: Кр-99062768-1 | E55: RAXMANOVA XILOLA IBRAGIMOVNA | F55: 998971046161 OZI, 998886959098 QIZI, | G55: Toshkent shahri Bektemir tumani Musaffo MFY Charog'on ko'chasi 2-uy 3-xonadon | H55: 3 | I55: 2568228.7
A56: ТОШКЕНТ ШАХРИ | B56: SUPER BRANCH | C56: Объезд | D56: Кр-99035831-1 | E56: XAMIDOV BUNYOD QAXOR O’G’LI | F56: 998977246861 SMS OZI, 998935303136 SMS UKASI, 998351959042 SMS UKASI, 998482468612 SMS OZI, | G56: TOSHKENT SHAHAR SIRG’ALI TUMANI XONTEPA MFY XONABOD KO’CHASI 14-UY | H56: 3 | I56: 2106164.5
A57: ТОШКЕНТ ШАХРИ | B57: SUPER BRANCH | C57: Объезд | D57: Кр-99039458-1 | E57: SHARIPOV BAXODIR ATAXANOVICH | F57: 998333930802 SMS QIZI, 998889964445 SMS OZI, 998914237477 SMS AYOLI, | G57: г. Ташкент, Чиланзарский район, кв. 19, Шухрат МСГ, 29- Дом, 49- Квартира | I57: 1635056.6 | K57: 845 | 70000000 | 0
A58: ТОШКЕНТ ШАХРИ | B58: SUPER BRANCH | C58: Объезд | D58: Кр-99062609-3 | E58: ABDURASHIDOV SHAHZOD ABDURASHID O’G’LI | F58: 998774024744 SMS AYOLI, 998983097733 SMS OZI 2, 998994445444 SMS OZI, | G58: TOSHKENT SHAHAR YUNUSOBOD TUMANI XAKIKAT MFY YANGIQURGON PR 2 KUCHASI 41-UY | H58: 3 | I58: 263834.4 | K58: yopildi
A59: ФАРГОНА ВИЛОЯТИ | B59: BOSH OFIS | C59: Объезд | D59: Кр-99038391-1 | E59: ERKABOYEV OYBEK XUSANOVICH | F59: 998939799696 uzi, 998937494886 ayoli, 998937316996 ugli, | G59: Фаргона тумани Корасув МФЙ Шижоат кучаси ОҚБИЛОЛ ҚФЙ, ЯНГИ ОБОД МФЙ, ЎРИКЗОР КЎЧАСИ, uy:89 | H59: 3 | I59: 1895110.1 | K59: 770
A60: ФАРГОНА ВИЛОЯТИ | B60: SUPER BRANCH | C60: Объезд | D60: Кр-99060331-1 | E60: UMAROVA EXTIBOR SOTVOLDIYEVNA | F60: 998905331878 узи, 998932974444 невара, 998982775557 уй, 998943313223 эри, | G60: FARG’ONA VILOYATI, FARG’ONA SHAHRI, FARG’ONA MFY, FITRAT KO’CHASI, 27-UY | H60: 64 | I60: 52103349 | K60: 1748
A61: ФАРГОНА ВИЛОЯТИ | B61: SUPER BRANCH | C61: Объезд | D61: Кр-99035634-1 | E61: QORABOYEVA GULXUMOR MUXAMMADRO’ZIYEVNA | F61: 998908538090 SMS OZI, 998908581817 SMS OGLI, 998916884060 SMS QIZI, 998902934565 SMS JIYANI, 998910207077 KUYOVI TOLOVCHI , | G61: FARG’ONA VILOYATI BOG’DOD TUMANI MURUVAT MFY YOSH AVLOD KO’CHASI 12-UY 14-XONADON | H61: 136 | I61: 27694569 | K61: 595
A62: ФАРГОНА ВИЛОЯТИ | B62: SUPER BRANCH | C62: Объезд | D62: Кр-99036005-1 | E62: YO’LDASHEV JASURBEK JALOLIDIN O’G’LI | F62: 998940591389 SMS O’ZI, 998939749309 SMS AYOLI, 998950051108 SMS ONASI , 998999150265 SMS DADASI , | G62: FARG’ONA VILOYATI BESHARIQ TUMANI KUM MFY KO’KDALA KO’CHASI 531-XONADON | H62: 52 | I62: 13255170 | K62: 629
A63: ФАРГОНА ВИЛОЯТИ | B63: SUPER BRANCH | C63: Объезд | D63: Кр-99039797-1 | E63: GAFOROV IKBOLJON UKTAMOVICH | F63: 998903699953 SMS OZI, 998911081214 SMS AYOLI, 998916729177 SMS OMASI, 998918865940 SMS UY, 998505995135 SMS UZI NEW, 998905618936 OPASI HADEB BEZOVTA QILINMASIN , | G63: FARG’ONA VILOYATI RISHTON TUMANI ISTIQBOL MFY ZARARIK KO’CHASI 26-UY | H63: 3 | I63: 5440624.2 | K63: 892
A64: ФАРГОНА ВИЛОЯТИ | B64: SUPER BRANCH | C64: Объезд | D64: Кр-99047608-1 | E64: ADXAMOV ABDUXALIL AKRAMJONOVICH | F64: 998886630222 SMS JIYANI TOLOVCHI, 998939840364 SMS OZI , 998889840364 SMS AYOLI, 998881519222 SMS OGLI, 998889440364 OZI NEW, 998912821221 TOLOVCHINI DUGONASINI DADASI DUGONASI BILAN BIRGA TOLAYDI , | G64: QUVASOY SHAHRI | H64: 3 | I64: 4804994.1 | K64: 1391
A65: ФАРГОНА ВИЛОЯТИ | B65: SUPER BRANCH | C65: Объезд | D65: Кр-99040038-1 | E65: KARIMOV TEMURBEK TURSUNALI O’G’LI | F65: 998939833343 SMS OZI, 998916564748 SMS ONASI, 998330310616 SMS OPASI, 998319363322 SMS OPASI 2, | G65: FARG’ONA VILOYATI FARG’ONA SHAHAR 9-FARG’ONA MFY M-SHAYXZODA 38-XONADON | H65: 3 | I65: 2531496.3 | K65: 936
A66: ФАРГОНА ВИЛОЯТИ | B66: SUPER BRANCH | C66: Объезд | D66: Кр-99039003-2 | E66: ALIXONOV SHOKIRJON OLIMXANOVICH | F66: 998936405000 SMS OZI, 998998350010 SMS OGLI, 998916615593 SMS AYOLI, 998903270001 SMS OGLI 2 BEGONA, | G66: FARG’ONA VILOYATI FARG’ONA SHAHAR SHODIYONA MFY TINIQ SOY KO’CHASI 79-XONADON | H66: 3 | I66: 1635814 | K66: 811
A67: ФАРГОНА ВИЛОЯТИ | B67: SUPER BRANCH | C67: Объезд | D67: Кр-99062879-1 | E67: XOLBEKOV TO’LQINJON FOZILOVICH | F67: 998972906368 SMS QIZI, 998974206368 SMS OZI, 998992206368 SMS AYOLI, | G67: QO’SHTEPA TUMANI , MEVAZOR 80-XONADON | H67: 3 | I67: 1125156 | K67: 1928
A68: ФАРГОНА ВИЛОЯТИ | B68: SUPER BRANCH | C68: Объезд | D68: Кр-99036500-3 | E68: O’RMONOV MUXIBILLO XAMIDULLO O’G’LI | F68: 998770238647 SMS ZALOGADATEL , 998957372797 SMS UYI , 998911525257 SMS OZI, 998957944494 SMS OZI 2, 998957372737 GAROV EGASI TOLOVCHI , | G68: FARG’ONA VILOYATI O’ZBEKISTON TUMANI DEXQONOBOD QISHLOG’I 147-UY | I68: 396728.34 | K68: 660
A69: ФАРГОНА ВИЛОЯТИ | B69: SUPER BRANCH | C69: Объезд | D69: Кр-99040285-2 | E69: NURBOYEV XUSNIDDIN ISROYILOVICH | F69: 998995312666 SMS OZI, 998905332666 SMS AYOLI, 998952152666 SMS OGLI, 998953226662 SMS OGLI 2, | G69: FARG’ONA VILOYATI OLTIARIQ TUMANI DO’STLIK MFY S.SHROZIY KO’CHASI 103-XONADON | H69: 3 | I69: 156464.56 | K69: 989
A70: ФАРГОНА ВИЛОЯТИ | B70: Фарғона филиали | C70: Объезд | D70: Кр-99021030-1 | E70: XAYITBOYEV BOBIRJON MADAMINOVICH | F70: 91-128-80-09 SMS OZI BOG'CHALARGA GO'SHT TARQATADI , 94-235-80-09 SMS OZI 2 BEGONA, 91-660-53-47 SMS AYOLI, 90-531-73-73 SMS UKASI, | G70: FARG'ONA VILOYATI QUVA TUMANI MANAVIYAT KO'CHASI 44-XONADON | H70: 245 | I70: 1.0856115e+08 | K70: 137
A71: ФАРГОНА ВИЛОЯТИ | B71: Фарғона филиали | C71: Объезд | D71: Кр-99040913-4 | E71: ISMIXANOVA SEVILA MUSTAFAYEVNA | F71: +998907030041 O’ZI, 998904077354 SHERIGI, 998905815272 SINGLI, 998907040019 SMS O’ZI, | G71: FARG’ONA VILOYATI FARG’ONA SHAHAR IBRAT MFY REGISTON (O’RTA SHO’RA) KO’CHASI 2-UY 9-XONADON | H71: 94 | I71: 32146157 | K71: 1088
A72: ФАРГОНА ВИЛОЯТИ | B72: Фарғона филиали | C72: Объезд | D72: Кр-99041055-5 | E72: MUMINOV MAMIRJON ABDUMALIKOVICH | F72: +998958366468 O’ZI, 998942063001 O¹G’LI, | G72: FARG’ONA VILOYATI QO’SHTEPA TUMANI KARNAYCHI MFY ARCHAZOR KO’CHASI 234-UY | H72: 3 | I72: 6577703.8 | K72: 1102
A73: ФАРГОНА ВИЛОЯТИ | B73: Фарғона филиали | C73: Объезд | D73: Кр-99041883-1 | E73: UZAKOV ANVARJON MAKSIMOVICH | F73: +998993036357 SMS O’ZI, 998906326357 AYOLI, 998990097733 O’G’LI 2, 998991406357 O’G’LI, | G73: FARG’ONA VILOYATI OLTIARIQ TUMANI TINCHILIK MFY TADBIRKOR KO’CHASI 19-XONADON | H73: 3 | I73: 5607092.6 | K73: кисман толов кберди | 1218
A74: ФАРГОНА ВИЛОЯТИ | B74: Фарғона филиали | C74: Объезд | D74: Кр-99027916-2 | E74: SATTOROVA XURSHIDAXON RAVSHANJON QIZI | F74: 91-043-26-93 SMS O'ZI, 91-043-45-10 SMS ERI , 77-706-37-34 SMS UKASI , 91-679-72-32 SMS DADASI , 998953566333 Tolovchi, +998953566333 SMS O’ZI, 998777916333 ukasi shu tolovchi , | G74: FARG’ONA VILOYATI FARG’ONA SHAHAR FURQAT MFY, YOSHLIK KO’CHASI 93-A UY | H74: 3 | I74: 4053994.8 | K74: 255
A75: ФАРГОНА ВИЛОЯТИ | B75: Фарғона филиали | C75: Объезд | D75: Кр-99033555-2 | E75: AKBAROV IKROM MUXAMEDOVICH | F75: 998902938949 SMS O’ZI, 998903438280 SMS AKASI, 998905652884 SMS AYOLI, 998905084464 SMS JIYANI, | G75: FARG’ONA VILOYATI QO’QON SHAHAR USTA BOZOR MFY PARPASHABOF KO’CHASI 209-XONADON | H75: 3 | I75: 3640787.2 | K75: 496
A76: ФАРГОНА ВИЛОЯТИ | B76: Фарғона филиали | C76: Объезд | D76: Кр-99031452-1 | E76: MUXITDINOVA MAXFUZAXON ABDUVAXOBOVNA | F76: 88-864-34-24 SMS O'ZI NON PATIR SOTADI , 91-282-12-21 SMS AMAKISI TO’LOVCHI , 91-665-15-66 SMS GAROV EGASI , 99-494-11-72 SMS XOLASI , | G76: FARG’ONA VILOYATI FAR’ONA SHAHAR AL-XORAZIMIY MFY, AL-XORAZIMIY KO’CHASI 11-UY 54 XONADON | H76: 3 | I76: 3103855.8 | K76: 385
A77: ФАРГОНА ВИЛОЯТИ | B77: Фарғона филиали | C77: Объезд | D77: Кр-99032078-3 | E77: ABDULLAJONOV XOJIAKBAR OBIDJON O’G’LI | F77: 998949997060 SMS O’ZI axrana bolib ishlid , 998947097060 SMS AYOLI, 998948129222 SMS AKASI, 998959709293 SMS KELINI, 998507138440 OZI NEW , | G77: FARG’ONA VILOYATI FARG’ONA TUMANI MINDONOBOD MFY MADADKOR KO’CHASI 13-XONADON | H77: 3 | I77: 1777206.6 | K77: 415
A78: ФАРГОНА ВИЛОЯТИ | B78: Фарғона филиали | C78: Объезд | D78: Кр-99027619-5 | E78: RO’ZIBOYEV JASURBEK ABDUSATTOR O’G’LI | F78: 77-009-11-61 SMS OZI, 94-010-90-40 SMS Ortogi BEKZOD begona, 99-763-91-92 SMS AKASI MUXRIDDIN, 998994998162 Oyisi(941210467), | G78: FARGONA VILOYATI BOG’DOD TUMANI MATQULOBOT QISHLOGI ISTIQLOL KOCHASI 234-UY | H78: 3 | I78: 1369284.9 | K78: 238
A79: ФАРГОНА ВИЛОЯТИ | B79: Фарғона филиали | C79: Объезд | D79: Кр-99032078-4 | E79: ABDULLAJONOV XOJIAKBAR OBIDJON O’G’LI | F79: 998949997060 SMS O’ZI axrana bolib ishlid , 998947097060 SMS AYOLI, 998948129222 SMS AKASI, 998959709293 SMS KELINI, 998507138440 OZI NEW , | G79: FARG’ONA VILOYATI FARG’ONA TUMANI MINDONOBOD MFY MADADKOR KO’CHASI 13-XONADON | H79: 3 | I79: 1168148.1 | K79: 416
A80: ХОРАЗМ ВИЛОЯТИ | B80: SUPER BRANCH | C80: Объезд | D80: Кр-99040263-2 | E80: ABDULLAYEV BAXODIR ALIMBAYEVICH | F80: 998991660816 SMS OZI, 998990624394 SMS OZI 2, 998949923336 SMS OGLI, | G80: XORAZM VILOYATI XONQA TUMANI PAXTAKOR MFY PAXTAKOR 4-TOR KO’CHASI 3-UY | H80: 3 | I80: 3489755.8 | K80: 1-2 kunda filialga borib tolab ketad | 985
... A87: ХОРАЗМ ВИЛОЯТИ | B87: Урганч филиали | C87: Объезд | D87: Кр-99048761-2 | E87: RAXIMOV QADAMBOY RUSTAMOVICH | F87: +998972214945 SMS O’G’LI, 998870014945 SMS AYOLI, 998876454945 SMS UZI, | G87: ХОРАЗМ ВИЛОЯТИ ХОНКА Ш., ЖАННАТМАКОН МФЙ, НАФОСАТ, 1 ТОР КЎЧАСИ, uy:20 | H87: 3 | I87: 338345 | K87: kotarmad | 1417

Sheet Оплатили
A1: ← Вернуться в отчёт
A2: Область | B2: Филиал | C2: Группа | D2: Код клиента | E2: Клиент | F2: Номер телефона | G2: Адрес | H2: Кол-во просроченных дней | I2: Итого просрочка | J2: Оплата | K2: Izoh
A3: АНДИЖОН ВИЛОЯТИ | B3: BOSH OFIS | C3: Оплатил дозвон | D3: Кр-99027266-4 | E3: RAXMONOV ISROILJON XXX | F3: 998971516979 SMS O'ZI, 998331516979 SMS AYOLI, 998951086979 SMS O’G’LI, 998950902334 SMS QIZI, +998971516979 SMS O’ZI, 998889956979 SMS AYOLI, | G3: ANDIJON VILOYATI ANDIJON TUMANI ZAVROQ MFY SHOXI-ZINDA KO’CHASI 4-UY | H3: 3 | I3: 3717878 | J3: 3717878
A4: АНДИЖОН ВИЛОЯТИ | B4: SUPER BRANCH | C4: Оплатил дозвон | D4: Кр-99031618-3 | E4: DJUMAYEV OZODBEK XOSHIMJON O’G’LI | F4: 88-046-01-09 SMS O’ZI , 94-536-25-36 SMS AYOLI, 99-849-09-58 SMS UKASI, 77-072-11-63 SMS DADASI, | G4: ANDIJON VILOYATI ASAKA TUMANI TURON MFY XOJI KO’CHASI 67-UY | H4: 3 | I4: 1246693.6 | J4: 1246693.6
A5: АНДИЖОН ВИЛОЯТИ | B5: SUPER BRANCH | C5: Оплатил дозвон | D5: Кр-99056916-1 | E5: BO’RANOVA MARG’UBA TOXIROVNA | F5: 998881102465 SMS OZI, 998939940815 SMS OGLI, 998880052564 SMS XOJAYINI, 998905422591 SMS QZI, | G5: ANDIJON VILOYATI QO’RG’ONTEPA TUMANI UCHQUN MFY OGOXLIK KO’CHASI 1-UY | H5: 3 | I5: 1090321.7 | J5: 1090321.7
A6: АНДИЖОН ВИЛОЯТИ | B6: SUPER BRANCH | C6: Оплатил дозвон | D6: Кр-99057626-1 | E6: DAVRONOV AXMADBEK ODILOVICH | F6: 998995170264 SMS UZI, 998996940764 SMS AYOLI, 998945170264 SMS UZI 2, 998902174389 SMS JIYAN, | G6: ANDIJON VILOYATI PAXTAOBOD TUMANI ANDIJON MFY, O’RIKZOR KO’CHASI 134-UY | H6: 3 | I6: 44890.31 | J6: 44890.31
A7: АНДИЖОН ВИЛОЯТИ | B7: Андижон филиали | C7: Оплатил дозвон | D7: Кр-99062635-2 | E7: USMANOVA GULNOZA SHAVKATOVNA | F7: +998914907321 SMS O’ZI, 998500551620 SMS SINGLISI, 998889933833 SMS QIZI, 998946978207 SMS ONASI, 998500231621 SMS Tolovchi O'zi, | G7: Andijon viloyati Xo’jaobod tumani Mustaqillikning 27-yilligi MFY Obod ko’chasi, 67a-yu | H7: 6 | I7: 4359925.6 | J7: 4359925.6
A8: АНДИЖОН ВИЛОЯТИ | B8: Андижон филиали | C8: Оплатил дозвон | D8: Кр-99033630-6 | E8: ODAMBOYEVA NAZOKAT QAXRAMON QIZI | F8: 998505729393 SMS O’ZI, 998934349373 SMS KELINOYISI, 998994418804 SMS AKASI, 998940615252 SMS QARINDOSHI, +998501956662 SMS O’ZI, 998934258424 SMS POCHCHASI, 998946653675 SMS XOLASI, | G8: ANDIJON VILOYATI XO’JAOBOD TUMANI MUSTAQILLIKNING 27 YILLIGI MFY OBOD 1-TOR KO’CHASI 9-UY | H8: 3 | I8: 3866352 | J8: 3866352
A9: АНДИЖОН ВИЛОЯТИ | B9: Андижон филиали | C9: Оплатил дозвон | D9: Кр-99033630-5 | E9: ODAMBOYEVA NAZOKAT QAXRAMON QIZI | F9: 998505729393 SMS O’ZI, 998934349373 SMS KELINOYISI, 998994418804 SMS AKASI, 998940615252 SMS QARINDOSHI, +998501956662 SMS O’ZI, 998934258424 SMS POCHCHASI, 998946653675 SMS XOLASI, | G9: ANDIJON VILOYATI XO’JAOBOD TUMANI MUSTAQILLIKNING 27 YILLIGI MFY OBOD 1-TOR KO’CHASI 9-UY | H9: 3 | I9: 3247845.4 | J9: 3247845.4
A10: АНДИЖОН ВИЛОЯТИ | B10: Андижон филиали | C10: Оплатил дозвон | D10: Кр-99029219-1 | E10: XUSANBOYEVA NARGIZA XOLMUROD QIZI | F10: 998507163988 SMS OZI TULOVCHISI, 93-061-98-00 SMS ERI TULOVCHISI, 94-425-98-92 SMS OZI TULOVCHISI, 93-429-12-09 SMS ONASI, 998507163998 SMS ozi new , | G10: ANDIJON TUMANI MARXAMAT TUMANI DURAFSHON KOCHASI DONISHMAND KOCHASI 8-UY | H10: 1 | I10: 2120319.3 | J10: 2120319.3 | K10: bugun yopadi
A11: АНДИЖОН ВИЛОЯТИ | B11: Андижон филиали | C11: Оплатил дозвон | D11: Кр-99031618-1 | E11: DJUMAYEV OZODBEK XOSHIMJON O’G’LI | F11: 88-046-01-09 SMS O’ZI , 94-536-25-36 SMS AYOLI, 99-849-09-58 SMS UKASI, 77-072-11-63 SMS DADASI, | G11: ANDIJON VILOYATI ASAKA TUMANI TURON MFY XOJI KO’CHASI 67-UY | H11: 2 | I11: 1933119.9 | J11: 1933119.9
A12: АНДИЖОН ВИЛОЯТИ | B12: Андижон филиали | C12: Оплатил дозвон | D12: Кр-99057395-3 | E12: SOBIROV AXMADULLOX MUXAMMADJON O’G’LI | F12: 998979712424 SMS UZI, 998887527779 AKASI, 998884104045 SMS KELNOYISI, 998972040525 SMS DADASI, +998979712424 SMS O’ZI, 998942493838 SMS AKASI, | G12: ANDIJON VILOYATI OLTINKO’L TUMANI CHO’NTAK MFY, MUSTAQILLIK KO’CHASI 227-UY | H12: 3 | I12: 1240770 | J12: 1240770
A13: БУХОРО ВИЛОЯТИ | B13: SUPER BRANCH | C13: Оплатил дозвон | D13: Кр-99018891-5 | E13: FAXILLOYEVA MOXINUR FOZILOVNA | F13: 97-306-16-10 SMS OZI, 90-513-05-03 SMS ERI BEGONA , 97-854-75-48 SMS QAYNONA, 91-411-91-88 SMS QAYNOTA, 50-578-16-10 SMS UZI2, | G13: BUXORO VILOYATI BUXORO TUMANI NOVMETAN QFY | H13: 3 | I13: 2655794.9 | J13: 2655794.9 | K13: BUGUN 2SOATDA | 98
A14: БУХОРО ВИЛОЯТИ | B14: SUPER BRANCH | C14: Оплатил дозвон | D14: Кр-99041395-2 | E14: G’AYBULLOYEVA LAYLO ABDULLO QIZI | F14: 998950856644 SMS ERI, 998970153002 SMS ERI 2, 998955250119 SMS ERI2, 998400722322 SMS OZI2, 998997015300 SMS ERI NEW, | G14: TOSHKENT SHAHAR YANGIXAYOT TUMANI YANGIDARXON MFY, 8-UY, 36-XONADON | I14: 321272.7 | J14: 321272.7 | K14: KO'TARMAYABDI TELEGRAMDAN YOZDIM BUGUN TO'LASHI KERAK | 1161
A15: БУХОРО ВИЛОЯТИ | B15: Бухоро филиали | C15: Оплатил дозвон | D15: Кр-99063805-1 | E15: NASIROVA SANAVAR SHARIFDJANOVNA | F15: +998777630387 SMS O’ZI, 998909710400 SMS O’G’LI, 998996007310 SMS ERI, | G15: BUXORO VILOYATI BUXORO SHAHAR YANGIOBOD MFY YANGIOBOD KO’CHASI 123-UY | H15: 3 | I15: 9936501.7 | J15: 9936501.7 | K15: 2192
A16: БУХОРО ВИЛОЯТИ | B16: Бухоро филиали | C16: Оплатил дозвон | D16: Кр-99064605-1 | E16: YUSUPOV ASILBEK ASQADOVICH | F16: 998888300445 SMS O’ZI, 998931898363 SMS DO’STI, 998995482555 SMS DO’STI, | G16: BUXORO VILOYATI KOGON TUMANI NURAFSHON MFY YUKORI CHUKATI 20-UY | H16: 3 | I16: 1237055.3 | J16: 1237055.3 | K16: 2391
A17: БУХОРО ВИЛОЯТИ | B17: Бухоро филиали | C17: Оплатил дозвон | D17: Кр-99044175-1 | E17: MURODOV MUROD UMAR O’G’LI | F17: +998995624067 SMS O’ZI, 998914450878 SMS DO’STI, 998918384026 SMS ONASI, 998948893111 SMS DO’STI, | G17: Паноб МФЙ, Янги ҳаёт қишлоғи, 138-уй | I17: 475170.39 | J17: 475170.39 | K17: BUGUNGA TO'LEMIZ FILIALGA BORIB DEDILA | 1300
A18: БУХОРО ВИЛОЯТИ | B18: Бухоро филиали | C18: Оплатил дозвон | D18: Кр-99032335-1 | E18: HAZRATOV BAXSHILLO NURILLAYEVICH | F18: 998949144311 SMS O’ZI, 998942474311 SMS O’ZI 2, 998930734311 SMS O’G’LI AMRILLO, | G18: BUXORO VILOYATI OLOT TUMANI SOIN QORADUL QFY 18-UY | I18: 377458.36 | J18: 377458.36 | K18: BUGUNGA VADA BERGAN | 428
A19: ЖИЗЗАХ ВИЛОЯТИ | B19: BOSH OFIS | C19: Оплатил дозвон | D19: Кр-99033893-2 | E19: NORMATOV BEKZOD XOLJURAYEVICH | F19: 998916270830 SMS OZI, 998910290447 SMS AYOLI, 998905381311 SMS SINGLI, | G19: JIZZAX VILOYATI JIZZAX SHAHRI QALIYA MFY ABU RAYHON BERUNIY KUCHASI 8-UY | H19: 3 | I19: 508860.35 | J19: 508860.35
A20: ЖИЗЗАХ ВИЛОЯТИ | B20: SUPER BRANCH | C20: Оплатил дозвон | D20: Кр-99022847-4 | E20: MELIBAYEV MIRSAID XABIBULLAYEVICH | F20: 91-590-31-00 SMS UZI , 97-643-31-00 SMS OGLI, 91-188-19-20 SMS AYOLI, 90-180-40-02 SMS SHEREGI, | G20: JIZAX VILOYATI ZAFAROBOD TUMANI NURAFSHON QFY NARKUTSOY KUCHASI 15-UY | H20: 3 | I20: 3937776.1 | J20: 3937776.1
A21: ЖИЗЗАХ ВИЛОЯТИ | B21: SUPER BRANCH | C21: Оплатил дозвон | D21: Кр-99029615-3 | E21: QILICHBEKOV UTKIR LATIFOVICH | F21: 99-034-81-71 SMS O'ZI, 99-095-20-12 SMS AYOLI , 88-208-15-45 SMS AKASI , 88-296-26-29 SMS HAMKASB , | G21: JIZZAX VILOYATI JIZZAX SHAHRI ZILOL MAHALLASI MUSTAQILLIK KUCHASI 12-UY 20 XONADON | H21: 3 | I21: 1544289.2 | J21: 1544289.2
A22: ЖИЗЗАХ ВИЛОЯТИ | B22: SUPER BRANCH | C22: Оплатил дозвон | D22: Кр-99029332-2 | E22: SHERMATOV BAXTIYOR OCHILOVICH | F22: 77-301-76-76 sms SIN, 99-504-76-76 sms SIN, 91-599-69-02 sms UZI, 773017676 sms SIN, 915996902 sms UZI, 995047676 sms SIN, | G22: JIZZAX VILOYATI SH.RASHIDOV TUMANI PAXTAOBOD QFY YAHTANLIK MFY BOG’DOD KUCHASI 51-UY | H22: 3 | I22: 1463726 | J22: 1463726
A23: ЖИЗЗАХ ВИЛОЯТИ | B23: SUPER BRANCH | C23: Оплатил дозвон | D23: Кр-99053654-1 | E23: XOLBEKOV QUVONCHBEK SAID O’G’LI | F23: 998993542391 SMS OZI, 998943750194 SMS ONASI, 998931257179 SMS UY, 998932347179 SMS DOSTI, | G23: JIZZAX VILOYATI ARNASOY TUMANI G'OLIBLAR SHFY ULUG'BEK KUCHASI 22-UY 2-XONADON | H23: 3 | I23: 1392080.4 | J23: 1392080.4
A24: ЖИЗЗАХ ВИЛОЯТИ | B24: SUPER BRANCH | C24: Оплатил дозвон | D24: Кр-99028409-6 | E24: ABDIYEV ZAFARJON XOLBOYEVICH | F24: 93-091-09-39 SMS OZI, 93-686-93-77 SMS AYOLI, 94-727-50-75 SMS SIN, 930910939 SMS OZI, 936869377 SMS AYOLI, 947275075 SMS SIN, | G24: МАДАНИЯТ КФЙ, МАДАНИЯТ КФЙ, ЗАРГАР КИШЛОГИ, uy:Р/С | H24: 3 | I24: 1130130.7 | J24: 1130130.7
A25: ЖИЗЗАХ ВИЛОЯТИ | B25: SUPER BRANCH | C25: Оплатил дозвон | D25: Кр-99039705-2 | E25: TURSUNBOYEV MIRZOXID MUZAFFAR O’G’LI | F25: 998700262501 SMS OZI, 998933472491 SMS DADASI, 998772180718 SMS ONASI, | G25: JIZZAX VILOYATI PAXTAKOR TUMANI CHAMANZOR QFY IBN SINO KUCHASI 7/2 - UY | H25: 3 | I25: 904738.23 | J25: 904738.23
A26: ЖИЗЗАХ ВИЛОЯТИ | B26: Жиззах филиали | C26: Оплатил дозвон | D26: Кр-99007949-4 | E26: MAJIDOV XASAN BOSIMOVICH | F26: 94-573-50-05 SMS OZI, 99-588-08-73 SMS OZI tanmidi , 99-201-19-78 SMS AYOLI, 94-574-16-47 SMS Uz, 94-573-50-05 sms OZI, | G26: JIZZAX VILOYATI ZARBDOR TUMANI LALIMKOR QFY TINCHLIK KO’CHASI 47-UY | H26: 3 | I26: 6840511.4 | J26: 6840511.4
A27: ЖИЗЗАХ ВИЛОЯТИ | B27: Жиззах филиали | C27: Оплатил дозвон | D27: Кр-99029615-2 | E27: QILICHBEKOV UTKIR LATIFOVICH | F27: 99-034-81-71 SMS O'ZI, 99-095-20-12 SMS AYOLI , 88-208-15-45 SMS AKASI , 88-296-26-29 SMS HAMKASB , | G27: JIZZAX VILOYATI JIZZAX SHAHRI ZILOL MAHALLASI MUSTAQILLIK KUCHASI 12-UY 20 XONADON | H27: 3 | I27: 2917352.2 | J27: 2917352.2
A28: ЖИЗЗАХ ВИЛОЯТИ | B28: Жиззах филиали | C28: Оплатил дозвон | D28: Кр-99041360-2 | E28: QOSIMOV XAYRULLO RAXIMBERDIYEVICH | F28: +998943473031 SMS 1, 998941362625 SMS 2, 998977253031 SMS 3, | G28: JIZZAX VILOYATI DUSTLIK TUMANI MANAS MFY XATIRCHI KUCHASI 18/8-UY | H28: 3 | I28: 2482424.1 | J28: 2482424.1
A29: ЖИЗЗАХ ВИЛОЯТИ | B29: Жиззах филиали | C29: Оплатил дозвон | D29: Кр-99028729-2 | E29: AMANOV BUNYOD MUMIN O’G’LI | F29: 998991791177 SMS OZI, 998902642879 SMS OPASI, 998509979579 SMS TOLOVCHISI, 998996790117 SMS AYOLI, 998881591177 AYOLI, 998944449556 ONASI, | G29: МУЗБУЛОК МФЙ, МУЗБУЛОК МФЙ, ЛОЙИХАДАГИ, uy:Р.С | H29: 3 | I29: 1400224.3 | J29: 1400224.3
A30: ЖИЗЗАХ ВИЛОЯТИ | B30: Жиззах филиали | C30: Оплатил дозвон | D30: Кр-99029332-3 | E30: SHERMATOV BAXTIYOR OCHILOVICH | F30: 77-301-76-76 sms SIN, 99-504-76-76 sms SIN, 91-599-69-02 sms UZI, 773017676 sms SIN, 915996902 sms UZI, 995047676 sms SIN, | G30: JIZZAX VILOYATI SH.RASHIDOV TUMANI PAXTAOBOD QFY YAHTANLIK MFY BOG’DOD KUCHASI 51-UY | H30: 3 | I30: 1022357 | J30: 1022357
... A34: ЖИЗЗАХ ВИЛОЯТИ | B34: Жиззах филиали | C34: Оплатил дозвон | D34: Кр-99028409-7 | E34: ABDIYEV ZAFARJON XOLBOYEVICH | F34: 93-091-09-39 SMS OZI, 93-686-93-77 SMS AYOLI, 94-727-50-75 SMS SIN, 930910939 SMS OZI, 936869377 SMS AYOLI, 947275075 SMS SIN, | G34: МАДАНИЯТ КФЙ, МАДАНИЯТ КФЙ, ЗАРГАР КИШЛОГИ, uy:Р/С | H34: 3 | I34: 450103 | J34: 450103
A35: КАШКАДАРЁ ВИЛОЯТИ | B35: SUPER BRANCH | C35: Оплатил дозвон | D35: Кр-99036280-3 | E35: DJURAYEV URAL NORTULAYEVICH | F35: 998973133705 SMS OZI, 998886389305 SMS AYOLI, 998882214343 SMS AKASI, 998970706311 SMS UKASI, | G35: КАШКАДАРЁ ВИЛОЯТИ КОСОН ТУМАНИ Эсабой МФЙ Эсабой кучаси 11 уй | H35: 3 | I35: 0 | K35: bugun abetgacha yopaman hammasini ddi | 641 | 2477161.57
A36: КАШКАДАРЁ ВИЛОЯТИ | B36: SUPER BRANCH | C36: Оплатил дозвон | D36: Кр-99039364-1 | E36: AZIMOV TURG’UN TUFLIYEVICH | F36: 998946868512 SMS OZI, 998786757278 SMS AYOLI, 998505792187 SMS DADSI, 998973168020 SMS ONASI, | G36: QASHQADARYO VILOYATI QAMASHI TUMANI JONBUZSOY MFY UMID NIXOLI KUCHASI 46-UY | H36: 2 | I36: 0 | K36: bugun kechgacha bittasi yopiladi bittasini hoz yopadi | 847 | 3113172.12
A37: КАШКАДАРЁ ВИЛОЯТИ | B37: SUPER BRANCH | C37: Оплатил дозвон | D37: Кр-99040370-1 | E37: AZIMOV HASAN G’AYRAT O’G’LI | F37: 998979514900 SMS OZI (BEGONA))), 998880073012 SMS AKASI (HAMKASBI), 998973863606 SMS DADASI (BEGONA), 998973183000 SMS DADASI UZIIII, | G37: QASHQADARYO VILOYATI SHAXRISABZ TUMANI LOLISTON MFY PAXTAKOR QISHLOG’I XISOR KUCHASI 45-UY | H37: 3 | I37: 0 | K37: bankdan kirim qildi kechga korinadi 3000 | 1001 | 3207080.8
A38: КАШКАДАРЁ ВИЛОЯТИ | B38: Қарши филиали | C38: Оплатил дозвон | D38: Кр-99036280-2 | E38: DJURAYEV URAL NORTULAYEVICH | F38: 998973133705 SMS OZI, 998886389305 SMS AYOLI, 998882214343 SMS AKASI, 998970706311 SMS UKASI, | G38: КАШКАДАРЁ ВИЛОЯТИ КОСОН ТУМАНИ Эсабой МФЙ Эсабой кучаси 11 уй | H38: 3 | I38: 0 | K38: bugun abetgacha yopaman hammasini ddi | 640 | 1399498.04
A39: КАШКАДАРЁ ВИЛОЯТИ | B39: Қарши филиали | C39: Оплатил дозвон | D39: Кр-99036280-4 | E39: DJURAYEV URAL NORTULAYEVICH | F39: 998973133705 SMS OZI, 998886389305 SMS AYOLI, 998882214343 SMS AKASI, 998970706311 SMS UKASI, | G39: КАШКАДАРЁ ВИЛОЯТИ КОСОН ТУМАНИ Эсабой МФЙ Эсабой кучаси 11 уй | H39: 3 | I39: 0 | K39: bugun abetgacha yopaman hammasini ddi | 642 | 3152875.11
A40: КАШКАДАРЁ ВИЛОЯТИ | B40: Қарши филиали | C40: Оплатил дозвон | D40: Кр-99036962-2 | E40: SALOMOV ILYOS SODIKOVICH | F40: 998335456770 SMS OZI, 998908970677 SMS OILASI, 998996361855 SMS UKASI, 998916361855 SMS AKASI UZIII, | G40: КАШКАДАРЁ ВИЛОЯТИ КАРШИ ШАХРИ КАВАЛИ МФЙ ЧОРСУ КУЧАСИ 26-УЙ | H40: 3 | I40: 0 | K40: BUGUN YOPADII | 679 | 694811.8
A41: КАШКАДАРЁ ВИЛОЯТИ | B41: Қарши филиали | C41: Оплатил дозвон | D41: Кр-99063749-1 | E41: HAYITOV NOSIRBEK ILHOMOVICH | G41: КАШКАДАРЁ ВИЛОЯТИ КАСБИ ТУМАНИ ОКТЕПА МФЙ ДЕНОВ КИШЛОГИ | I41: 0 | K41: bugun yopaman ddi | 2174 | 216610.95
A42: КОРАКАЛПОГИСТОН РЕСПУБЛИКАСИ | B42: SUPER BRANCH | C42: Оплатил дозвон | D42: Кр-99040984-1 | E42: UTAROV JAKSILIK DJITESOVICH | F42: 998913033891 SMS OZI, 998913917972 SMS AYOLI, 998991941402 SMS OGLI, | G42: NUKUS SHAHRI | H42: 3 | I42: 4465307.9 | J42: 4465307.9
A43: КОРАКАЛПОГИСТОН РЕСПУБЛИКАСИ | B43: SUPER BRANCH | C43: Оплатил дозвон | D43: Кр-99060436-1 | E43: DJALIMBETOVA KALIXAN SHUKURBAEVNA | F43: 998913008425 узи, 998902628687 кизи, 998913738425 угли, 998973650906 угли, | G43: QORAQALPOGISTON RES NUKUS SHAHAR KATTAGAR MFY SHARSHARA KUSHASI 11 UY | H43: 3 | I43: 4363232.2 | J43: 4363232.2
A44: КОРАКАЛПОГИСТОН РЕСПУБЛИКАСИ | B44: SUPER BRANCH | C44: Оплатил дозвон | D44: Кр-99064541-1 | E44: MADAMINOV RASUL FAXRIDDIN O’G’LI | F44: 998934215520 SMS UKASI, 998937435525 SMS AYOLI, 998937705522 SMS UZI, | G44: ЧОЙКУЛ ҚФЙ, БОСУВ МФЙ, uy:Р/З | H44: 3 | I44: 3874563 | J44: 3874563
A45: КОРАКАЛПОГИСТОН РЕСПУБЛИКАСИ | B45: SUPER BRANCH | C45: Оплатил дозвон | D45: Кр-99041583-1 | E45: ATAMURATOVA ZAURE KENESBAEVNA | F45: +998913926462 OZI, | G45: Моншаклы МФЙ, Улугбек кучаси, 34-уй | H45: 3 | I45: 3106671.4 | J45: 3106671.4 | K45: QISMAN
A46: КОРАКАЛПОГИСТОН РЕСПУБЛИКАСИ | B46: SUPER BRANCH | C46: Оплатил дозвон | D46: Кр-99054949-1 | E46: NIYETBAYEVA AINUR NIYETULLAYEVNA | F46: 998886580422 SMS OZI, 998883384007 SMS QIZI, 998888921002 SMS QIZI, 998881378382 SMS ERI , | G46: QARAQALPOGISTON RES NUKUS TUMANI DIYXAN ARNA MFY SHADLI EL KUSHASI 23A-UY | H46: 3 | I46: 2646783.4 | J46: 2646783.4
A47: КОРАКАЛПОГИСТОН РЕСПУБЛИКАСИ | B47: SUPER BRANCH | C47: Оплатил дозвон | D47: Кр-99062824-1 | E47: ALIYEV KUDIYAR ALLIYAROVICH | F47: 998933611148 SMS OANSI, 998972904286 SMS OZI, 998991623511 SMS AYOLI, 998991633511 SMS QIZI, | G47: QORAQOLPAGISTON RESPUBLIKASI NUKUS AMUDARYA MFY ELIM BAR KOCHASI 35-UY | H47: 3 | I47: 2471223.6 | J47: 2471223.6 | K47: qisman
A48: КОРАКАЛПОГИСТОН РЕСПУБЛИКАСИ | B48: SUPER BRANCH | C48: Оплатил дозвон | D48: Кр-99061977-1 | E48: DJUMAMBETOV ADILBAY DJIYLISBAEVICH | F48: 998935690685 SMS OZI, 998938712409 SMS AYOLI, 998333252268 SMS OPASI, 998945833936 SMS OPASI2, | G48: QORAQALPOGISTON RES SHUMANAY TUMANI MAMIY OFY ABAT JURT KUSHASI 4 UY | H48: 3 | I48: 2439603.4 | J48: 2439603.4
A49: КОРАКАЛПОГИСТОН РЕСПУБЛИКАСИ | B49: Нукус филиали | C49: Оплатил дозвон | D49: Кр-99064163-3 | E49: KURBANBAEV JANDULLA KOSHKINBAEVICH | F49: 998501579573 OZI, 998930953883 OGLI, 998933633239 OYALI, | G49: Коркалпогистон Рес Нукус шахар Наубахар МФЙ Ак тау кучаси 61 уй | H49: 3 | I49: 7796351.5 | J49: 7796351.5 | K49: qisman
A50: КОРАКАЛПОГИСТОН РЕСПУБЛИКАСИ | B50: Нукус филиали | C50: Оплатил дозвон | D50: Кр-99064151-1 | E50: DOSIMBETOV KUAT NAZARBEKOVICH | F50: 998941117577 OZI, 998944581211 UKASI, 998996530048 OYALI, | G50: КОРКАЛПОГИСТОН РЕС ЧИМБОЙ ТУМАНИ ТАГЖАП ССГ, АННА РОЗЫМ АХОЛИ ПУНКТИ, uy:Р/У | H50: 3 | I50: 5169425.8 | J50: 5169425.8
A51: КОРАКАЛПОГИСТОН РЕСПУБЛИКАСИ | B51: Нукус филиали | C51: Оплатил дозвон | D51: Кр-99064262-2 | E51: KOSIMOVA LUIZA BAXADIROVNA | F51: 998875028884 OZI, 998970634141 ERI, 998973792012 QIZI, | G51: Коркалпогистон Рес Нукус шахар Гоне кала МФЙ, Каракалпакстан кучаси, 39-уй, 39-хонадон | H51: 3 | I51: 3050193.2 | J51: 3050193.2 | K51: qisman
A52: КОРАКАЛПОГИСТОН РЕСПУБЛИКАСИ | B52: Нукус филиали | C52: Оплатил дозвон | D52: Кр-99063510-2 | E52: DAULETBAEVA ANISA EREJEPBAEVNA | F52: 998906541221 UKASI, 998913034700 OZI, 998939201001 ERI, | G52: QORAQALPOGISTON RES NUKUS SHAHAR QOS BULOQ MFY GUJIMLI KUSHASI 28 UY | H52: 3 | I52: 2918680.4 | J52: 2918680.4
A53: КОРАКАЛПОГИСТОН РЕСПУБЛИКАСИ | B53: Нукус филиали | C53: Оплатил дозвон | D53: Кр-99049371-1 | E53: TOREMURATOVA GULAYIM AYAPBERGENOVNA | F53: 998907369948 OZI, 998913007873 OGLI, 998946853336 QIZI, 998913837073 ogli neww, | G53: Qaraqalpogiston Respublikasi Xojayli tumani Kulap OFY Shiraq kushasi 13 uy | H53: 3 | I53: 2436444.3 | J53: 2436444.3 | K53: qisman
A54: КОРАКАЛПОГИСТОН РЕСПУБЛИКАСИ | B54: Нукус филиали | C54: Оплатил дозвон | D54: Кр-99064286-1 | E54: ABILOV SAGINDIK MAXSETBAEVICH | F54: 998913020929 OGLI, 998913024212 OZI, 998913802331 OYALI, | G54: Коркалпогистон Рес Нукус щахар Наубахар МФЙ, Мийрим-шапаат кучаси, 11-уй | H54: 3 | I54: 2420833 | J54: 2420833
A55: КОРАКАЛПОГИСТОН РЕСПУБЛИКАСИ | B55: Нукус филиали | C55: Оплатил дозвон | D55: Кр-99029035-2 | E55: AZATOV SHERZOD MUXTAR ULI | F55: 91-266-77-70 SMS O'ZI, 91-381-77-43 SMS UKASI, 91-307-67-66 SMS AYOLI, 998913022574 SMS OTASI, 998913907744 SMS ONASI, | G55: QARAQALPOGISTON RESPUBLIKASI XOJELI TUMANI ALMAZAR 94-UY | H55: 1 | I55: 1745949.1 | J55: 1745949.1 | K55: qisman
A56: КОРАКАЛПОГИСТОН РЕСПУБЛИКАСИ | B56: Нукус филиали | C56: Оплатил дозвон | D56: Кр-99064434-1 | E56: JENGISBAEV RAXIM JENGISBAEVICH | F56: 998907007556 UKASI, 998933693080 OZI, 998995831124 AKASI, | G56: Республика Каракалпакстан, Нукус г., ул. Бахытлы, дом 12 | H56: 3 | I56: 1363570 | J56: 1363570
A57: КОРАКАЛПОГИСТОН РЕСПУБЛИКАСИ | B57: Нукус филиали | C57: Оплатил дозвон | D57: Кр-99064042-1 | E57: NURATDINOV RUSLAN MUXITOVICH | F57: 998912596868 UKASI, 998934893302 OYALI, 998999575356 OZI, | G57: КОРКАЛПОГИСТОН РЕС НУКУС ЩАХАР БЕСТОБЕ МФЙ, БЕСТОБЕ МФЙ, ШАРЬЯР КЎЧАСИ, uy:5/2 | H57: 3 | I57: 227952.1 | J57: 227952.1
A58: НАМАНГАН ВИЛОЯТИ | B58: BOSH OFIS | C58: Оплатил дозвон | D58: Кр-99035133-2 | E58: AXMEDOV ABDURAXIM XUSNIDDIN O’G’LI | F58: 998886165577 SMS O’ZI , 998884657477 SMS DADASI, 998881182277 SMS ONASI , 998361655772 SMS O’ZI , | G58: NAMANGAN VILOYATI YANGI NAMANGAN TUMANI YOSHLIK MFY SARBON KO’CHA 75 UY | H58: 3 | I58: 395550.31 | J58: 395550.31 | K58: yopildi | Хороший
A59: НАМАНГАН ВИЛОЯТИ | B59: SUPER BRANCH | C59: Оплатил дозвон | D59: Кр-99025559-4 | E59: ZOKIROV ASADBEK TOXIR-O’G’LI | F59: 88-258-68-78 SMS OZI, 99-087-18-22 SMS DADSI, 99-933-18-22 SMS ONASI, 94-999-68-78 SMS UKASI, | G59: NAMANGAN TUMAN NO’G’AYQO’RG’ON MFY MUSTAQILLIK 20 YILLIGI KO’CHASI 52 UY | H59: 3 | I59: 5270487.7 | J59: 5270487.7 | K59: yopildi | Хороший
A60: НАМАНГАН ВИЛОЯТИ | B60: Наманган филиали | C60: Оплатил дозвон | D60: Кр-99063074-1 | E60: QAYUMOVA ROZIYAXON ABDUSAMATOVNA | F60: +998933221064 SMS O’ZI, 998933671070 JIYANI, 998944478313 ERI, | G60: НАМАНГАН ВИЛОЯТИ ЯНГИҚЎРҒОН ТУМАНИ 3-МАШЪЛ КЎЧАСИ 21-УЙ | H60: 3 | I60: 6044721.8 | J60: 6044721.8 | K60: yopildi | Стандартрый
A61: НАМАНГАН ВИЛОЯТИ | B61: Наманган филиали | C61: Оплатил дозвон | D61: Кр-99033252-2 | E61: SANJAROV ULUG’BEK XASANOVICH | F61: 998901568000 SMS O’ZI, 998873066332 SMS O’ZI 2, 998997213296 SMS AYOLI, 998075232962 SMS AYOLI 2, +998901568000 SMS O’ZI, | G61: NAMANGAN VILOYATI DAVLATOBOD TUMANI XALQLAR DO’STLIGI MFY 4-KICHIK NOXIYA 5 UY 36 XONADON | H61: 3 | I61: 3883881.6 | J61: 3883881.6 | K61: yopildi | Хороший
A62: НАМАНГАН ВИЛОЯТИ | B62: Наманган филиали | C62: Оплатил дозвон | D62: Кр-99038435-2 | E62: G’IYASOV ZUXRIDDIN MAXMUDJONOVICH | F62: 998972478889 SMS OZI, 998976826262 SMS AKASI, 998902750979 SMS ONASI, 998971570893 SMS AYOLI, | G62: NAMANGAN VILOYATI NAMANGAN TUMANI OLAXAMAK MFY ZIYOKOR KO’CHA 14 UY | H62: 3 | I62: 2159607 | J62: 2159607 | K62: yopildi | Хороший
A63: НАМАНГАН ВИЛОЯТИ | B63: Наманган филиали | C63: Оплатил дозвон | D63: Кр-99064125-1 | E63: O’TANOV MUXIDDIN TURSUNOVICH | F63: +998882053232 SMS O’ZI, 998888267475 SMS JIYANI, 998942783839 SMS AYOLI, | G63: НАМАНГАН ВИЛОЯТИ НОРИН ТУМАНИ МАРҒИЗОР МФЙ НАВО КЎЧАСИ 14 УЙ | H63: 3 | I63: 1462144.2 | J63: 1462144.2 | K63: undruvchi oldi pulini | Стандартрый
A64: НАМАНГАН ВИЛОЯТИ | B64: Наманган филиали | C64: Оплатил дозвон | D64: Кр-99030695-2 | E64: USMONXANOV IBROXIMJON ISROIL O’G’LI | F64: 91-280-30-80 SMS O'ZI, 90-791-83-86 SMS AYOLI, 93-492-63-63 SMS ONASI, 90-794-25-65 SMS UYI, +998934926363 Primary phone from road24, 998934926363 Primary phone from road24, 907918386 SMS AYOLI, 907942565 SMS UYI, 912803080 SMS O’ZI, 934926363 SMS ONASI, | G64: NAMANGAN VILOYATI NAMANGAN SHAHAR YANGI NAMANGAN TUMANI BUNYODKOR MFY SANOAT KO’CHASI 52A UY | H64: 3 | I64: 1390136.2 | J64: 1390136.2 | K64: yopildi | Хороший
A65: САМАРКАНД ВИЛОЯТИ | B65: Самарқанд филиали | C65: Оплатил дозвон | D65: Кр-99005310-1 | E65: USMONOV ABDUMALIK SHARIFBOYEVICH | F65: 998900000000 SMS OZI, +998991314667 SMS AKASI TULOVCHI, 998502501824 SMS AYOLI, 998939133686 SMS OZI, 998992390932 SMS UYI, | G65: SAMARQAND VILOYATI ISHTIXON TUMANI O’RTAQISHLOQ QFY, JAROSTI QISHLOG’I 127-UY | H65: 3 | I65: 1641259.2 | J65: 1641259.2 | K65: xudoyor akaga berdu | 19
A66: САМАРКАНД ВИЛОЯТИ | B66: Самарқанд филиали | C66: Оплатил дозвон | D66: Кр-99063849-1 | E66: ULMASOV XOTAM SHOMARDJONOVICH | F66: 998889936664 SMS UYI, 998905056661 SMS OZI, 998973996662 SMS AYOLI, | G66: SAMARQAND VILOYATI SAMARQAND SHAHAR SATTEPO MFY SATTEPO DAHASI 170-UY 79-XONADON | H66: 3 | I66: 189984.64 | J66: 189984.64 | K66: hoz tolaydi | 2207
A67: САМАРКАНД ВИЛОЯТИ | B67: Самарқанд филиали | C67: Оплатил дозвон | D67: Кр-99028869-7 | E67: KOMILOV FARXOD SHUXRATOVICH | F67: 90-451-67-88 SMS , 99-068-68-88 SMS O'ZI 2, 90-656-67-88 SMS QIZI, +998904516788 SMS OZI, | G67: SAMARQAND VILOYATI SAMARQAND TUMANI ULUGBEK QFY CHORSHANBA MFY NILUFAR KUCHASI 19-UY | I67: 25152.68 | J67: 25152.68 | K67: 290
A68: СУРХОНДАРЁ ВИЛОЯТИ | B68: SUPER BRANCH | C68: Оплатил дозвон | D68: Кр-99061497-1 | E68: XIDIROV O’TKIRBEK BAHODIR O’G’LI | F68: +998945124647 SMS OZI, 998919073838 SMS HAMKASBI, 998958702770 SMS AKASI, | G68: SURXONDARYO VILOYATI OLTINSOY TUMANI TO’XTAMISH SUVLISOY QISHLOG’I 57-UY | H68: 3 | I68: 1545007.4 | J68: 1545007.4 | K68: oylik tolovi yopildi | 1780
A69: СУРХОНДАРЁ ВИЛОЯТИ | B69: SUPER BRANCH | C69: Оплатил дозвон | D69: Кр-99022504-4 | E69: MUQUMOVA MAXFURAT QUVOTOVNA | F69: 91-229-38-19 SMS, 91-715-95-96 SMS UY, 91-075-20-16 SMS O’G’LI BEKZOD, 998917191006 SMS ozi, 998882439996 SMS OZI TOLOVCHI , 998887239996 SMS new uzi, | G69: SURXONDARYO VILOYATI SHO’RCHI TUMANI YANGIBOZOR QFY OQQURG’ON MFY MUSTAQILLIK KO’CHASI 132-UY | H69: 3 | I69: 590942.28 | J69: 590942.28 | K69: oylik tolovi yopild | 155
A70: СУРХОНДАРЁ ВИЛОЯТИ | B70: SUPER BRANCH | C70: Оплатил дозвон | D70: Кр-99033003-2 | E70: MAMATMUROTOV SIROJIDDIN ABDIKADIROVICH | F70: 998990928761 SMS O’ZI, 998880431616 SMS UY, 998595373735 SMS OILASI, 998888490130 SMS UKASI, | G70: SURXANDARYO VILOYATI DENOV TUMANI BOG’ISHAMOL MFY O’RIKZOR KOCHASI 1-UY | H70: 2 | I70: 501843.97 | J70: 501843.97 | K70: krediti yopild | 459
A71: СУРХОНДАРЁ ВИЛОЯТИ | B71: Денов филиали | C71: Оплатил дозвон | D71: Кр-99041316-1 | E71: TURSUNOV SHOMUROD TOSHTEMIROVICH | F71: 998888064664 SMS ZALOGADATEL, 998888074664 SMS O’ZI, 998993433364 SMS UY, | G71: Сурхандарьинская область, Денауский район, Ш.Қобилов СИУ, Элобод МСГ, ул. Нурли саодат, дом 169 | H71: 3 | I71: 6216612.4 | J71: 6216612.4 | K71: oylik yopildi | 1142
A72: СУРХОНДАРЁ ВИЛОЯТИ | B72: Денов филиали | C72: Оплатил дозвон | D72: Кр-99042816-2 | E72: RAHIMOV HUMOYUN BEKMUROD O’G’LI | F72: 998942097777 SMS AKASI, 998975341111 SMS O’ZI, 998994161900 SMS SHERIGI, | G72: Тошкент шаҳри, Чилонзор, 17 мавзе, 33 Уй, 69 Квартира | H72: 3 | I72: 3934813.6 | J72: 3934813.6 | K72: oylik tolovi yopildi | 1267
A73: СУРХОНДАРЁ ВИЛОЯТИ | B73: Денов филиали | C73: Оплатил дозвон | D73: Кр-99012829-1 | E73: MIRZAYEV ERGASH ALMARDONOVICH | F73: 90-000-00-00 SMS, 998950987102 SMSO’G’LI, 998970846111 SMS O’ZI, 998978122070 SMS UY, | G73: SURXONDARYO VILOYATI DENOV TUMANI XATRABOD QFY XO’JAXALQ MFY ISTIQLOL KO’CHASI 45-UY | H73: 3 | I73: 1660921.6 | J73: 1660921.6 | K73: oylik tolovi yopildi | 67
A74: СУРХОНДАРЁ ВИЛОЯТИ | B74: Денов филиали | C74: Оплатил дозвон | D74: Кр-99027666-1 | E74: MELIBOYEVA SURAYYO NUMANJONOVNA | F74: 99-708-53-90 SMS O'ZI, 93-633-43-90 SMS UY, 99-426-43-90 SMS UY 2, | G74: SURXANDARYO VILOYATI UZUN TUMANI T.CHINOR MFY OBIZARANG KO’CHASI 404-UY | H74: 3 | I74: 482429.69 | J74: 482429.69 | K74: oylik tolovi yopild | 243
A75: ТОШКЕНТ ШАХРИ | B75: BOSH OFIS | C75: Оплатил дозвон | D75: Кр-99002592-8 | E75: AZIZXON SEVDA SHAVKATOVNA | F75: 90-331-22-27 SMS, 90-038-22-27 SMS MUROD AKA tolovchi , 71-217-36-07 SMS UY, 99-811-81-12 SMS MUROT AKA, | G75: TOSHKENT SHAHAR UCHTEPA TUMANI KVL G9a 11 UY 35 XONADON | H75: 36 | I75: 32075115 | J75: 32075115 | K75: 3 | 277000000 | 32075114.65 | tlgdan yozvordim
A76: ТОШКЕНТ ШАХРИ | B76: BOSH OFIS | C76: Оплатил дозвон | D76: Кр-99064392-1 | E76: SAMANDAROVA UMIDA SALIMOVNA | F76: 998777121240 SMS ERINIKI, 998902179222 SMS O’ZINIKI, 998903886222 SMS FARZANDINIKI, | G76: Богимайдон МФЙ, Мирзо Улугбек кучаси, 103-уй, 43-хонадон | H76: 3 | I76: 3088784 | J76: 3088784 | K76: qisman
A77: ТОШКЕНТ ШАХРИ | B77: BOSH OFIS | C77: Оплатил дозвон | D77: Кр-99035201-3 | E77: ABDUFATTOXOV ABDUG’AFFOR JAXONGIR O’G’LI | F77: 998974454581 SMS O’ZI, 998999037757 SMS AKASI, 998990204270 SMS DO’STI, 998901225256 SMS UKASI, 998977417070 SMS shuxrat amakisi, | G77: TOSHKENT SHAHAR SHAYXONTOXUR TUMANI XUVAYDI MFY ZAFAROBOD KO’CHASI 2-UY | H77: 3 | I77: 1141312.9 | J77: 1141312.9 | K77: yopildi
A78: ТОШКЕНТ ШАХРИ | B78: SUPER BRANCH | C78: Оплатил дозвон | D78: Кр-99063105-1 | E78: RAXIMOVA NILUFAR YULDASHEVNA | F78: 998977927577 OZI, 998995077757 OZI 2, 998985777757 OZI 3, 998770977577 OGLI, | G78: TOSHKENT SHAHAR SHAYXANTOXUR TUMANI SEBZOR KO’CHASI 7-UY,35-XONADON | H78: 64 | I78: 61205024 | J78: 61205024 | K78: yopildi
A79: ТОШКЕНТ ШАХРИ | B79: SUPER BRANCH | C79: Оплатил дозвон | D79: Кр-99037575-2 | E79: AZIMXODJAYEV BEXZOD DJAMALITDINOVICH | F79: 998998400008 SMS OZI, 998977071020 SMS DO’ST, 998977469176 SMS DOSTI 2, 998930906353 SMS OZI 2 begona, | G79: TOSHKENT SHAHAR OLMAZOR TUMANI, YANGI TOSHKENT MFY,KELES O’LI 15-UY | H79: 31 | I79: 18163834 | J79: 18163834 | K79: yopildi
... A94: ФАРГОНА ВИЛОЯТИ | B94: SUPER BRANCH | C94: Оплатил дозвон | D94: Кр-99062574-1 | E94: XUSANOVA ZIYODAXON IBRAGIMJANOVNA | F94: 998991015479 uzi, 998991165479 qizi, 998941386867 opasi, | G94: Манзил: FARG’ONA VILOYATI QUVASOY SHAHRI QO’CHQORCHI MFY OLTIN VODIY KO’CHASI 36-UY | H94: 3 | I94: 3087678 | J94: 3087678 | K94: 1829
A95: ФАРГОНА ВИЛОЯТИ | B95: SUPER BRANCH | C95: Оплатил дозвон | D95: Кр-99057272-1 | E95: QAYUMOV KOMILJON OBIDJONOVICH | F95: 998999870715 SMS UZI, 998997870414 SMS AYOLI, 998777918272 SMS O'G'LI, 998990198272 SMS UY, | G95: FARG’ONA VILOYATI QUVASOY SHAHAR ISFAYRAMSOY MFY MIRISHKOR KO’CHASI 8 A-XONADON | I95: 1876302.8 | J95: 1876302.8 | K95: 1607
A96: ФАРГОНА ВИЛОЯТИ | B96: SUPER BRANCH | C96: Оплатил дозвон | D96: Кр-99039833-1 | E96: USMANOV RAXIM MUXAMEDOVICH | F96: 998990409522 SMS OZI, 998900552185 SMS UKASI, 998132411102 SMS UKASI 2, 998910593282 SMS KELINI, | G96: FARG’ONA VILOYATI QO’QON SHAHAR YANGI CHORSU MFY NORBO’TABEK KO’CHASI 4-UY | H96: 3 | I96: 199392.81 | J96: 199392.81 | K96: ярим соатлада толов кберади | 896
A97: ФАРГОНА ВИЛОЯТИ | B97: Фарғона филиали | C97: Оплатил дозвон | D97: Кр-99044631-3 | E97: XAMIDOVA NAFISAXON XUSNIDDIN QIZI | F97: +998700283633 SMS O’ZI, 998774246212 ONASI, 998916516081 UKASI, 998992267314 ERI, | G97: FARG’ONA VILOYATI MARG’ILON SHAHAR CHILONZOR MFY TINCHILIK 181-UY 20-XONADON | H97: 3 | I97: 4512610.7 | J97: 4512610.7 | K97: 1313
A98: ФАРГОНА ВИЛОЯТИ | B98: Фарғона филиали | C98: Оплатил дозвон | D98: Кр-99041498-1 | E98: XAMZAYEVA MUKARRAMXON GANIXONOVNA | F98: +998914524444 SMS O’ZI 2 begana, 998903005488 SMS O’ZI, 998907794977 ERI, 998954747111 O’G’LI, | G98: ХУЖАРИК МФЙ, Ж.МАНГУБЕРДИ КЎЧАСИ, uy:, | H98: 3 | I98: 3953180.1 | J98: 3953180.1 | K98: 1175
A99: ФАРГОНА ВИЛОЯТИ | B99: Фарғона филиали | C99: Оплатил дозвон | D99: Кр-99048148-2 | E99: XAMIDOVA TAVAKALXON ISAYEVNA | F99: 998882102992 QIZI, 998887728808 O’G’LI 2, 998888112992 SMS O’ZI, 998997615500 O’G’LI, | G99: FARG’ONA VILOYATI FARG’ONA SHAHAR OQARIQ MFY OQARIQ KO’CHASI 311 A-UY | H99: 3 | I99: 3943330.9 | J99: 3943330.9 | K99: 1406
A100: ФАРГОНА ВИЛОЯТИ | B100: Фарғона филиали | C100: Оплатил дозвон | D100: Кр-99031813-4 | E100: QOBILOV NORMURODJON SIROJIDDIN O’G’LI | F100: 998900997097 SMS O’ZI, 998908483011 SMS ONASI, 998916706232 SMS AKASI, 998939792626 SMS AKASI 2, | G100: FARG’ONA VILOYATI FARG’ONA SHAHAR XUVAYDO MFY, XALQLAR DO’SLIGI 59-UY | H100: 3 | I100: 1131850.7 | J100: 1131850.7 | K100: 406
A101: ФАРГОНА ВИЛОЯТИ | B101: Фарғона филиали | C101: Оплатил дозвон | D101: Кр-99062967-1 | E101: YUNUSALIYEV QAXRAMONJON RASULOVICH | F101: +998903609057 SMS O’ZI, 998336772616 KIYOVI, 998777162689 QIZI, 998908551566 AYOLI, | G101: FARG’ONA VILOYATI BOG’DOD TUMANI MATQULOBOD MFY YUKSAK KO’CHASI 240-UY | I101: 156636.6 | J101: 156636.6 | K101: 1957
A102: ХОРАЗМ ВИЛОЯТИ | B102: SUPER BRANCH | C102: Оплатил дозвон | D102: Кр-99024098-2 | E102: AXMEDOV RUSLANBEK BAXODIROVICH | F102: 99-135-99-59 SMS UZI, 91-093-65-95 SMS UZI, 93-743-23-09 SMS QIZI, | G102: XORAZM VILOYATI URGANCH SHAHAR XALQ SO’ZI KUCHASI 21 UY | H102: 3 | I102: 2961411 | J102: 2961411 | K102: kotarmad | 175
A103: ХОРАЗМ ВИЛОЯТИ | B103: SUPER BRANCH | C103: Оплатил дозвон | D103: Кр-99046648-2 | E103: KURBANOV MANSUR RUSTAMOVICH | F103: +998959856565 SMS UZI, 998772525545 SMS AYOLI begona, 998937445100 SMS OTASI, | G103: ХОРАЗМ ВИЛОЯТИ УРГАНЧ Ш., БИНОКОР МФЙ, БИНОКОР КЎЧАСИ, uy:35 | H103: 3 | I103: 2144399.4 | J103: 2144399.4 | K103: yopildi | 1367
A104: ХОРАЗМ ВИЛОЯТИ | B104: SUPER BRANCH | C104: Оплатил дозвон | D104: Кр-99040248-2 | E104: KARIMOV OG’ABEK MURODOVICH | F104: 998975167776 SMS OZI, 998900770911 SMS ONASI, 998888587477 SMS AYOLI, 998885177776 SMS AYOLI2, | G104: XORAZM VILOYATI URGANCH TUMANI BAYNALMINALCHI MFY XUNARMAND 7-TOR KO’CHASI 1 A-UY | H104: 3 | I104: 1003504.2 | J104: 1003504.2 | K104: tolavotti | 979
A105: ХОРАЗМ ВИЛОЯТИ | B105: SUPER BRANCH | C105: Оплатил дозвон | D105: Кр-99048302-1 | E105: NURMATOV OG‘ABEK FAXRIDDIN O‘G‘LI | F105: +998919981626 Primary phone from road24, 998919981626 Primary phone from road24, 998905580815 SMS OTASI, 998910908909 SMS AKASI, | G105: Хорезмская область, Шаватский район, Каткалъа ССГ, Янги турмуш МСГ, ул. Бунёдкор, дом 33 | I105: 144126.75 | J105: 144126.75 | K105: hozi tolid | 1408
A106: ХОРАЗМ ВИЛОЯТИ | B106: Урганч филиали | C106: Оплатил дозвон | D106: Кр-99046032-1 | E106: NURMETOV OTABEK ISMAILOVICH | F106: +998955903632 SMS O’G’LI, 998993134005 SMS AYOLI, 998993837328 SMS UZI, | G106: Хорезмская область, Ургенчский район, Чондиркиёт ССГ, Киллавут МСГ, ул. Проектная, дом 73 | H106: 3 | I106: 3653019.8 | J106: 3653019.8 | K106: yopildi | 1344
A107: ХОРАЗМ ВИЛОЯТИ | B107: Урганч филиали | C107: Оплатил дозвон | D107: Кр-99046648-1 | E107: KURBANOV MANSUR RUSTAMOVICH | F107: +998959856565 SMS UZI, 998772525545 SMS AYOLI begona, 998937445100 SMS OTASI, | G107: ХОРАЗМ ВИЛОЯТИ УРГАНЧ Ш., БИНОКОР МФЙ, БИНОКОР КЎЧАСИ, uy:35 | H107: 3 | I107: 2136123 | J107: 2136123 | K107: yopildi | 1366
A108: ХОРАЗМ ВИЛОЯТИ | B108: Урганч филиали | C108: Оплатил дозвон | D108: Кр-99041377-1 | E108: JUMADURDIYEV BEKTEMIR XAJIYEVICH | F108: 998885461411 SMS UZI, 998975133428 SMS ONASI, 998975136424 SMS POCHCHASI, | G108: ҒАЛАБА ҚФЙ, ОБОД МФЙ, ОБОД КЎЧАСИ, uy:22 | H108: 3 | I108: 2046510.6 | J108: 2046510.6 | K108: oyligini kutvotti | 1156
A109: ХОРАЗМ ВИЛОЯТИ | B109: Урганч филиали | C109: Оплатил дозвон | D109: Кр-99042982-1 | E109: ISKANDAROV SHAVKAT O’KTAMOVICH | F109: +998995042130 SMS UZI, 998772507192 SMS AYOLI, | G109: ХОРАЗМ ВИЛОЯТИ БОГОТ ТУМАНИ НУРАФШОН ШФЙ, ТАНТАНА КЎЧАСИ, uy:28 | H109: 3 | I109: 1729157.5 | J109: 1729157.5 | K109: bugun kechga yopad,,,, 17,30 | 1276
A110: ХОРАЗМ ВИЛОЯТИ | B110: Урганч филиали | C110: Оплатил дозвон | D110: Кр-99027635-1 | E110: ATANAZAROV ELBEK TO’LQIN O’G’LI | F110: 95-910-57-07 SMS OZI, 99-048-80-30 SMS ONASI, 99-909-43-73 SMS DADASI, | G110: XORAZM VILOYATI YANGIBOZOR TUMANI JAYXUN MAXALLASI TURON KUCHASI 8 UY | I110: 205770.9 | J110: 205770.9 | K110: yopildi | 239

Sheet Оплатили без разговора
A1: ← Вернуться в отчёт
A2: Область | B2: Филиал | C2: Группа | D2: Код клиента | E2: Клиент | F2: Номер телефона | G2: Адрес | H2: Кол-во просроченных дней | I2: Итого просрочка | J2: Оплата | K2: Izoh
A3: ТОШКЕНТ ШАХРИ | B3: SUPER BRANCH | C3: Ko'tarmadi | D3: Кр-99037130-1 | E3: ABDURAIMOVA DILNAVO ABDUALIMOVNA | F3: 998977146828 SMS OZI, 998996899248 SMS QARINDOSHI, 998884452393 SMS OVSINI, 998917821504 SMS O’ZI 2, | G3: KO’RMANA MFY 10-MAVZE 21-UY,10-XONADON | H3: 3 | I3: 4608834.4 | J3: 4608834.4 | K3: 676 | 73000000 | 2233728.8
